Workbook

Sheet Léeme
A1: Modelo financiero: distribuidora de medicamentos para compras públicas en Panamá
A2: Preparado el 6 de octubre de 2026 como apoyo del plan de negocio. Cifras en balboas (B/. = US$).
A4: Cómo usarlo
A5: 1. Elija el escenario en Supuestos!B3 (1 = pesimista, 2 = base, 3 = optimista). Todo el modelo se recalcula.
A6: 2. Cambie cualquier valor azul de las columnas D, E o F de Supuestos, o la columna "Incluir" de SKUs, para probar otra hipótesis.
A7: 3. Supuestos!B4 = 1 aplica las tarifas de la propuesta de SignatureLex en lugar de las de mercado.
A8: 4. Resultados vivos: Valoración (VPN, TIR, múltiplo, capital requerido), Anual (estado de resultados e impuestos), Mensual (flujo de caja).
A9: 5. Las hojas Escenarios, Monte Carlo y Sensibilidad son resultados fijos del motor en Python (20,000 simulaciones); no cambian al editar supuestos.
A11: Convenciones
A12: Texto azul = dato de entrada o supuesto editable. Negro = fórmula. Verde = vínculo a otra hoja. Relleno amarillo = supuestos clave.
A13: F = dato verificado en fuente abierta (URL en Fuentes o en la columna Fuente). E = estimación del analista, a validar.
A15: Lógica del modelo (mes a mes, 60 meses desde la constitución de la S.A.)
... A30: Las variantes «Reestructurado» de la hoja Escenarios y la de Bueno financiando suponen un coordinador con sueldo de B/.1,000 al mes (más cargas); el caso base usa B/.1,500 y la simulación sortea entre 800 y 2,500.

Sheet Supuestos
A1: Supuestos
A3: Escenario | B3: 2 | C3: =CHOOSE($B$3,"Pesimista","Base","Optimista") -> Base
A4: SignatureLex | B4: 0 | C4: Usar tarifas de la propuesta de SignatureLex (1) o de mercado (0)
A6: Clave | B6: Parámetro | C6: Unidad | D6: Pesimista | E6: Base | F6: Optimista | G6: Usado | H6: Fuente o base
A7: reg_m | B7: Mes en que salen los registros sanitarios (desde la constitución) | C7: mes | D7: 9 | E7: 6 | F7: 5 | G7: =CHOOSE(p_sc,D7,E7,F7) -> 6 | H7: Base = plazo de 5-6 meses planteado por el socio panameño; pesimista = supuesto de riesgo
A8: lead_days | B8: Tiempo de reposición: orden al proveedor hasta stock en Panamá | C8: días | D8: 120 | E8: 90 | F8: 75 | G8: =CHOOSE(p_sc,D8,E8,F8) -> 90 | H8: E: producción + flete marítimo + aduana; confirmar con Zywie y el agente de carga
A9: ship_m | B9: Meses entre embarque (B/L) y stock disponible | C9: meses | D9: 2 | E9: 2 | F9: 2 | G9: =CHOOSE(p_sc,D9,E9,F9) -> 2 | H9: E: tránsito marítimo con transbordo + desaduanaje
A10: ramp_m | B10: Meses para llegar a la participación madura en compras descentralizadas | C10: meses | D10: 18 | E10: 12 | F10: 9 | G10: =CHOOSE(p_sc,D10,E10,F10) -> 12 | H10: E: curva de aprendizaje; descalificación de nuevos 56% vs 34% (OCDS MINSA 2022-23)
A11: cen_start | B11: Mes del primer contrato centralizado (LPU CSS / subasta MINSA) | C11: mes | D11: 27 | E11: 15 | F11: 12 | G11: =CHOOSE(p_sc,D11,E11,F11) -> 15 | H11: E: la LPU 01-2026 vence a mediados de 2027; la siguiente se licitaría alrededor de esa fecha
A12: mkt | B12: Factor de mercado (demanda futura vs datos 2025-26) | C12: x | D12: 0.75 | E12: 0.9 | F12: 1 | G12: =CHOOSE(p_sc,D12,E12,F12) -> 0.9 | H12: F: presupuesto CSS 2027 de medicamentos -28.6% (Prensa, 4-sep-2026); E: ajuste
A13: share_dec | B13: Participación madura en compras descentralizadas (valor) | C13: % | D13: 0.1 | E13: 0.22 | F13: 0.32 | G13: =CHOOSE(p_sc,D13,E13,F13) -> 0.22 | H13: E: P(ganar|ofertar) entrantes 17%, establecidos 26% (OCDS MINSA 2020-24)
A14: pwin_cen | B14: Probabilidad de ganar un renglón centralizado ofertado | C14: % | D14: 0.15 | E14: 0.3 | F14: 0.45 | G14: =CHOOSE(p_sc,D14,E14,F14) -> 0.3 | H14: E: P(ganar|precio más bajo y calificado) 95%; entrantes descalificados 56%
A15: realiz | B15: Cantidad realmente comprada vs máxima del contrato | C15: % | D15: 0.55 | E15: 0.75 | F15: 0.9 | G15: =CHOOSE(p_sc,D15,E15,F15) -> 0.75 | H15: F: compromiso mínimo CSS 50% con excepciones amplias (Adenda 1 LPU 01-2026)
A16: minsa_occ | B16: Probabilidad de que MINSA haga su compra centralizada en el año | C16: % | D16: 0.3 | E16: 0.5 | F16: 0.7 | G16: =CHOOSE(p_sc,D16,E16,F16) -> 0.5 | H16: F: compra conjunta 2025 fracasó; DE 16 de 2026 sin acto publicado a oct-2026
A17: pf_dec | B17: Precio de oferta descentralizado vs mediana actual | C17: x | D17: 0.8 | E17: 0.9 | F17: 0.95 | G17: =CHOOSE(p_sc,D17,E17,F17) -> 0.9 | H17: F: precio ganador / mediana de ofertas = 0.91 (B1)
A18: pf_cen | B18: Precio de oferta centralizado vs adjudicado actual | C18: x | D18: 0.9 | E18: 0.95 | F18: 1 | G18: =CHOOSE(p_sc,D18,E18,F18) -> 0.95 | H18: F: adjudicado / referencia 0.963 en LPU 01-2026; E: descuento para desplazar
... A41: rs_off | B41: Tasas oficiales por registro (DNFD 500 + MEF + Colegio) | C41: B/. | D41: 570 | E41: 570 | F41: 570 | G41: =CHOOSE(p_sc,D41,E41,F41) -> 570 | H41: F: DE 27 art. 15; MEF y Colegio guía MINSA 2012
A42: rs_iea | B42: Análisis de control previo IEA por producto | C42: B/. | D42: 1500 | E42: 600 | F42: 300 | G42: =IF(p_sl=1,1500,CHOOSE(p_sc,D42,E42,F42)) -> 600 | H42: F: rango oficial 200-1,000 (2012); E: cotizar con el IEA
A43: rs_law | B43: Honorario y gastos del abogado por registro | C43: B/. | D43: 1350 | E43: 800 | F43: 500 | G43: =IF(p_sl=1,1350,CHOOSE(p_sc,D43,E43,F43)) -> 800 | H43: F: SignatureLex 600 + 750; arancel mínimo 500
A44: rs_smp | B44: Muestras y courier por registro | C44: B/. | D44: 300 | E44: 150 | F44: 100 | G44: =CHOOSE(p_sc,D44,E44,F44) -> 150 | H44: E
A45: rs_succ | B45: Registros aprobados / registros presentados | C45: % | D45: 0.7 | E45: 0.85 | F45: 0.95 | G45: =CHOOSE(p_sc,D45,E45,F45) -> 0.85 | H45: E: expedientes débiles, observaciones de la DNFD
A46: postreg | B46: Análisis posregistro por producto (2 en 5 años), por año | C46: B/. | D46: 600 | E46: 240 | F46: 120 | G46: =CHOOSE(p_sc,D46,E46,F46) -> 240 | H46: F: Ley 419 art. 67; E: costo
A47: n2 | B47: Productos de la segunda ola (sin equivalencia terapéutica, fabricante verificado) | C47: SKU | D47: 0 | E47: 6 | F47: 12 | G47: =CHOOSE(p_sc,D47,E47,F47) -> 6 | H47: E: candidatos del catálogo con compras públicas: ibuprofeno 400, ambroxol jarabe, gliclazida 80, amoxicilina susp., loratadina, diclofenaco, eritromicina, cefepima
A48: m2 | B48: Mes en que se presentan los registros de la segunda ola | C48: mes | D48: 24 | E48: 18 | F48: 15 | G48: =CHOOSE(p_sc,D48,E48,F48) -> 18 | H48: Decisión: solo si la primera ola cumple la compuerta
A49: rel2 | B49: Ingreso por producto de la segunda ola vs promedio de la primera | C49: x | D49: 0.5 | E49: 0.7 | F49: 1 | G49: =CHOOSE(p_sc,D49,E49,F49) -> 0.7 | H49: E: los mejores productos van en la primera ola
A50: fact_share | B50: Porcentaje de las ventas que se factoriza | C50: % | D50: 0 | E50: 0 | F50: 0 | G50: =CHOOSE(p_sc,D50,E50,F50) -> 0 | H50: Opción de financiamiento; Ley 22 art. 97 permite ceder créditos
A51: fact_cost | B51: Costo mensual del factoring sobre el monto cedido | C51: % | D51: 0.015 | E51: 0.0125 | F51: 0.01 | G51: =CHOOSE(p_sc,D51,E51,F51) -> 0.0125 | H51: F: Balboa Factoring 2025: 14.6%-18.3% anual
A52: stop_det | B52: Mes de cierre del negocio (61 = no se cierra) | C52: mes | D52: 61 | E52: 61 | F52: 61 | G52: =CHOOSE(p_sc,D52,E52,F52) -> 61 | H52: Compuerta operativa: cerrar si nueve meses después de la primera venta las ventas anualizadas no cubren el umbral
A53: inv_liq | B53: Recuperación del inventario si se cierra | C53: % | D53: 0.5 | E53: 0.5 | F53: 0.5 | G53: =CHOOSE(p_sc,D53,E53,F53) -> 0.5 | H53: E: venta a otros distribuidores o devolución parcial
A54: isr | B54: Impuesto sobre la renta | C54: % | D54: 0.25 | E54: 0.25 | F54: 0.25 | G54: =CHOOSE(p_sc,D54,E54,F54) -> 0.25 | H54: F: Código Fiscal art. 699
A55: divtax | B55: Impuesto de dividendos | C55: % | D55: 0.1 | E55: 0.1 | F55: 0.1 | G55: =CHOOSE(p_sc,D55,E55,F55) -> 0.1 | H55: F: Código Fiscal art. 733
... A66: zy_markup | B66: Margen de Zywie sobre el precio de fábrica (dentro del índice del proveedor) | C66: % | D66: 0.25 | E66: 0.15 | F66: 0.05 | G66: =CHOOSE(p_sc,D66,E66,F66) -> 0.15 | H66: E: comercializadora intermediaria
A68: Costos fijos mensuales (B/./mes)
A69: # | B69: Concepto | C69: Inicio | D69: Pesimista | E69: Base | F69: Optimista | G69: Usado (con cargas o ITBMS) | H69: Fuente o base | I69: Mes inicio | J69: Tipo
A70: 1 | B70: Regente farmacéutico (medio tiempo, mínimo 4 h/día) | C70: licencia | D70: 1200 | E70: 700 | F70: 450 | G70: =CHOOSE(p_sc,D70,E70,F70)*(1+p_oncost) -> 896 | H70: F: DE 27 art. 382; SignatureLex 400-500; Paylab 1,339-3,228 tiempo completo | I70: =c_lic_m -> 3 | J70: sueldo + cargas laborales
A71: 2 | B71: 3PL farmacéutico licenciado: cuota mínima | C71: licencia | D71: 1200 | E71: 600 | F71: 300 | G71: =CHOOSE(p_sc,D71,E71,F71)*(1+p_itbms_srv) -> 642 | H71: B7: mínimo 300-1,200; sin cotización firme | I71: =c_lic_m -> 3 | J71: servicio + ITBMS
A72: 3 | B72: Contabilidad e impuestos | C72: mes 1 | D72: 450 | E72: 300 | F72: 200 | G72: =CHOOSE(p_sc,D72,E72,F72)*(1+p_itbms_srv) -> 321 | H72: E | I72: =1 -> 1 | J72: servicio + ITBMS
A73: 4 | B73: Auditoría anual (requisito de fianzas y Registro de Oferentes), prorrateada | C73: mes 1 | D73: 400 | E73: 250 | F73: 150 | G73: =CHOOSE(p_sc,D73,E73,F73)*(1+p_itbms_srv) -> 267.5 | H73: F: DE 27 art. 725 exige estados certificados por CPA; E: costo | I73: =1 -> 1 | J73: servicio + ITBMS
A74: 5 | B74: Asesoría legal por hora (sin iguala mensual) | C74: mes 1 | D74: 800 | E74: 300 | F74: 150 | G74: =CHOOSE(p_sc,D74,E74,F74)*(1+p_itbms_srv) -> 321 | H74: E; SignatureLex propone iguala de 2,000 | I74: =1 -> 1 | J74: servicio + ITBMS
A75: 6 | B75: Coordinador de licitaciones y operaciones (medio tiempo) | C75: registros - 1 | D75: 2500 | E75: 1500 | F75: 800 | G75: =CHOOSE(p_sc,D75,E75,F75)*(1+p_oncost) -> 1920 | H75: E: alguien debe vigilar PanamaCompra a diario y armar ofertas | I75: =MAX(c_reg_m-1,1) -> 5 | J75: sueldo + cargas laborales
A76: 7 | B76: Seguros (responsabilidad civil y de producto) | C76: licencia | D76: 200 | E76: 100 | F76: 75 | G76: =CHOOSE(p_sc,D76,E76,F76) -> 100 | H76: E | I76: =c_lic_m -> 3 | J76: otro
A77: 8 | B77: Software, banca, telecomunicaciones y administración | C77: mes 1 | D77: 200 | E77: 120 | F77: 80 | G77: =CHOOSE(p_sc,D77,E77,F77)*(1+p_itbms_srv) -> 128.4 | H77: E | I77: =1 -> 1 | J77: servicio + ITBMS
A78: 9 | B78: Impuesto municipal | C78: mes 1 | D78: 200 | E78: 100 | F78: 100 | G78: =CHOOSE(p_sc,D78,E78,F78) -> 100 | H78: F: tope PwC; E: tramo | I78: =1 -> 1 | J78: otro
B79: Total costos fijos a plena operación | G79: =SUM(G70:G78) -> 4695.9
A81: Gastos de arranque, una sola vez (B/.)
A82: # | B82: Concepto | C82: Mes | D82: Pesimista | E82: Base | F82: Optimista | G82: Usado (con ITBMS) | H82: Fuente o base | I82: SignatureLex | J82: Tipo
A83: 1 | B83: Due diligence de fabricante y documentos (fase 0, antes de constituir) | C83: 0 | D83: 6000 | E83: 2500 | F83: 1000 | G83: =IF(AND(p_sl=1,I83>0),I83,CHOOSE(p_sc,D83,E83,F83))*(1+p_itbms_srv) -> 2675 | H83: E: auditoría virtual de planta y verificación documental | I83: 0 | J83: servicio + ITBMS
A84: 2 | B84: Constitución, libros, poderes, RUC, aviso de operación y municipal | C84: 1 | D84: 3500 | E84: 2500 | F84: 1500 | G84: =IF(AND(p_sl=1,I84>0),I84,CHOOSE(p_sc,D84,E84,F84))*(1+p_itbms_srv) -> 2675 | H84: F: SignatureLex ~5,700; Díaz & Asociados 1,500 (S.A. operativa) | I84: 5700 | J84: servicio + ITBMS
A85: 3 | B85: Pacto de accionistas, contrato de suministro exclusivo y acuerdo de calidad | C85: 1 | D85: 4000 | E85: 2500 | F85: 1500 | G85: =IF(AND(p_sl=1,I85>0),I85,CHOOSE(p_sc,D85,E85,F85))*(1+p_itbms_srv) -> 2675 | H85: F: SignatureLex 1,500 + 1% escalonado; E | I85: 1750 | J85: servicio + ITBMS
A86: 4 | B86: Diagnóstico regulatorio inicial y matriz de portafolio | C86: 1 | D86: 650 | E86: 650 | F86: 500 | G86: =IF(AND(p_sl=1,I86>0),I86,CHOOSE(p_sc,D86,E86,F86))*(1+p_itbms_srv) -> 695.5 | H86: F: SignatureLex 500 + 150 | I86: 650 | J86: servicio + ITBMS
A87: 5 | B87: Apoyo para abrir cuenta bancaria | C87: 1 | D87: 3150 | E87: 300 | F87: 0 | G87: =IF(AND(p_sl=1,I87>0),I87,CHOOSE(p_sc,D87,E87,F87))*(1+p_itbms_srv) -> 321 | H87: F: SignatureLex 3,000 + 150 | I87: 3150 | J87: servicio + ITBMS
A88: 6 | B88: Licencia de operación: tasa oficial 250 + planos, SOP e inspección | C88: 2 | D88: 4000 | E88: 1750 | F88: 1000 | G88: =IF(AND(p_sl=1,I88>0),I88,CHOOSE(p_sc,D88,E88,F88))*(1+p_itbms_srv) -> 1872.5 | H88: F: DE 27 art. 15 (200 + 50); SignatureLex 3,500 + 500 | I88: 4000 | J88: servicio + ITBMS
A89: 7 | B89: Revisión del 3PL y acuerdo de calidad | C89: 2 | D89: 2650 | E89: 750 | F89: 400 | G89: =IF(AND(p_sl=1,I89>0),I89,CHOOSE(p_sc,D89,E89,F89))*(1+p_itbms_srv) -> 802.5 | H89: F: SignatureLex 2,500 + 150 | I89: 2650 | J89: servicio + ITBMS
A90: 8 | B90: Programa de cumplimiento y anticorrupción | C90: 2 | D90: 3150 | E90: 1500 | F90: 800 | G90: =IF(AND(p_sl=1,I90>0),I90,CHOOSE(p_sc,D90,E90,F90))*(1+p_itbms_srv) -> 1605 | H90: F: SignatureLex 3,000 + 150 | I90: 3150 | J90: servicio + ITBMS
A91: 9 | B91: Certificado de BPA | C91: 3 | D91: 100 | E91: 100 | F91: 100 | G91: =IF(AND(p_sl=1,I91>0),I91,CHOOSE(p_sc,D91,E91,F91)) -> 100 | H91: F: DE 27 art. 15 | I91: 100 | J91: otro
A92: 10 | B92: Registro patronal CSS y contratos laborales | C92: 3 | D92: 900 | E92: 300 | F92: 100 | G92: =IF(AND(p_sl=1,I92>0),I92,CHOOSE(p_sc,D92,E92,F92))*(1+p_itbms_srv) -> 321 | H92: F: SignatureLex 750 + 150 | I92: 900 | J92: servicio + ITBMS
A93: 11 | B93: PanamaCompra, Registro Nacional de Oferentes y proveedor CSS | C93: 4 | D93: 2700 | E93: 500 | F93: 0 | G93: =IF(AND(p_sl=1,I93>0),I93,CHOOSE(p_sc,D93,E93,F93))*(1+p_itbms_srv) -> 535 | H93: F: SignatureLex 3 x (750 + 150); trámites sin tasa oficial | I93: 2700 | J93: servicio + ITBMS
B94: Total arranque (incluye fase 0) | G94: =SUM(G83:G93) -> 14277.5
A96: Cargos anuales (meses 1, 13, 25, 37 y 49; el aviso de operación se calcula aparte sobre el patrimonio)
B97: Tasa única S.A. | E97: 300 | G97: =E97 -> 300 | H97: F: DGI | J97: otro
B98: Agente residente | E98: 250 | G98: =E98*(1+p_itbms_srv) -> 267.5 | H98: F: mercado 250-350 | J98: servicio + ITBMS
B99: Total cargos anuales | G99: =SUM(G97:G98) -> 567.5
A101: Valores calculados (no editar)
A102: c_lic_m | B102: Mes de la licencia de operación | G102: =3 -> 3
A103: c_rs_pay_m | B103: Mes en que se pagan los registros de la primera ola | G103: =3 -> 3
A104: c_lead_m | B104: Tiempo de reposición (meses) | G104: =ROUND(p_lead_days/30,0) -> 3
A105: c_dso_m | B105: Días de cobro (meses) | G105: =ROUND(p_dso_days/30,0) -> 5
A106: c_credit_m | B106: Crédito del proveedor (meses) | G106: =ROUND(p_credit_days/30,0) -> 0
A107: c_ship_m | B107: Embarque a stock (meses) | G107: =ROUND(p_ship_m,0) -> 2
A108: c_reg_m | B108: Mes de registros (entero) | G108: =ROUND(p_reg_m,0) -> 6
A109: c_first_dec | B109: Primer mes con ventas descentralizadas | G109: =c_reg_m+c_lead_m -> 9
A110: c_cen_start | B110: Primer mes con contrato centralizado | G110: =MAX(ROUND(p_cen_start,0),c_first_dec) -> 15
A111: c_rt | B111: Meses de trámite del registro | G111: =MAX(c_reg_m-c_rs_pay_m,1) -> 3
A112: c_m2 | B112: Mes de registros de la segunda ola | G112: =ROUND(p_m2,0) -> 18
A113: c_first_dec2 | B113: Primer mes con ventas de la segunda ola | G113: =c_m2+c_rt+c_lead_m -> 24
A114: c_n1 | B114: Productos presentados en la primera ola | G114: =MAX(SUM(SKUs!$D$6:$D$24),1) -> 11
A115: c_k2 | B115: Factor de escala de la segunda ola | G115: =p_n2*p_rel2/c_n1 -> 0.38181818
A116: c_rs_unit | B116: Costo total por registro (B/.; ITBMS sobre el abogado) | G116: =p_rs_off+p_rs_iea+p_rs_law*(1+p_itbms_srv)+p_rs_smp -> 2176
A117: c_bid_m | B117: Meses de colateral de la fianza de propuesta (entero) | G117: =ROUND(p_bid_m,0) -> 3
A118: c_n_reg1 | B118: Registros aprobados esperados, primera ola | G118: =SUM(SKUs!$D$6:$D$24)*p_rs_succ -> 9.35
A119: c_n_reg2 | B119: Registros aprobados esperados, segunda ola | G119: =p_n2*p_rs_succ -> 5.1

Sheet SKUs
A1: Portafolio y economía por producto
A2: Demanda pública anualizada 2025-26 (r2e); precios medianos o adjudicados; costos puestos con referencias de India (B2). Ventas a madurez antes de rampa y erosión.
A3: Canales: LPU = licitación de precio único CSS; MINSA central = subasta en reversa o compra conjunta; desc. = contratación menor y compra menor ágil.
A5: ID | B5: Producto | C5: Grupo | D5: Incluir (1/0) | E5: FOB base (B/./u) | F5: Logística (B/./u) | G5: Fuente del costo | H5: CSS LPU: unid./año | I5: CSS LPU: precio | J5: MINSA central: unid./año | K5: MINSA central: precio | L5: CSS desc.: unid./año | M5: CSS desc.: precio | N5: MINSA/patronatos desc.: unid./año | O5: MINSA/patronatos desc.: precio | P5: Costo puesto en Panamá | Q5: Precio oferta LPU | R5: Precio oferta MINSA central | S5: Precio oferta CSS desc. | T5: Precio oferta MINSA desc. | U5: Margen LPU | V5: Margen MINSA central | W5: Margen CSS desc. | X5: Margen MINSA desc. | Y5: Oferta LPU | Z5: Oferta MINSA central | AA5: Oferta CSS desc. | AB5: Oferta MINSA desc. | AC5: Ventas CSS desc. (madurez) | AD5: Ventas MINSA desc. (madurez) | AE5: Ventas LPU si gana | AF5: Ventas MINSA central si gana | AG5: Costo CSS desc. | AH5: Costo MINSA desc. | AI5: Costo LPU | AJ5: Costo MINSA central | AK5: Ventas esperadas año maduro | AL5: Utilidad bruta esperada | AM5: Costo FOB (para Zywie) | AN5: Oferta LPU con fianza de propuesta (B/./año)
A6: PCT500 | B6: Paracetamol 500 mg tableta | C6: Bueno | D6: 1 | E6: 0.004 | F6: 0.00237 | G6: B2 landed.csv: FOB = TNMSC L1 x1.4; adder LCL 200 USD/CBM | H6: 23770516 | I6: 0.01 | J6: 0 | K6: 0 | L6: 5810286 | M6: 0.02 | N6: 11102514 | O6: 0.02 | P6: =E6*p_sup_idx*(1+p_pack)+F6*p_log_mult -> 0.00762 | Q6: =I6*p_pf_cen -> 0.0095 | R6: =K6*p_pf_cen -> 0 | S6: =M6*p_pf_dec -> 0.018 | T6: =O6*p_pf_dec -> 0.018 | U6: =IF(Q6>0,1-P6/Q6,-9) -> 0.19789474 | V6: =IF(R6>0,1-P6/R6,-9) -> -9 | W6: =IF(S6>0,1-P6/S6,-9) -> 0.57666667 | X6: =IF(T6>0,1-P6/T6,-9) -> 0.57666667 | Y6: =IF(AND($D6=1,H6>0,U6>=p_gm_cen),1,0) -> 0 | Z6: =IF(AND($D6=1,J6>0,V6>=p_gm_cen),1,0) -> 0 | AA6: =IF(AND($D6=1,L6>0,W6>=p_gm_dec),1,0) -> 1 | AB6: =IF(AND($D6=1,N6>0,X6>=p_gm_dec),1,0) -> 1 | AC6: =AA6*L6*p_mkt*S6*p_rs_succ*p_share_dec -> 17601.68 | AD6: =AB6*N6*p_mkt*T6*p_rs_succ*p_share_dec -> 33633.956 | AE6: =Y6*H6*p_mkt*Q6*p_rs_succ*p_realiz -> 0 | AF6: =Z6*J6*p_mkt*R6*p_rs_succ*p_realiz -> 0 | AG6: =IF(S6>0,AC6*P6/S6,0) -> 7451.378 | AH6: =IF(T6>0,AD6*P6/T6,0) -> 14238.375 | AI6: =IF(Q6>0,AE6*P6/Q6,0) -> 0 | AJ6: =IF(R6>0,AF6*P6/R6,0) -> 0 | AK6: =AC6+AD6+AE6*p_pwin_cen+AF6*p_pwin_cen*p_minsa_occ -> 51235.636 | AL6: =(AC6-AG6)+(AD6-AH6)+(AE6-AI6)*p_pwin_cen+(AF6-AJ6)*p_pwin_cen*p_minsa_occ -> 29545.884 | AM6: =IF(P6>0,E6*p_sup_idx*(1+p_pack)/P6,0) -> 0.68897638 | AN6: =IF(AND(Y6=1,H6*I6*15/12>70000),H6*p_mkt*Q6*p_rs_succ,0) -> 0
A7: PCTSYR | B7: Paracetamol 120-160 mg/5 ml jarabe (frasco 120 ml) | C7: Bueno | D7: 1 | E7: 0.17 | F7: 0.1629 | G7: B2: TNMSC 60 ml x1.7 escalado a 120 ml; adder por volumen | H7: 315718 | I7: 0.59 | J7: 524358 | K7: 0.4 | L7: 0 | M7: 0 | N7: 61873 | O7: 0.95 | P7: =E7*p_sup_idx*(1+p_pack)+F7*p_log_mult -> 0.386025 | Q7: =I7*p_pf_cen -> 0.5605 | R7: =K7*p_pf_cen -> 0.38 | S7: =M7*p_pf_dec -> 0 | T7: =O7*p_pf_dec -> 0.855 | U7: =IF(Q7>0,1-P7/Q7,-9) -> 0.31128457 | V7: =IF(R7>0,1-P7/R7,-9) -> -0.015855263 | W7: =IF(S7>0,1-P7/S7,-9) -> -9 | X7: =IF(T7>0,1-P7/T7,-9) -> 0.54850877 | Y7: =IF(AND($D7=1,H7>0,U7>=p_gm_cen),1,0) -> 1 | Z7: =IF(AND($D7=1,J7>0,V7>=p_gm_cen),1,0) -> 0 | AA7: =IF(AND($D7=1,L7>0,W7>=p_gm_dec),1,0) -> 0 | AB7: =IF(AND($D7=1,N7>0,X7>=p_gm_dec),1,0) -> 1 | AC7: =AA7*L7*p_mkt*S7*p_rs_succ*p_share_dec -> 0 | AD7: =AB7*N7*p_mkt*T7*p_rs_succ*p_share_dec -> 8903.3081 | AE7: =Y7*H7*p_mkt*Q7*p_rs_succ*p_realiz -> 101530.77 | AF7: =Z7*J7*p_mkt*R7*p_rs_succ*p_realiz -> 0 | AG7: =IF(S7>0,AC7*P7/S7,0) -> 0 | AH7: =IF(T7>0,AD7*P7/T7,0) -> 4019.7655 | AI7: =IF(Q7>0,AE7*P7/Q7,0) -> 69925.805 | AJ7: =IF(R7>0,AF7*P7/R7,0) -> 0 | AK7: =AC7+AD7+AE7*p_pwin_cen+AF7*p_pwin_cen*p_minsa_occ -> 39362.538 | AL7: =(AC7-AG7)+(AD7-AH7)+(AE7-AI7)*p_pwin_cen+(AF7-AJ7)*p_pwin_cen*p_minsa_occ -> 14365.031 | AM7: =IF(P7>0,E7*p_sup_idx*(1+p_pack)/P7,0) -> 0.57800661 | AN7: =IF(AND(Y7=1,H7*I7*15/12>70000),H7*p_mkt*Q7*p_rs_succ,0) -> 135374.35
A8: AMCTAB | B8: Amoxicilina + clavulánico 500/125 mg tableta | C8: Bueno | D8: 1 | E8: 0.086 | F8: 0.00265 | G8: B2: TNMSC empanelment L1 x1.4 | H8: 46534 | I8: 0.179 | J8: 191135 | K8: 0.19 | L8: 0 | M8: 0 | N8: 30555 | O8: 0.29 | P8: =E8*p_sup_idx*(1+p_pack)+F8*p_log_mult -> 0.115525 | Q8: =I8*p_pf_cen -> 0.17005 | R8: =K8*p_pf_cen -> 0.1805 | S8: =M8*p_pf_dec -> 0 | T8: =O8*p_pf_dec -> 0.261 | U8: =IF(Q8>0,1-P8/Q8,-9) -> 0.32064099 | V8: =IF(R8>0,1-P8/R8,-9) -> 0.3599723 | W8: =IF(S8>0,1-P8/S8,-9) -> -9 | X8: =IF(T8>0,1-P8/T8,-9) -> 0.55737548 | Y8: =IF(AND($D8=1,H8>0,U8>=p_gm_cen),1,0) -> 1 | Z8: =IF(AND($D8=1,J8>0,V8>=p_gm_cen),1,0) -> 1 | AA8: =IF(AND($D8=1,L8>0,W8>=p_gm_dec),1,0) -> 0 | AB8: =IF(AND($D8=1,N8>0,X8>=p_gm_dec),1,0) -> 1 | AC8: =AA8*L8*p_mkt*S8*p_rs_succ*p_share_dec -> 0 | AD8: =AB8*N8*p_mkt*T8*p_rs_succ*p_share_dec -> 1342.1681 | AE8: =Y8*H8*p_mkt*Q8*p_rs_succ*p_realiz -> 4540.145 | AF8: =Z8*J8*p_mkt*R8*p_rs_succ*p_realiz -> 19794.299 | AG8: =IF(S8>0,AC8*P8/S8,0) -> 0 | AH8: =IF(T8>0,AD8*P8/T8,0) -> 594.07651 | AI8: =IF(Q8>0,AE8*P8/Q8,0) -> 3084.3884 | AJ8: =IF(R8>0,AF8*P8/R8,0) -> 12668.9 | AK8: =AC8+AD8+AE8*p_pwin_cen+AF8*p_pwin_cen*p_minsa_occ -> 5673.3564 | AL8: =(AC8-AG8)+(AD8-AH8)+(AE8-AI8)*p_pwin_cen+(AF8-AJ8)*p_pwin_cen*p_minsa_occ -> 2253.6285 | AM8: =IF(P8>0,E8*p_sup_idx*(1+p_pack)/P8,0) -> 0.97706124 | AN8: =IF(AND(Y8=1,H8*I8*15/12>70000),H8*p_mkt*Q8*p_rs_succ,0) -> 0
A9: AMCSUS | B9: Amoxicilina + clavulánico 400/57 mg/5 ml suspensión (100 ml) | C9: Bueno | D9: 1 | E9: 1.1 | F9: 0.1955 | G9: B2: derivado de Jan Aushadhi MRP; baja confianza | H9: 10217 | I9: 1.98 | J9: 0 | K9: 0 | L9: 0 | M9: 0 | N9: 6891 | O9: 4.18 | P9: =E9*p_sup_idx*(1+p_pack)+F9*p_log_mult -> 1.63925 | Q9: =I9*p_pf_cen -> 1.881 | R9: =K9*p_pf_cen -> 0 | S9: =M9*p_pf_dec -> 0 | T9: =O9*p_pf_dec -> 3.762 | U9: =IF(Q9>0,1-P9/Q9,-9) -> 0.12852206 | V9: =IF(R9>0,1-P9/R9,-9) -> -9 | W9: =IF(S9>0,1-P9/S9,-9) -> -9 | X9: =IF(T9>0,1-P9/T9,-9) -> 0.56426103 | Y9: =IF(AND($D9=1,H9>0,U9>=p_gm_cen),1,0) -> 0 | Z9: =IF(AND($D9=1,J9>0,V9>=p_gm_cen),1,0) -> 0 | AA9: =IF(AND($D9=1,L9>0,W9>=p_gm_dec),1,0) -> 0 | AB9: =IF(AND($D9=1,N9>0,X9>=p_gm_dec),1,0) -> 1 | AC9: =AA9*L9*p_mkt*S9*p_rs_succ*p_share_dec -> 0 | AD9: =AB9*N9*p_mkt*T9*p_rs_succ*p_share_dec -> 4362.9994 | AE9: =Y9*H9*p_mkt*Q9*p_rs_succ*p_realiz -> 0 | AF9: =Z9*J9*p_mkt*R9*p_rs_succ*p_realiz -> 0 | AG9: =IF(S9>0,AC9*P9/S9,0) -> 0 | AH9: =IF(T9>0,AD9*P9/T9,0) -> 1901.1289 | AI9: =IF(Q9>0,AE9*P9/Q9,0) -> 0 | AJ9: =IF(R9>0,AF9*P9/R9,0) -> 0 | AK9: =AC9+AD9+AE9*p_pwin_cen+AF9*p_pwin_cen*p_minsa_occ -> 4362.9994 | AL9: =(AC9-AG9)+(AD9-AH9)+(AE9-AI9)*p_pwin_cen+(AF9-AJ9)*p_pwin_cen*p_minsa_occ -> 2461.8706 | AM9: =IF(P9>0,E9*p_sup_idx*(1+p_pack)/P9,0) -> 0.88073814 | AN9: =IF(AND(Y9=1,H9*I9*15/12>70000),H9*p_mkt*Q9*p_rs_succ,0) -> 0
A10: CRO1G | B10: Ceftriaxona 1 g vial | C10: Bueno | D10: 1 | E10: 0.2 | F10: 0.01837 | G10: B2: Delhi RC 2022; exportaciones Seair 0.21-0.37 | H10: 194242 | I10: 0.239 | J10: 201135 | K10: 0.25 | L10: 1671 | M10: 0.78 | N10: 119983 | O10: 0.613 | P10: =E10*p_sup_idx*(1+p_pack)+F10*p_log_mult -> 0.28087 | Q10: =I10*p_pf_cen -> 0.22705 | R10: =K10*p_pf_cen -> 0.2375 | S10: =M10*p_pf_dec -> 0.702 | T10: =O10*p_pf_dec -> 0.5517 | U10: =IF(Q10>0,1-P10/Q10,-9) -> -0.2370403 | V10: =IF(R10>0,1-P10/R10,-9) -> -0.18261053 | W10: =IF(S10>0,1-P10/S10,-9) -> 0.59990028 | X10: =IF(T10>0,1-P10/T10,-9) -> 0.49090085 | Y10: =IF(AND($D10=1,H10>0,U10>=p_gm_cen),1,0) -> 0 | Z10: =IF(AND($D10=1,J10>0,V10>=p_gm_cen),1,0) -> 0 | AA10: =IF(AND($D10=1,L10>0,W10>=p_gm_dec),1,0) -> 1 | AB10: =IF(AND($D10=1,N10>0,X10>=p_gm_dec),1,0) -> 1 | AC10: =AA10*L10*p_mkt*S10*p_rs_succ*p_share_dec -> 197.42297 | AD10: =AB10*N10*p_mkt*T10*p_rs_succ*p_share_dec -> 11140.555 | AE10: =Y10*H10*p_mkt*Q10*p_rs_succ*p_realiz -> 0 | AF10: =Z10*J10*p_mkt*R10*p_rs_succ*p_realiz -> 0 | AG10: =IF(S10>0,AC10*P10/S10,0) -> 78.988873 | AH10: =IF(T10>0,AD10*P10/T10,0) -> 5671.6469 | AI10: =IF(Q10>0,AE10*P10/Q10,0) -> 0 | AJ10: =IF(R10>0,AF10*P10/R10,0) -> 0 | AK10: =AC10+AD10+AE10*p_pwin_cen+AF10*p_pwin_cen*p_minsa_occ -> 11337.978 | AL10: =(AC10-AG10)+(AD10-AH10)+(AE10-AI10)*p_pwin_cen+(AF10-AJ10)*p_pwin_cen*p_minsa_occ -> 5587.3419 | AM10: =IF(P10>0,E10*p_sup_idx*(1+p_pack)/P10,0) -> 0.93459608 | AN10: =IF(AND(Y10=1,H10*I10*15/12>70000),H10*p_mkt*Q10*p_rs_succ,0) -> 0
A11: CTX1G | B11: Cefotaxima 1 g vial | C11: Bueno | D11: 1 | E11: 0.11 | F11: 0.01807 | G11: B2: derivado de Jan Aushadhi MRP | H11: 168687 | I11: 0.259 | J11: 177344 | K11: 0.27 | L11: 7200 | M11: 1 | N11: 79691 | O11: 0.53 | P11: =E11*p_sup_idx*(1+p_pack)+F11*p_log_mult -> 0.162445 | Q11: =I11*p_pf_cen -> 0.24605 | R11: =K11*p_pf_cen -> 0.2565 | S11: =M11*p_pf_dec -> 0.9 | T11: =O11*p_pf_dec -> 0.477 | U11: =IF(Q11>0,1-P11/Q11,-9) -> 0.33978866 | V11: =IF(R11>0,1-P11/R11,-9) -> 0.36668616 | W11: =IF(S11>0,1-P11/S11,-9) -> 0.81950556 | X11: =IF(T11>0,1-P11/T11,-9) -> 0.65944444 | Y11: =IF(AND($D11=1,H11>0,U11>=p_gm_cen),1,0) -> 1 | Z11: =IF(AND($D11=1,J11>0,V11>=p_gm_cen),1,0) -> 1 | AA11: =IF(AND($D11=1,L11>0,W11>=p_gm_dec),1,0) -> 1 | AB11: =IF(AND($D11=1,N11>0,X11>=p_gm_dec),1,0) -> 1 | AC11: =AA11*L11*p_mkt*S11*p_rs_succ*p_share_dec -> 1090.584 | AD11: =AB11*N11*p_mkt*T11*p_rs_succ*p_share_dec -> 6397.5218 | AE11: =Y11*H11*p_mkt*Q11*p_rs_succ*p_realiz -> 23813.744 | AF11: =Z11*J11*p_mkt*R11*p_rs_succ*p_realiz -> 26099.162 | AG11: =IF(S11>0,AC11*P11/S11,0) -> 196.84435 | AH11: =IF(T11>0,AD11*P11/T11,0) -> 2178.7116 | AI11: =IF(Q11>0,AE11*P11/Q11,0) -> 15722.104 | AJ11: =IF(R11>0,AF11*P11/R11,0) -> 16528.961 | AK11: =AC11+AD11+AE11*p_pwin_cen+AF11*p_pwin_cen*p_minsa_occ -> 18547.103 | AL11: =(AC11-AG11)+(AD11-AH11)+(AE11-AI11)*p_pwin_cen+(AF11-AJ11)*p_pwin_cen*p_minsa_occ -> 8975.5721 | AM11: =IF(P11>0,E11*p_sup_idx*(1+p_pack)/P11,0) -> 0.88876235 | AN11: =IF(AND(Y11=1,H11*I11*15/12>70000),H11*p_mkt*Q11*p_rs_succ,0) -> 0
A12: ALBSUS | B12: Albendazol 400 mg/10 ml suspensión | C12: Bueno | D12: 1 | E12: 0.08 | F12: 0.03863 | G12: B2: Delhi RC 2022 x1.35 (frasco 10 ml) | H12: 18762 | I12: 1.81 | J12: 194990 | K12: 1.86 | L12: 0 | M12: 0 | N12: 10114 | O12: 1.62 | P12: =E12*p_sup_idx*(1+p_pack)+F12*p_log_mult -> 0.14363 | Q12: =I12*p_pf_cen -> 1.7195 | R12: =K12*p_pf_cen -> 1.767 | S12: =M12*p_pf_dec -> 0 | T12: =O12*p_pf_dec -> 1.458 | U12: =IF(Q12>0,1-P12/Q12,-9) -> 0.9164699 | V12: =IF(R12>0,1-P12/R12,-9) -> 0.91871534 | W12: =IF(S12>0,1-P12/S12,-9) -> -9 | X12: =IF(T12>0,1-P12/T12,-9) -> 0.90148834 | Y12: =IF(AND($D12=1,H12>0,U12>=p_gm_cen),1,0) -> 1 | Z12: =IF(AND($D12=1,J12>0,V12>=p_gm_cen),1,0) -> 1 | AA12: =IF(AND($D12=1,L12>0,W12>=p_gm_dec),1,0) -> 0 | AB12: =IF(AND($D12=1,N12>0,X12>=p_gm_dec),1,0) -> 1 | AC12: =AA12*L12*p_mkt*S12*p_rs_succ*p_share_dec -> 0 | AD12: =AB12*N12*p_mkt*T12*p_rs_succ*p_share_dec -> 2481.7875 | AE12: =Y12*H12*p_mkt*Q12*p_rs_succ*p_realiz -> 18509.897 | AF12: =Z12*J12*p_mkt*R12*p_rs_succ*p_realiz -> 197684.03 | AG12: =IF(S12>0,AC12*P12/S12,0) -> 0 | AH12: =IF(T12>0,AD12*P12/T12,0) -> 244.485 | AI12: =IF(Q12>0,AE12*P12/Q12,0) -> 1546.1335 | AJ12: =IF(R12>0,AF12*P12/R12,0) -> 16068.68 | AK12: =AC12+AD12+AE12*p_pwin_cen+AF12*p_pwin_cen*p_minsa_occ -> 37687.361 | AL12: =(AC12-AG12)+(AD12-AH12)+(AE12-AI12)*p_pwin_cen+(AF12-AJ12)*p_pwin_cen*p_minsa_occ -> 34568.734 | AM12: =IF(P12>0,E12*p_sup_idx*(1+p_pack)/P12,0) -> 0.73104505 | AN12: =IF(AND(Y12=1,H12*I12*15/12>70000),H12*p_mkt*Q12*p_rs_succ,0) -> 0
A13: MBZ100 | B13: Mebendazol 100 mg tableta | C13: Bueno | D13: 1 | E13: 0.008 | F13: 0.0015 | G13: B2: derivado de Jan Aushadhi MRP | H13: 188514 | I13: 0.13 | J13: 179270 | K13: 0.13 | L13: 13714 | M13: 0.22 | N13: 1714 | O13: 0.164 | P13: =E13*p_sup_idx*(1+p_pack)+F13*p_log_mult -> 0.012 | Q13: =I13*p_pf_cen -> 0.1235 | R13: =K13*p_pf_cen -> 0.1235 | S13: =M13*p_pf_dec -> 0.198 | T13: =O13*p_pf_dec -> 0.1476 | U13: =IF(Q13>0,1-P13/Q13,-9) -> 0.90283401 | V13: =IF(R13>0,1-P13/R13,-9) -> 0.90283401 | W13: =IF(S13>0,1-P13/S13,-9) -> 0.93939394 | X13: =IF(T13>0,1-P13/T13,-9) -> 0.91869919 | Y13: =IF(AND($D13=1,H13>0,U13>=p_gm_cen),1,0) -> 1 | Z13: =IF(AND($D13=1,J13>0,V13>=p_gm_cen),1,0) -> 1 | AA13: =IF(AND($D13=1,L13>0,W13>=p_gm_dec),1,0) -> 1 | AB13: =IF(AND($D13=1,N13>0,X13>=p_gm_dec),1,0) -> 1 | AC13: =AA13*L13*p_mkt*S13*p_rs_succ*p_share_dec -> 456.99711 | AD13: =AB13*N13*p_mkt*T13*p_rs_succ*p_share_dec -> 42.577611 | AE13: =Y13*H13*p_mkt*Q13*p_rs_succ*p_realiz -> 13357.749 | AF13: =Z13*J13*p_mkt*R13*p_rs_succ*p_realiz -> 12702.736 | AG13: =IF(S13>0,AC13*P13/S13,0) -> 27.696794 | AH13: =IF(T13>0,AD13*P13/T13,0) -> 3.4615944 | AI13: =IF(Q13>0,AE13*P13/Q13,0) -> 1297.9189 | AJ13: =IF(R13>0,AF13*P13/R13,0) -> 1234.274 | AK13: =AC13+AD13+AE13*p_pwin_cen+AF13*p_pwin_cen*p_minsa_occ -> 6412.3097 | AL13: =(AC13-AG13)+(AD13-AH13)+(AE13-AI13)*p_pwin_cen+(AF13-AJ13)*p_pwin_cen*p_minsa_occ -> 5806.6346 | AM13: =IF(P13>0,E13*p_sup_idx*(1+p_pack)/P13,0) -> 0.875 | AN13: =IF(AND(Y13=1,H13*I13*15/12>70000),H13*p_mkt*Q13*p_rs_succ,0) -> 0
A14: NYSSUS | B14: Nistatina 100,000 UI/ml suspensión | C14: Bueno | D14: 1 | E14: 0.4 | F14: 0.05903 | G14: E: sin precio público; supuesto a confirmar con Zywie | H14: 14898 | I14: 3.18 | J14: 18119 | K14: 3.39 | L14: 0 | M14: 0 | N14: 1856 | O14: 3.18 | P14: =E14*p_sup_idx*(1+p_pack)+F14*p_log_mult -> 0.58403 | Q14: =I14*p_pf_cen -> 3.021 | R14: =K14*p_pf_cen -> 3.2205 | S14: =M14*p_pf_dec -> 0 | T14: =O14*p_pf_dec -> 2.862 | U14: =IF(Q14>0,1-P14/Q14,-9) -> 0.8066766 | V14: =IF(R14>0,1-P14/R14,-9) -> 0.81865238 | W14: =IF(S14>0,1-P14/S14,-9) -> -9 | X14: =IF(T14>0,1-P14/T14,-9) -> 0.79593641 | Y14: =IF(AND($D14=1,H14>0,U14>=p_gm_cen),1,0) -> 1 | Z14: =IF(AND($D14=1,J14>0,V14>=p_gm_cen),1,0) -> 1 | AA14: =IF(AND($D14=1,L14>0,W14>=p_gm_dec),1,0) -> 0 | AB14: =IF(AND($D14=1,N14>0,X14>=p_gm_dec),1,0) -> 1 | AC14: =AA14*L14*p_mkt*S14*p_rs_succ*p_share_dec -> 0 | AD14: =AB14*N14*p_mkt*T14*p_rs_succ*p_share_dec -> 893.98806 | AE14: =Y14*H14*p_mkt*Q14*p_rs_succ*p_realiz -> 25822.685 | AF14: =Z14*J14*p_mkt*R14*p_rs_succ*p_realiz -> 33479.597 | AG14: =IF(S14>0,AC14*P14/S14,0) -> 0 | AH14: =IF(T14>0,AD14*P14/T14,0) -> 182.43041 | AI14: =IF(Q14>0,AE14*P14/Q14,0) -> 4992.1293 | AJ14: =IF(R14>0,AF14*P14/R14,0) -> 6071.4452 | AK14: =AC14+AD14+AE14*p_pwin_cen+AF14*p_pwin_cen*p_minsa_occ -> 13662.733 | AL14: =(AC14-AG14)+(AD14-AH14)+(AE14-AI14)*p_pwin_cen+(AF14-AJ14)*p_pwin_cen*p_minsa_occ -> 11071.947 | AM14: =IF(P14>0,E14*p_sup_idx*(1+p_pack)/P14,0) -> 0.89892643 | AN14: =IF(AND(Y14=1,H14*I14*15/12>70000),H14*p_mkt*Q14*p_rs_succ,0) -> 0
A15: HCTCRM | B15: Hidrocortisona crema (línea corticoide baja potencia) | C15: Bueno | D15: 1 | E15: 0.16 | F15: 0.04923 | G15: B2: derivado de Jan Aushadhi MRP (tubo 15 g) | H15: 89267 | I15: 0.555 | J15: 44276 | K15: 0.58 | L15: 634 | M15: 2.5 | N15: 1564 | O15: 1.875 | P15: =E15*p_sup_idx*(1+p_pack)+F15*p_log_mult -> 0.25923 | Q15: =I15*p_pf_cen -> 0.52725 | R15: =K15*p_pf_cen -> 0.551 | S15: =M15*p_pf_dec -> 2.25 | T15: =O15*p_pf_dec -> 1.6875 | U15: =IF(Q15>0,1-P15/Q15,-9) -> 0.5083357 | V15: =IF(R15>0,1-P15/R15,-9) -> 0.52952813 | W15: =IF(S15>0,1-P15/S15,-9) -> 0.88478667 | X15: =IF(T15>0,1-P15/T15,-9) -> 0.84638222 | Y15: =IF(AND($D15=1,H15>0,U15>=p_gm_cen),1,0) -> 1 | Z15: =IF(AND($D15=1,J15>0,V15>=p_gm_cen),1,0) -> 1 | AA15: =IF(AND($D15=1,L15>0,W15>=p_gm_dec),1,0) -> 1 | AB15: =IF(AND($D15=1,N15>0,X15>=p_gm_dec),1,0) -> 1 | AC15: =AA15*L15*p_mkt*S15*p_rs_succ*p_share_dec -> 240.07995 | AD15: =AB15*N15*p_mkt*T15*p_rs_succ*p_share_dec -> 444.18577 | AE15: =Y15*H15*p_mkt*Q15*p_rs_succ*p_realiz -> 27004.132 | AF15: =Z15*J15*p_mkt*R15*p_rs_succ*p_realiz -> 13997.249 | AG15: =IF(S15>0,AC15*P15/S15,0) -> 27.660411 | AH15: =IF(T15>0,AD15*P15/T15,0) -> 68.234832 | AI15: =IF(Q15>0,AE15*P15/Q15,0) -> 13276.968 | AJ15: =IF(R15>0,AF15*P15/R15,0) -> 6585.3117 | AK15: =AC15+AD15+AE15*p_pwin_cen+AF15*p_pwin_cen*p_minsa_occ -> 10885.093 | AL15: =(AC15-AG15)+(AD15-AH15)+(AE15-AI15)*p_pwin_cen+(AF15-AJ15)*p_pwin_cen*p_minsa_occ -> 5818.3104 | AM15: =IF(P15>0,E15*p_sup_idx*(1+p_pack)/P15,0) -> 0.81009142 | AN15: =IF(AND(Y15=1,H15*I15*15/12>70000),H15*p_mkt*Q15*p_rs_succ,0) -> 0
A16: MOMCRM | B16: Mometasona 0.1% crema (línea corticoide alta potencia) | C16: Bueno | D16: 1 | E16: 0.097 | F16: 0.04923 | G16: E: Jan Aushadhi MRP INR 16.88/15 g x0.55 | H16: 65534 | I16: 1.02 | J16: 34482 | K16: 0.65 | L16: 1840 | M16: 4.79 | N16: 343 | O16: 3.66 | P16: =E16*p_sup_idx*(1+p_pack)+F16*p_log_mult -> 0.1765425 | Q16: =I16*p_pf_cen -> 0.969 | R16: =K16*p_pf_cen -> 0.6175 | S16: =M16*p_pf_dec -> 4.311 | T16: =O16*p_pf_dec -> 3.294 | U16: =IF(Q16>0,1-P16/Q16,-9) -> 0.8178096 | V16: =IF(R16>0,1-P16/R16,-9) -> 0.71410121 | W16: =IF(S16>0,1-P16/S16,-9) -> 0.95904836 | X16: =IF(T16>0,1-P16/T16,-9) -> 0.94640483 | Y16: =IF(AND($D16=1,H16>0,U16>=p_gm_cen),1,0) -> 1 | Z16: =IF(AND($D16=1,J16>0,V16>=p_gm_cen),1,0) -> 1 | AA16: =IF(AND($D16=1,L16>0,W16>=p_gm_dec),1,0) -> 1 | AB16: =IF(AND($D16=1,N16>0,X16>=p_gm_dec),1,0) -> 1 | AC16: =AA16*L16*p_mkt*S16*p_rs_succ*p_share_dec -> 1334.996 | AD16: =AB16*N16*p_mkt*T16*p_rs_succ*p_share_dec -> 190.15241 | AE16: =Y16*H16*p_mkt*Q16*p_rs_succ*p_realiz -> 36434.528 | AF16: =Z16*J16*p_mkt*R16*p_rs_succ*p_realiz -> 12216.649 | AG16: =IF(S16>0,AC16*P16/S16,0) -> 54.670269 | AH16: =IF(T16>0,AD16*P16/T16,0) -> 10.191251 | AI16: =IF(Q16>0,AE16*P16/Q16,0) -> 6638.0214 | AJ16: =IF(R16>0,AF16*P16/R16,0) -> 3492.7252 | AK16: =AC16+AD16+AE16*p_pwin_cen+AF16*p_pwin_cen*p_minsa_occ -> 14288.004 | AL16: =(AC16-AG16)+(AD16-AH16)+(AE16-AI16)*p_pwin_cen+(AF16-AJ16)*p_pwin_cen*p_minsa_occ -> 11707.828 | AM16: =IF(P16>0,E16*p_sup_idx*(1+p_pack)/P16,0) -> 0.72114363 | AN16: =IF(AND(Y16=1,H16*I16*15/12>70000),H16*p_mkt*Q16*p_rs_succ,0) -> 48579.371
A17: AMI10 | B17: Amitriptilina 10 mg tableta | C17: CNS | D17: 0 | E17: 0.0039 | F17: 0.0015 | G17: E: Jan Aushadhi MRP INR 0.681/tab x0.54 | H17: 325776 | I17: 0.12 | J17: 152808 | K17: 0.12 | L17: 0 | M17: 0 | N17: 0 | O17: 0 | P17: =E17*p_sup_idx*(1+p_pack)+F17*p_log_mult -> 0.00661875 | Q17: =I17*p_pf_cen -> 0.114 | R17: =K17*p_pf_cen -> 0.114 | S17: =M17*p_pf_dec -> 0 | T17: =O17*p_pf_dec -> 0 | U17: =IF(Q17>0,1-P17/Q17,-9) -> 0.94194079 | V17: =IF(R17>0,1-P17/R17,-9) -> 0.94194079 | W17: =IF(S17>0,1-P17/S17,-9) -> -9 | X17: =IF(T17>0,1-P17/T17,-9) -> -9 | Y17: =IF(AND($D17=1,H17>0,U17>=p_gm_cen),1,0) -> 0 | Z17: =IF(AND($D17=1,J17>0,V17>=p_gm_cen),1,0) -> 0 | AA17: =IF(AND($D17=1,L17>0,W17>=p_gm_dec),1,0) -> 0 | AB17: =IF(AND($D17=1,N17>0,X17>=p_gm_dec),1,0) -> 0 | AC17: =AA17*L17*p_mkt*S17*p_rs_succ*p_share_dec -> 0 | AD17: =AB17*N17*p_mkt*T17*p_rs_succ*p_share_dec -> 0 | AE17: =Y17*H17*p_mkt*Q17*p_rs_succ*p_realiz -> 0 | AF17: =Z17*J17*p_mkt*R17*p_rs_succ*p_realiz -> 0 | AG17: =IF(S17>0,AC17*P17/S17,0) -> 0 | AH17: =IF(T17>0,AD17*P17/T17,0) -> 0 | AI17: =IF(Q17>0,AE17*P17/Q17,0) -> 0 | AJ17: =IF(R17>0,AF17*P17/R17,0) -> 0 | AK17: =AC17+AD17+AE17*p_pwin_cen+AF17*p_pwin_cen*p_minsa_occ -> 0 | AL17: =(AC17-AG17)+(AD17-AH17)+(AE17-AI17)*p_pwin_cen+(AF17-AJ17)*p_pwin_cen*p_minsa_occ -> 0 | AM17: =IF(P17>0,E17*p_sup_idx*(1+p_pack)/P17,0) -> 0.7733711 | AN17: =IF(AND(Y17=1,H17*I17*15/12>70000),H17*p_mkt*Q17*p_rs_succ,0) -> 0
... A24: PRD5 | B24: Prednisolona 5 mg tableta | C24: Modi | D24: 0 | E24: 0.0028 | F24: 0.0015 | G24: E: Jan Aushadhi MRP INR 0.50/tab x0.54 | H24: 3497727 | I24: 0.016 | J24: 0 | K24: 0 | L24: 139429 | M24: 0.24 | N24: 212682 | O24: 0.205 | P24: =E24*p_sup_idx*(1+p_pack)+F24*p_log_mult -> 0.005175 | Q24: =I24*p_pf_cen -> 0.0152 | R24: =K24*p_pf_cen -> 0 | S24: =M24*p_pf_dec -> 0.216 | T24: =O24*p_pf_dec -> 0.1845 | U24: =IF(Q24>0,1-P24/Q24,-9) -> 0.65953947 | V24: =IF(R24>0,1-P24/R24,-9) -> -9 | W24: =IF(S24>0,1-P24/S24,-9) -> 0.97604167 | X24: =IF(T24>0,1-P24/T24,-9) -> 0.97195122 | Y24: =IF(AND($D24=1,H24>0,U24>=p_gm_cen),1,0) -> 0 | Z24: =IF(AND($D24=1,J24>0,V24>=p_gm_cen),1,0) -> 0 | AA24: =IF(AND($D24=1,L24>0,W24>=p_gm_dec),1,0) -> 0 | AB24: =IF(AND($D24=1,N24>0,X24>=p_gm_dec),1,0) -> 0 | AC24: =AA24*L24*p_mkt*S24*p_rs_succ*p_share_dec -> 0 | AD24: =AB24*N24*p_mkt*T24*p_rs_succ*p_share_dec -> 0 | AE24: =Y24*H24*p_mkt*Q24*p_rs_succ*p_realiz -> 0 | AF24: =Z24*J24*p_mkt*R24*p_rs_succ*p_realiz -> 0 | AG24: =IF(S24>0,AC24*P24/S24,0) -> 0 | AH24: =IF(T24>0,AD24*P24/T24,0) -> 0 | AI24: =IF(Q24>0,AE24*P24/Q24,0) -> 0 | AJ24: =IF(R24>0,AF24*P24/R24,0) -> 0 | AK24: =AC24+AD24+AE24*p_pwin_cen+AF24*p_pwin_cen*p_minsa_occ -> 0 | AL24: =(AC24-AG24)+(AD24-AH24)+(AE24-AI24)*p_pwin_cen+(AF24-AJ24)*p_pwin_cen*p_minsa_occ -> 0 | AM24: =IF(P24>0,E24*p_sup_idx*(1+p_pack)/P24,0) -> 0.71014493 | AN24: =IF(AND(Y24=1,H24*I24*15/12>70000),H24*p_mkt*Q24*p_rs_succ,0) -> 0
B25: Totales (productos incluidos) | AC25: =SUM(AC6:AC24) -> 20921.76 | AD25: =SUM(AD6:AD24) -> 69833.199 | AE25: =SUM(AE6:AE24) -> 251013.65 | AF25: =SUM(AF6:AF24) -> 315973.72 | AG25: =SUM(AG6:AG24) -> 7837.2387 | AH25: =SUM(AH6:AH24) -> 29112.507 | AI25: =SUM(AI6:AI24) -> 116483.47 | AJ25: =SUM(AJ6:AJ24) -> 62650.296 | ... AL25: =SUM(AL6:AL24) -> 132162.78 | AM25: =IF(SUM(AG6:AJ24)>0,SUMPRODUCT(AG6:AG24+AH6:AH24+AI6:AI24+AJ6:AJ24,AM6:AM24)/SUM(AG6:AJ24),0) -> 0.74234978 | AN25: =SUM(AN6:AN24) -> 183953.72

Sheet Mensual
A1: Flujo mensual (B/.)
C2: Mes 0
A3: Mes | C3: 0 | D3: 1 | E3: 2 | F3: 3 | G3: 4 | H3: 5 | I3: 6 | J3: 7 | K3: 8 | L3: 9 | M3: 10 | N3: 11 | O3: 12 | P3: 13 | Q3: 14 | R3: 15 | S3: 16 | T3: 17 | U3: 18 | V3: 19 | W3: 20 | X3: 21 | Y3: 22 | Z3: 23 | AA3: 24 | AB3: 25 | AC3: 26 | AD3: 27 | AE3: 28 | AF3: 29 | AG3: 30 | AH3: 31 | AI3: 32 | AJ3: 33 | AK3: 34 | AL3: 35 | AM3: 36 | AN3: 37 | AO3: 38 | AP3: 39 | AQ3: 40 | AR3: 41 | AS3: 42 | AT3: 43 | AU3: 44 | AV3: 45 | AW3: 46 | AX3: 47 | AY3: 48 | AZ3: 49 | BA3: 50 | BB3: 51 | BC3: 52 | BD3: 53 | BE3: 54 | BF3: 55 | BG3: 56 | BH3: 57 | BI3: 58 | BJ3: 59 | BK3: 60 | BL3: 61
A4: Año | D4: =INT((MIN(D$3,60)-1)/12)+1 -> 1 | E4: =INT((MIN(E$3,60)-1)/12)+1 -> 1 | F4: =INT((MIN(F$3,60)-1)/12)+1 -> 1 | G4: =INT((MIN(G$3,60)-1)/12)+1 -> 1 | H4: =INT((MIN(H$3,60)-1)/12)+1 -> 1 | I4: =INT((MIN(I$3,60)-1)/12)+1 -> 1 | J4: =INT((MIN(J$3,60)-1)/12)+1 -> 1 | K4: =INT((MIN(K$3,60)-1)/12)+1 -> 1 | ... BL4: =INT((MIN(BL$3,60)-1)/12)+1 -> 5
A5: Factor de erosión de precios | D5: =(1-p_erosion)^(D4-1) -> 1 | E5: =(1-p_erosion)^(E4-1) -> 1 | F5: =(1-p_erosion)^(F4-1) -> 1 | G5: =(1-p_erosion)^(G4-1) -> 1 | H5: =(1-p_erosion)^(H4-1) -> 1 | I5: =(1-p_erosion)^(I4-1) -> 1 | J5: =(1-p_erosion)^(J4-1) -> 1 | K5: =(1-p_erosion)^(K4-1) -> 1 | ... BL5: =(1-p_erosion)^(BL4-1) -> 0.88529281
A6: Negocio activo (1/0) | D6: =IF(D$3<=ROUND(p_stop_det,0),1,0) -> 1 | E6: =IF(E$3<=ROUND(p_stop_det,0),1,0) -> 1 | F6: =IF(F$3<=ROUND(p_stop_det,0),1,0) -> 1 | G6: =IF(G$3<=ROUND(p_stop_det,0),1,0) -> 1 | H6: =IF(H$3<=ROUND(p_stop_det,0),1,0) -> 1 | I6: =IF(I$3<=ROUND(p_stop_det,0),1,0) -> 1 | J6: =IF(J$3<=ROUND(p_stop_det,0),1,0) -> 1 | K6: =IF(K$3<=ROUND(p_stop_det,0),1,0) -> 1 | ... BL6: =IF(BL$3<=ROUND(p_stop_det,0),1,0) -> 1
A7: Rampa primera ola | D7: =MAX(0,MIN(1,(D$3-c_first_dec+1)/p_ramp_m)) -> 0 | E7: =MAX(0,MIN(1,(E$3-c_first_dec+1)/p_ramp_m)) -> 0 | F7: =MAX(0,MIN(1,(F$3-c_first_dec+1)/p_ramp_m)) -> 0 | G7: =MAX(0,MIN(1,(G$3-c_first_dec+1)/p_ramp_m)) -> 0 | H7: =MAX(0,MIN(1,(H$3-c_first_dec+1)/p_ramp_m)) -> 0 | I7: =MAX(0,MIN(1,(I$3-c_first_dec+1)/p_ramp_m)) -> 0 | J7: =MAX(0,MIN(1,(J$3-c_first_dec+1)/p_ramp_m)) -> 0 | K7: =MAX(0,MIN(1,(K$3-c_first_dec+1)/p_ramp_m)) -> 0 | ... BL7: =MAX(0,MIN(1,(BL$3-c_first_dec+1)/p_ramp_m)) -> 1
A8: Rampa segunda ola | D8: =MAX(0,MIN(1,(D$3-c_first_dec2+1)/p_ramp_m)) -> 0 | E8: =MAX(0,MIN(1,(E$3-c_first_dec2+1)/p_ramp_m)) -> 0 | F8: =MAX(0,MIN(1,(F$3-c_first_dec2+1)/p_ramp_m)) -> 0 | G8: =MAX(0,MIN(1,(G$3-c_first_dec2+1)/p_ramp_m)) -> 0 | H8: =MAX(0,MIN(1,(H$3-c_first_dec2+1)/p_ramp_m)) -> 0 | I8: =MAX(0,MIN(1,(I$3-c_first_dec2+1)/p_ramp_m)) -> 0 | J8: =MAX(0,MIN(1,(J$3-c_first_dec2+1)/p_ramp_m)) -> 0 | K8: =MAX(0,MIN(1,(K$3-c_first_dec2+1)/p_ramp_m)) -> 0 | ... BL8: =MAX(0,MIN(1,(BL$3-c_first_dec2+1)/p_ramp_m)) -> 1
A9: Contratos centralizados activos | D9: =IF(D$3>=c_cen_start,1,0) -> 0 | E9: =IF(E$3>=c_cen_start,1,0) -> 0 | F9: =IF(F$3>=c_cen_start,1,0) -> 0 | G9: =IF(G$3>=c_cen_start,1,0) -> 0 | H9: =IF(H$3>=c_cen_start,1,0) -> 0 | I9: =IF(I$3>=c_cen_start,1,0) -> 0 | J9: =IF(J$3>=c_cen_start,1,0) -> 0 | K9: =IF(K$3>=c_cen_start,1,0) -> 0 | ... BL9: =IF(BL$3>=c_cen_start,1,0) -> 1
A10: Centralizado segunda ola | D10: =IF(D$3>=MAX(c_cen_start,c_first_dec2),1,0) -> 0 | E10: =IF(E$3>=MAX(c_cen_start,c_first_dec2),1,0) -> 0 | F10: =IF(F$3>=MAX(c_cen_start,c_first_dec2),1,0) -> 0 | G10: =IF(G$3>=MAX(c_cen_start,c_first_dec2),1,0) -> 0 | H10: =IF(H$3>=MAX(c_cen_start,c_first_dec2),1,0) -> 0 | I10: =IF(I$3>=MAX(c_cen_start,c_first_dec2),1,0) -> 0 | J10: =IF(J$3>=MAX(c_cen_start,c_first_dec2),1,0) -> 0 | K10: =IF(K$3>=MAX(c_cen_start,c_first_dec2),1,0) -> 0 | ... BL10: =IF(BL$3>=MAX(c_cen_start,c_first_dec2),1,0) -> 1
A11: Multiplicador descentralizado (olas) | D11: =1+c_k2*D8 -> 1 | E11: =1+c_k2*E8 -> 1 | F11: =1+c_k2*F8 -> 1 | G11: =1+c_k2*G8 -> 1 | H11: =1+c_k2*H8 -> 1 | I11: =1+c_k2*I8 -> 1 | J11: =1+c_k2*J8 -> 1 | K11: =1+c_k2*K8 -> 1 | ... BL11: =1+c_k2*BL8 -> 1.3818182
A12: Multiplicador centralizado (olas) | D12: =1+c_k2*D10 -> 1 | E12: =1+c_k2*E10 -> 1 | F12: =1+c_k2*F10 -> 1 | G12: =1+c_k2*G10 -> 1 | H12: =1+c_k2*H10 -> 1 | I12: =1+c_k2*I10 -> 1 | J12: =1+c_k2*J10 -> 1 | K12: =1+c_k2*K10 -> 1 | ... BL12: =1+c_k2*BL10 -> 1.3818182
A13: Ventas descentralizadas | D13: =(s_Rd3+s_Rd4)/12*D7*D11*D5*D6 -> 0 | E13: =(s_Rd3+s_Rd4)/12*E7*E11*E5*E6 -> 0 | F13: =(s_Rd3+s_Rd4)/12*F7*F11*F5*F6 -> 0 | G13: =(s_Rd3+s_Rd4)/12*G7*G11*G5*G6 -> 0 | H13: =(s_Rd3+s_Rd4)/12*H7*H11*H5*H6 -> 0 | I13: =(s_Rd3+s_Rd4)/12*I7*I11*I5*I6 -> 0 | J13: =(s_Rd3+s_Rd4)/12*J7*J11*J5*J6 -> 0 | K13: =(s_Rd3+s_Rd4)/12*K7*K11*K5*K6 -> 0 | ... BL13: =(s_Rd3+s_Rd4)/12*BL7*BL11*BL5*BL6 -> 9251.8155
A14: Ventas centralizadas | D14: =(s_Rc1*p_pwin_cen+s_Rc2*p_pwin_cen*p_minsa_occ)/12*D9*D12*D5*D6 -> 0 | E14: =(s_Rc1*p_pwin_cen+s_Rc2*p_pwin_cen*p_minsa_occ)/12*E9*E12*E5*E6 -> 0 | F14: =(s_Rc1*p_pwin_cen+s_Rc2*p_pwin_cen*p_minsa_occ)/12*F9*F12*F5*F6 -> 0 | G14: =(s_Rc1*p_pwin_cen+s_Rc2*p_pwin_cen*p_minsa_occ)/12*G9*G12*G5*G6 -> 0 | H14: =(s_Rc1*p_pwin_cen+s_Rc2*p_pwin_cen*p_minsa_occ)/12*H9*H12*H5*H6 -> 0 | I14: =(s_Rc1*p_pwin_cen+s_Rc2*p_pwin_cen*p_minsa_occ)/12*I9*I12*I5*I6 -> 0 | J14: =(s_Rc1*p_pwin_cen+s_Rc2*p_pwin_cen*p_minsa_occ)/12*J9*J12*J5*J6 -> 0 | K14: =(s_Rc1*p_pwin_cen+s_Rc2*p_pwin_cen*p_minsa_occ)/12*K9*K12*K5*K6 -> 0 | ... BL14: =(s_Rc1*p_pwin_cen+s_Rc2*p_pwin_cen*p_minsa_occ)/12*BL9*BL12*BL5*BL6 -> 12508.398
A15: VENTAS TOTALES | D15: =D13+D14 -> 0 | E15: =E13+E14 -> 0 | F15: =F13+F14 -> 0 | G15: =G13+G14 -> 0 | H15: =H13+H14 -> 0 | I15: =I13+I14 -> 0 | J15: =J13+J14 -> 0 | K15: =K13+K14 -> 0 | ... BL15: =BL13+BL14 -> 21760.214
A16: Costo de ventas descentralizado | D16: =(s_Rd3k+s_Rd4k)/12*D7*D11*D6 -> 0 | E16: =(s_Rd3k+s_Rd4k)/12*E7*E11*E6 -> 0 | F16: =(s_Rd3k+s_Rd4k)/12*F7*F11*F6 -> 0 | G16: =(s_Rd3k+s_Rd4k)/12*G7*G11*G6 -> 0 | H16: =(s_Rd3k+s_Rd4k)/12*H7*H11*H6 -> 0 | I16: =(s_Rd3k+s_Rd4k)/12*I7*I11*I6 -> 0 | J16: =(s_Rd3k+s_Rd4k)/12*J7*J11*J6 -> 0 | K16: =(s_Rd3k+s_Rd4k)/12*K7*K11*K6 -> 0 | ... BL16: =(s_Rd3k+s_Rd4k)/12*BL7*BL11*BL6 -> 4254.8192
A17: Costo de ventas centralizado | D17: =(s_Rc1k*p_pwin_cen+s_Rc2k*p_pwin_cen*p_minsa_occ)/12*D9*D12*D6 -> 0 | E17: =(s_Rc1k*p_pwin_cen+s_Rc2k*p_pwin_cen*p_minsa_occ)/12*E9*E12*E6 -> 0 | F17: =(s_Rc1k*p_pwin_cen+s_Rc2k*p_pwin_cen*p_minsa_occ)/12*F9*F12*F6 -> 0 | G17: =(s_Rc1k*p_pwin_cen+s_Rc2k*p_pwin_cen*p_minsa_occ)/12*G9*G12*G6 -> 0 | H17: =(s_Rc1k*p_pwin_cen+s_Rc2k*p_pwin_cen*p_minsa_occ)/12*H9*H12*H6 -> 0 | I17: =(s_Rc1k*p_pwin_cen+s_Rc2k*p_pwin_cen*p_minsa_occ)/12*I9*I12*I6 -> 0 | J17: =(s_Rc1k*p_pwin_cen+s_Rc2k*p_pwin_cen*p_minsa_occ)/12*J9*J12*J6 -> 0 | K17: =(s_Rc1k*p_pwin_cen+s_Rc2k*p_pwin_cen*p_minsa_occ)/12*K9*K12*K6 -> 0 | ... BL17: =(s_Rc1k*p_pwin_cen+s_Rc2k*p_pwin_cen*p_minsa_occ)/12*BL9*BL12*BL6 -> 5106.1158
A18: COSTO DE VENTAS | D18: =D16+D17 -> 0 | E18: =E16+E17 -> 0 | F18: =F16+F17 -> 0 | G18: =G16+G17 -> 0 | H18: =H16+H17 -> 0 | I18: =I16+I17 -> 0 | J18: =J16+J17 -> 0 | K18: =K16+K17 -> 0 | ... BL18: =BL16+BL17 -> 9360.9351
A19: Inventario objetivo al cierre (costo) | C19: 0 | D19: =IF(AND(D$3>=c_first_dec,D$3<=ROUND(p_stop_det,0)),(s_Rd3k+s_Rd4k)/12*E7*E11*p_cover_m+(s_Rc1k*p_pwin_cen+s_Rc2k*p_pwin_cen*p_minsa_occ)/12*E9*E12*p_cen_stock_m,0) -> 0 | E19: =IF(AND(E$3>=c_first_dec,E$3<=ROUND(p_stop_det,0)),(s_Rd3k+s_Rd4k)/12*F7*F11*p_cover_m+(s_Rc1k*p_pwin_cen+s_Rc2k*p_pwin_cen*p_minsa_occ)/12*F9*F12*p_cen_stock_m,0) -> 0 | F19: =IF(AND(F$3>=c_first_dec,F$3<=ROUND(p_stop_det,0)),(s_Rd3k+s_Rd4k)/12*G7*G11*p_cover_m+(s_Rc1k*p_pwin_cen+s_Rc2k*p_pwin_cen*p_minsa_occ)/12*G9*G12*p_cen_stock_m,0) -> 0 | G19: =IF(AND(G$3>=c_first_dec,G$3<=ROUND(p_stop_det,0)),(s_Rd3k+s_Rd4k)/12*H7*H11*p_cover_m+(s_Rc1k*p_pwin_cen+s_Rc2k*p_pwin_cen*p_minsa_occ)/12*H9*H12*p_cen_stock_m,0) -> 0 | H19: =IF(AND(H$3>=c_first_dec,H$3<=ROUND(p_stop_det,0)),(s_Rd3k+s_Rd4k)/12*I7*I11*p_cover_m+(s_Rc1k*p_pwin_cen+s_Rc2k*p_pwin_cen*p_minsa_occ)/12*I9*I12*p_cen_stock_m,0) -> 0 | I19: =IF(AND(I$3>=c_first_dec,I$3<=ROUND(p_stop_det,0)),(s_Rd3k+s_Rd4k)/12*J7*J11*p_cover_m+(s_Rc1k*p_pwin_cen+s_Rc2k*p_pwin_cen*p_minsa_occ)/12*J9*J12*p_cen_stock_m,0) -> 0 | J19: =IF(AND(J$3>=c_first_dec,J$3<=ROUND(p_stop_det,0)),(s_Rd3k+s_Rd4k)/12*K7*K11*p_cover_m+(s_Rc1k*p_pwin_cen+s_Rc2k*p_pwin_cen*p_minsa_occ)/12*K9*K12*p_cen_stock_m,0) -> 0 | K19: =IF(AND(K$3>=c_first_dec,K$3<=ROUND(p_stop_det,0)),(s_Rd3k+s_Rd4k)/12*L7*L11*p_cover_m+(s_Rc1k*p_pwin_cen+s_Rc2k*p_pwin_cen*p_minsa_occ)/12*L9*L12*p_cen_stock_m,0) -> 0 | ... BK19: =IF(AND(BK$3>=c_first_dec,BK$3<=ROUND(p_stop_det,0)),(s_Rd3k+s_Rd4k)/12*BL7*BL11*p_cover_m+(s_Rc1k*p_pwin_cen+s_Rc2k*p_pwin_cen*p_minsa_occ)/12*BL9*BL12*p_cen_stock_m,0) -> 22976.689
A20: Mercancía recibida (costo, incl. mermas) | D20: =IF(D$3>ROUND(p_stop_det,0),0,D18*(1+p_expiry)+D19-C19) -> 0 | E20: =IF(E$3>ROUND(p_stop_det,0),0,E18*(1+p_expiry)+E19-D19) -> 0 | F20: =IF(F$3>ROUND(p_stop_det,0),0,F18*(1+p_expiry)+F19-E19) -> 0 | G20: =IF(G$3>ROUND(p_stop_det,0),0,G18*(1+p_expiry)+G19-F19) -> 0 | H20: =IF(H$3>ROUND(p_stop_det,0),0,H18*(1+p_expiry)+H19-G19) -> 0 | I20: =IF(I$3>ROUND(p_stop_det,0),0,I18*(1+p_expiry)+I19-H19) -> 0 | J20: =IF(J$3>ROUND(p_stop_det,0),0,J18*(1+p_expiry)+J19-I19) -> 0 | K20: =IF(K$3>ROUND(p_stop_det,0),0,K18*(1+p_expiry)+K19-J19) -> 0 | ... BK20: =IF(BK$3>ROUND(p_stop_det,0),0,BK18*(1+p_expiry)+BK19-BJ19) -> 9641.7631
A21: Pago de anticipos al proveedor | D21: =p_adv*IFERROR(INDEX($D$20:$BK$20,1,D$3+c_lead_m),0) -> 0 | E21: =p_adv*IFERROR(INDEX($D$20:$BK$20,1,E$3+c_lead_m),0) -> 0 | F21: =p_adv*IFERROR(INDEX($D$20:$BK$20,1,F$3+c_lead_m),0) -> 0 | G21: =p_adv*IFERROR(INDEX($D$20:$BK$20,1,G$3+c_lead_m),0) -> 0 | H21: =p_adv*IFERROR(INDEX($D$20:$BK$20,1,H$3+c_lead_m),0) -> 0 | I21: =p_adv*IFERROR(INDEX($D$20:$BK$20,1,I$3+c_lead_m),0) -> 541.15982 | J21: =p_adv*IFERROR(INDEX($D$20:$BK$20,1,J$3+c_lead_m),0) -> 389.5119 | K21: =p_adv*IFERROR(INDEX($D$20:$BK$20,1,K$3+c_lead_m),0) -> 468.7999 | ... BK21: =p_adv*IFERROR(INDEX($D$20:$BK$20,1,BK$3+c_lead_m),0) -> 0
A22: Pago de saldos al proveedor | D22: =IF(AND(D$3+c_ship_m-c_credit_m>=1,D$3+c_ship_m-c_credit_m<=60),(1-p_adv)*INDEX($D$20:$BK$20,1,D$3+c_ship_m-c_credit_m),0) -> 0 | E22: =IF(AND(E$3+c_ship_m-c_credit_m>=1,E$3+c_ship_m-c_credit_m<=60),(1-p_adv)*INDEX($D$20:$BK$20,1,E$3+c_ship_m-c_credit_m),0) -> 0 | F22: =IF(AND(F$3+c_ship_m-c_credit_m>=1,F$3+c_ship_m-c_credit_m<=60),(1-p_adv)*INDEX($D$20:$BK$20,1,F$3+c_ship_m-c_credit_m),0) -> 0 | G22: =IF(AND(G$3+c_ship_m-c_credit_m>=1,G$3+c_ship_m-c_credit_m<=60),(1-p_adv)*INDEX($D$20:$BK$20,1,G$3+c_ship_m-c_credit_m),0) -> 0 | H22: =IF(AND(H$3+c_ship_m-c_credit_m>=1,H$3+c_ship_m-c_credit_m<=60),(1-p_adv)*INDEX($D$20:$BK$20,1,H$3+c_ship_m-c_credit_m),0) -> 0 | I22: =IF(AND(I$3+c_ship_m-c_credit_m>=1,I$3+c_ship_m-c_credit_m<=60),(1-p_adv)*INDEX($D$20:$BK$20,1,I$3+c_ship_m-c_credit_m),0) -> 0 | J22: =IF(AND(J$3+c_ship_m-c_credit_m>=1,J$3+c_ship_m-c_credit_m<=60),(1-p_adv)*INDEX($D$20:$BK$20,1,J$3+c_ship_m-c_credit_m),0) -> 1262.7062 | K22: =IF(AND(K$3+c_ship_m-c_credit_m>=1,K$3+c_ship_m-c_credit_m<=60),(1-p_adv)*INDEX($D$20:$BK$20,1,K$3+c_ship_m-c_credit_m),0) -> 908.86111 | ... BK22: =IF(AND(BK$3+c_ship_m-c_credit_m>=1,BK$3+c_ship_m-c_credit_m<=60),(1-p_adv)*INDEX($D$20:$BK$20,1,BK$3+c_ship_m-c_credit_m),0) -> 0
A23: PAGOS AL PROVEEDOR | D23: =D21+D22 -> 0 | E23: =E21+E22 -> 0 | F23: =F21+F22 -> 0 | G23: =G21+G22 -> 0 | H23: =H21+H22 -> 0 | I23: =I21+I22 -> 541.15982 | J23: =J21+J22 -> 1652.2182 | K23: =K21+K22 -> 1377.661 | ... BK23: =BK21+BK22 -> 0
A24: COBRANZA (incl. liquidación de inventario al cierre) | D24: =(1-p_fact_share)*IF(D$3-c_dso_m>=1,INDEX($D$15:$BK$15,1,D$3-c_dso_m),0)*(1-p_baddebt)+p_fact_share*IF(D$3-1>=1,INDEX($D$15:$BK$15,1,D$3-1),0)*(1-p_baddebt)*(1-p_fact_cost*c_dso_m)+IF(D$3=ROUND(p_stop_det,0)+1,INDEX($D$19:$BK$19,1,ROUND(p_stop_det,0))*p_inv_liq,0) -> 0 | E24: =(1-p_fact_share)*IF(E$3-c_dso_m>=1,INDEX($D$15:$BK$15,1,E$3-c_dso_m),0)*(1-p_baddebt)+p_fact_share*IF(E$3-1>=1,INDEX($D$15:$BK$15,1,E$3-1),0)*(1-p_baddebt)*(1-p_fact_cost*c_dso_m)+IF(E$3=ROUND(p_stop_det,0)+1,INDEX($D$19:$BK$19,1,ROUND(p_stop_det,0))*p_inv_liq,0) -> 0 | F24: =(1-p_fact_share)*IF(F$3-c_dso_m>=1,INDEX($D$15:$BK$15,1,F$3-c_dso_m),0)*(1-p_baddebt)+p_fact_share*IF(F$3-1>=1,INDEX($D$15:$BK$15,1,F$3-1),0)*(1-p_baddebt)*(1-p_fact_cost*c_dso_m)+IF(F$3=ROUND(p_stop_det,0)+1,INDEX($D$19:$BK$19,1,ROUND(p_stop_det,0))*p_inv_liq,0) -> 0 | G24: =(1-p_fact_share)*IF(G$3-c_dso_m>=1,INDEX($D$15:$BK$15,1,G$3-c_dso_m),0)*(1-p_baddebt)+p_fact_share*IF(G$3-1>=1,INDEX($D$15:$BK$15,1,G$3-1),0)*(1-p_baddebt)*(1-p_fact_cost*c_dso_m)+IF(G$3=ROUND(p_stop_det,0)+1,INDEX($D$19:$BK$19,1,ROUND(p_stop_det,0))*p_inv_liq,0) -> 0 | H24: =(1-p_fact_share)*IF(H$3-c_dso_m>=1,INDEX($D$15:$BK$15,1,H$3-c_dso_m),0)*(1-p_baddebt)+p_fact_share*IF(H$3-1>=1,INDEX($D$15:$BK$15,1,H$3-1),0)*(1-p_baddebt)*(1-p_fact_cost*c_dso_m)+IF(H$3=ROUND(p_stop_det,0)+1,INDEX($D$19:$BK$19,1,ROUND(p_stop_det,0))*p_inv_liq,0) -> 0 | I24: =(1-p_fact_share)*IF(I$3-c_dso_m>=1,INDEX($D$15:$BK$15,1,I$3-c_dso_m),0)*(1-p_baddebt)+p_fact_share*IF(I$3-1>=1,INDEX($D$15:$BK$15,1,I$3-1),0)*(1-p_baddebt)*(1-p_fact_cost*c_dso_m)+IF(I$3=ROUND(p_stop_det,0)+1,INDEX($D$19:$BK$19,1,ROUND(p_stop_det,0))*p_inv_liq,0) -> 0 | J24: =(1-p_fact_share)*IF(J$3-c_dso_m>=1,INDEX($D$15:$BK$15,1,J$3-c_dso_m),0)*(1-p_baddebt)+p_fact_share*IF(J$3-1>=1,INDEX($D$15:$BK$15,1,J$3-1),0)*(1-p_baddebt)*(1-p_fact_cost*c_dso_m)+IF(J$3=ROUND(p_stop_det,0)+1,INDEX($D$19:$BK$19,1,ROUND(p_stop_det,0))*p_inv_liq,0) -> 0 | K24: =(1-p_fact_share)*IF(K$3-c_dso_m>=1,INDEX($D$15:$BK$15,1,K$3-c_dso_m),0)*(1-p_baddebt)+p_fact_share*IF(K$3-1>=1,INDEX($D$15:$BK$15,1,K$3-1),0)*(1-p_baddebt)*(1-p_fact_cost*c_dso_m)+IF(K$3=ROUND(p_stop_det,0)+1,INDEX($D$19:$BK$19,1,ROUND(p_stop_det,0))*p_inv_liq,0) -> 0 | ... BK24: =(1-p_fact_share)*IF(BK$3-c_dso_m>=1,INDEX($D$15:$BK$15,1,BK$3-c_dso_m),0)*(1-p_baddebt)+p_fact_share*IF(BK$3-1>=1,INDEX($D$15:$BK$15,1,BK$3-1),0)*(1-p_baddebt)*(1-p_fact_cost*c_dso_m)+IF(BK$3=ROUND(p_stop_det,0)+1,INDEX($D$19:$BK$19,1,ROUND(p_stop_det,0))*p_inv_liq,0) -> 21651.413
A25: Gastos variables (distribución y multas) | D25: =(p_dist+p_penal)*D15 -> 0 | E25: =(p_dist+p_penal)*E15 -> 0 | F25: =(p_dist+p_penal)*F15 -> 0 | G25: =(p_dist+p_penal)*G15 -> 0 | H25: =(p_dist+p_penal)*H15 -> 0 | I25: =(p_dist+p_penal)*I15 -> 0 | J25: =(p_dist+p_penal)*J15 -> 0 | K25: =(p_dist+p_penal)*K15 -> 0 | ... BK25: =(p_dist+p_penal)*BK15 -> 979.20961
A26: Costos fijos | D26: =IF(D$3>ROUND(p_stop_det,0)+3,0,SUMPRODUCT(f_used*(D$3>=f_start))) -> 1137.9 | E26: =IF(E$3>ROUND(p_stop_det,0)+3,0,SUMPRODUCT(f_used*(E$3>=f_start))) -> 1137.9 | F26: =IF(F$3>ROUND(p_stop_det,0)+3,0,SUMPRODUCT(f_used*(F$3>=f_start))) -> 2775.9 | G26: =IF(G$3>ROUND(p_stop_det,0)+3,0,SUMPRODUCT(f_used*(G$3>=f_start))) -> 2775.9 | H26: =IF(H$3>ROUND(p_stop_det,0)+3,0,SUMPRODUCT(f_used*(H$3>=f_start))) -> 4695.9 | I26: =IF(I$3>ROUND(p_stop_det,0)+3,0,SUMPRODUCT(f_used*(I$3>=f_start))) -> 4695.9 | J26: =IF(J$3>ROUND(p_stop_det,0)+3,0,SUMPRODUCT(f_used*(J$3>=f_start))) -> 4695.9 | K26: =IF(K$3>ROUND(p_stop_det,0)+3,0,SUMPRODUCT(f_used*(K$3>=f_start))) -> 4695.9 | ... BK26: =IF(BK$3>ROUND(p_stop_det,0)+3,0,SUMPRODUCT(f_used*(BK$3>=f_start))) -> 4695.9
A27: Análisis posregistro | D27: =IF(D$3>ROUND(p_stop_det,0)+3,0,c_n_reg1*p_postreg/12*IF(D$3>=c_reg_m,1,0)+c_n_reg2*p_postreg/12*IF(D$3>=c_m2+c_rt,1,0)) -> 0 | E27: =IF(E$3>ROUND(p_stop_det,0)+3,0,c_n_reg1*p_postreg/12*IF(E$3>=c_reg_m,1,0)+c_n_reg2*p_postreg/12*IF(E$3>=c_m2+c_rt,1,0)) -> 0 | F27: =IF(F$3>ROUND(p_stop_det,0)+3,0,c_n_reg1*p_postreg/12*IF(F$3>=c_reg_m,1,0)+c_n_reg2*p_postreg/12*IF(F$3>=c_m2+c_rt,1,0)) -> 0 | G27: =IF(G$3>ROUND(p_stop_det,0)+3,0,c_n_reg1*p_postreg/12*IF(G$3>=c_reg_m,1,0)+c_n_reg2*p_postreg/12*IF(G$3>=c_m2+c_rt,1,0)) -> 0 | H27: =IF(H$3>ROUND(p_stop_det,0)+3,0,c_n_reg1*p_postreg/12*IF(H$3>=c_reg_m,1,0)+c_n_reg2*p_postreg/12*IF(H$3>=c_m2+c_rt,1,0)) -> 0 | I27: =IF(I$3>ROUND(p_stop_det,0)+3,0,c_n_reg1*p_postreg/12*IF(I$3>=c_reg_m,1,0)+c_n_reg2*p_postreg/12*IF(I$3>=c_m2+c_rt,1,0)) -> 187 | J27: =IF(J$3>ROUND(p_stop_det,0)+3,0,c_n_reg1*p_postreg/12*IF(J$3>=c_reg_m,1,0)+c_n_reg2*p_postreg/12*IF(J$3>=c_m2+c_rt,1,0)) -> 187 | K27: =IF(K$3>ROUND(p_stop_det,0)+3,0,c_n_reg1*p_postreg/12*IF(K$3>=c_reg_m,1,0)+c_n_reg2*p_postreg/12*IF(K$3>=c_m2+c_rt,1,0)) -> 187 | ... BK27: =IF(BK$3>ROUND(p_stop_det,0)+3,0,c_n_reg1*p_postreg/12*IF(BK$3>=c_reg_m,1,0)+c_n_reg2*p_postreg/12*IF(BK$3>=c_m2+c_rt,1,0)) -> 289
A28: Gastos de arranque | D28: =SUMIF(u_month,D$3,u_used) -> 6366.5 | E28: =SUMIF(u_month,E$3,u_used) -> 4280 | F28: =SUMIF(u_month,F$3,u_used) -> 421 | G28: =SUMIF(u_month,G$3,u_used) -> 535 | H28: =SUMIF(u_month,H$3,u_used) -> 0 | I28: =SUMIF(u_month,I$3,u_used) -> 0 | J28: =SUMIF(u_month,J$3,u_used) -> 0 | K28: =SUMIF(u_month,K$3,u_used) -> 0 | ... BK28: =SUMIF(u_month,BK$3,u_used) -> 0
A29: Registros sanitarios | D29: =IF(D$3=c_rs_pay_m,SUM(SKUs!$D$6:$D$24)*c_rs_unit,0)+IF(D$3=MAX(1,MIN(60,c_m2)),p_n2*c_rs_unit,0) -> 0 | E29: =IF(E$3=c_rs_pay_m,SUM(SKUs!$D$6:$D$24)*c_rs_unit,0)+IF(E$3=MAX(1,MIN(60,c_m2)),p_n2*c_rs_unit,0) -> 0 | F29: =IF(F$3=c_rs_pay_m,SUM(SKUs!$D$6:$D$24)*c_rs_unit,0)+IF(F$3=MAX(1,MIN(60,c_m2)),p_n2*c_rs_unit,0) -> 23936 | G29: =IF(G$3=c_rs_pay_m,SUM(SKUs!$D$6:$D$24)*c_rs_unit,0)+IF(G$3=MAX(1,MIN(60,c_m2)),p_n2*c_rs_unit,0) -> 0 | H29: =IF(H$3=c_rs_pay_m,SUM(SKUs!$D$6:$D$24)*c_rs_unit,0)+IF(H$3=MAX(1,MIN(60,c_m2)),p_n2*c_rs_unit,0) -> 0 | I29: =IF(I$3=c_rs_pay_m,SUM(SKUs!$D$6:$D$24)*c_rs_unit,0)+IF(I$3=MAX(1,MIN(60,c_m2)),p_n2*c_rs_unit,0) -> 0 | J29: =IF(J$3=c_rs_pay_m,SUM(SKUs!$D$6:$D$24)*c_rs_unit,0)+IF(J$3=MAX(1,MIN(60,c_m2)),p_n2*c_rs_unit,0) -> 0 | K29: =IF(K$3=c_rs_pay_m,SUM(SKUs!$D$6:$D$24)*c_rs_unit,0)+IF(K$3=MAX(1,MIN(60,c_m2)),p_n2*c_rs_unit,0) -> 0 | ... BK29: =IF(BK$3=c_rs_pay_m,SUM(SKUs!$D$6:$D$24)*c_rs_unit,0)+IF(BK$3=MAX(1,MIN(60,c_m2)),p_n2*c_rs_unit,0) -> 0
A30: Cargos anuales | D30: =IF(D$3>ROUND(p_stop_det,0)+3,0,IF(OR(D$3=1,D$3=13,D$3=25,D$3=37,D$3=49),c_annual,0)) -> 567.5 | E30: =IF(E$3>ROUND(p_stop_det,0)+3,0,IF(OR(E$3=1,E$3=13,E$3=25,E$3=37,E$3=49),c_annual,0)) -> 0 | F30: =IF(F$3>ROUND(p_stop_det,0)+3,0,IF(OR(F$3=1,F$3=13,F$3=25,F$3=37,F$3=49),c_annual,0)) -> 0 | G30: =IF(G$3>ROUND(p_stop_det,0)+3,0,IF(OR(G$3=1,G$3=13,G$3=25,G$3=37,G$3=49),c_annual,0)) -> 0 | H30: =IF(H$3>ROUND(p_stop_det,0)+3,0,IF(OR(H$3=1,H$3=13,H$3=25,H$3=37,H$3=49),c_annual,0)) -> 0 | I30: =IF(I$3>ROUND(p_stop_det,0)+3,0,IF(OR(I$3=1,I$3=13,I$3=25,I$3=37,I$3=49),c_annual,0)) -> 0 | J30: =IF(J$3>ROUND(p_stop_det,0)+3,0,IF(OR(J$3=1,J$3=13,J$3=25,J$3=37,J$3=49),c_annual,0)) -> 0 | K30: =IF(K$3>ROUND(p_stop_det,0)+3,0,IF(OR(K$3=1,K$3=13,K$3=25,K$3=37,K$3=49),c_annual,0)) -> 0 | ... BK30: =IF(BK$3>ROUND(p_stop_det,0)+3,0,IF(OR(BK$3=1,BK$3=13,BK$3=25,BK$3=37,BK$3=49),c_annual,0)) -> 0
A31: Monto afianzado (cumplimiento, sobre la cantidad máxima) | D31: =(s_Rc1*p_pwin_cen*p_bond_css*15/12+s_Rc2*p_pwin_cen*p_minsa_occ*p_bond_minsa)/p_realiz*D9*D12*D6 -> 0 | E31: =(s_Rc1*p_pwin_cen*p_bond_css*15/12+s_Rc2*p_pwin_cen*p_minsa_occ*p_bond_minsa)/p_realiz*E9*E12*E6 -> 0 | F31: =(s_Rc1*p_pwin_cen*p_bond_css*15/12+s_Rc2*p_pwin_cen*p_minsa_occ*p_bond_minsa)/p_realiz*F9*F12*F6 -> 0 | G31: =(s_Rc1*p_pwin_cen*p_bond_css*15/12+s_Rc2*p_pwin_cen*p_minsa_occ*p_bond_minsa)/p_realiz*G9*G12*G6 -> 0 | H31: =(s_Rc1*p_pwin_cen*p_bond_css*15/12+s_Rc2*p_pwin_cen*p_minsa_occ*p_bond_minsa)/p_realiz*H9*H12*H6 -> 0 | I31: =(s_Rc1*p_pwin_cen*p_bond_css*15/12+s_Rc2*p_pwin_cen*p_minsa_occ*p_bond_minsa)/p_realiz*I9*I12*I6 -> 0 | J31: =(s_Rc1*p_pwin_cen*p_bond_css*15/12+s_Rc2*p_pwin_cen*p_minsa_occ*p_bond_minsa)/p_realiz*J9*J12*J6 -> 0 | K31: =(s_Rc1*p_pwin_cen*p_bond_css*15/12+s_Rc2*p_pwin_cen*p_minsa_occ*p_bond_minsa)/p_realiz*K9*K12*K6 -> 0 | ... BK31: =(s_Rc1*p_pwin_cen*p_bond_css*15/12+s_Rc2*p_pwin_cen*p_minsa_occ*p_bond_minsa)/p_realiz*BK9*BK12*BK6 -> 69493.012
A32: Fianza de propuesta vigente (LPU) | D32: =p_bid_bond*s_bid*15/12*D12*IF(AND(D$3>=c_cen_start-c_bid_m,MOD(D$3-(c_cen_start-c_bid_m),15)<c_bid_m),1,0)*D6 -> 0 | E32: =p_bid_bond*s_bid*15/12*E12*IF(AND(E$3>=c_cen_start-c_bid_m,MOD(E$3-(c_cen_start-c_bid_m),15)<c_bid_m),1,0)*E6 -> 0 | F32: =p_bid_bond*s_bid*15/12*F12*IF(AND(F$3>=c_cen_start-c_bid_m,MOD(F$3-(c_cen_start-c_bid_m),15)<c_bid_m),1,0)*F6 -> 0 | G32: =p_bid_bond*s_bid*15/12*G12*IF(AND(G$3>=c_cen_start-c_bid_m,MOD(G$3-(c_cen_start-c_bid_m),15)<c_bid_m),1,0)*G6 -> 0 | H32: =p_bid_bond*s_bid*15/12*H12*IF(AND(H$3>=c_cen_start-c_bid_m,MOD(H$3-(c_cen_start-c_bid_m),15)<c_bid_m),1,0)*H6 -> 0 | I32: =p_bid_bond*s_bid*15/12*I12*IF(AND(I$3>=c_cen_start-c_bid_m,MOD(I$3-(c_cen_start-c_bid_m),15)<c_bid_m),1,0)*I6 -> 0 | J32: =p_bid_bond*s_bid*15/12*J12*IF(AND(J$3>=c_cen_start-c_bid_m,MOD(J$3-(c_cen_start-c_bid_m),15)<c_bid_m),1,0)*J6 -> 0 | K32: =p_bid_bond*s_bid*15/12*K12*IF(AND(K$3>=c_cen_start-c_bid_m,MOD(K$3-(c_cen_start-c_bid_m),15)<c_bid_m),1,0)*K6 -> 0 | ... BK32: =p_bid_bond*s_bid*15/12*BK12*IF(AND(BK$3>=c_cen_start-c_bid_m,MOD(BK$3-(c_cen_start-c_bid_m),15)<c_bid_m),1,0)*BK6 -> 0
A33: Colateral inmovilizado | C33: 0 | D33: =(D31+D32)*p_collat -> 0 | E33: =(E31+E32)*p_collat -> 0 | F33: =(F31+F32)*p_collat -> 0 | G33: =(G31+G32)*p_collat -> 0 | H33: =(H31+H32)*p_collat -> 0 | I33: =(I31+I32)*p_collat -> 0 | J33: =(J31+J32)*p_collat -> 0 | K33: =(K31+K32)*p_collat -> 0 | ... BK33: =(BK31+BK32)*p_collat -> 34746.506
A34: Cambio en colateral | D34: =D33-C33 -> 0 | E34: =E33-D33 -> 0 | F34: =F33-E33 -> 0 | G34: =G33-F33 -> 0 | H34: =H33-G33 -> 0 | I34: =I33-H33 -> 0 | J34: =J33-I33 -> 0 | K34: =K33-J33 -> 0 | ... BK34: =BK33-BJ33 -> -15886.913
A35: Prima de fianzas | D35: =(D31+D32)*p_bond_prem/12 -> 0 | E35: =(E31+E32)*p_bond_prem/12 -> 0 | F35: =(F31+F32)*p_bond_prem/12 -> 0 | G35: =(G31+G32)*p_bond_prem/12 -> 0 | H35: =(H31+H32)*p_bond_prem/12 -> 0 | I35: =(I31+I32)*p_bond_prem/12 -> 0 | J35: =(J31+J32)*p_bond_prem/12 -> 0 | K35: =(K31+K32)*p_bond_prem/12 -> 0 | ... BK35: =(BK31+BK32)*p_bond_prem/12 -> 92.65735
A36: Costo de factoring | D36: =p_fact_share*D15*(1-p_baddebt)*p_fact_cost*c_dso_m -> 0 | E36: =p_fact_share*E15*(1-p_baddebt)*p_fact_cost*c_dso_m -> 0 | F36: =p_fact_share*F15*(1-p_baddebt)*p_fact_cost*c_dso_m -> 0 | G36: =p_fact_share*G15*(1-p_baddebt)*p_fact_cost*c_dso_m -> 0 | H36: =p_fact_share*H15*(1-p_baddebt)*p_fact_cost*c_dso_m -> 0 | I36: =p_fact_share*I15*(1-p_baddebt)*p_fact_cost*c_dso_m -> 0 | J36: =p_fact_share*J15*(1-p_baddebt)*p_fact_cost*c_dso_m -> 0 | K36: =p_fact_share*K15*(1-p_baddebt)*p_fact_cost*c_dso_m -> 0 | ... BK36: =p_fact_share*BK15*(1-p_baddebt)*p_fact_cost*c_dso_m -> 0
A37: Pérdida de inventario por cierre | D37: =IF(D$3=ROUND(p_stop_det,0)+1,INDEX($D$19:$BK$19,1,ROUND(p_stop_det,0))*(1-p_inv_liq),0) -> 0 | E37: =IF(E$3=ROUND(p_stop_det,0)+1,INDEX($D$19:$BK$19,1,ROUND(p_stop_det,0))*(1-p_inv_liq),0) -> 0 | F37: =IF(F$3=ROUND(p_stop_det,0)+1,INDEX($D$19:$BK$19,1,ROUND(p_stop_det,0))*(1-p_inv_liq),0) -> 0 | G37: =IF(G$3=ROUND(p_stop_det,0)+1,INDEX($D$19:$BK$19,1,ROUND(p_stop_det,0))*(1-p_inv_liq),0) -> 0 | H37: =IF(H$3=ROUND(p_stop_det,0)+1,INDEX($D$19:$BK$19,1,ROUND(p_stop_det,0))*(1-p_inv_liq),0) -> 0 | I37: =IF(I$3=ROUND(p_stop_det,0)+1,INDEX($D$19:$BK$19,1,ROUND(p_stop_det,0))*(1-p_inv_liq),0) -> 0 | J37: =IF(J$3=ROUND(p_stop_det,0)+1,INDEX($D$19:$BK$19,1,ROUND(p_stop_det,0))*(1-p_inv_liq),0) -> 0 | K37: =IF(K$3=ROUND(p_stop_det,0)+1,INDEX($D$19:$BK$19,1,ROUND(p_stop_det,0))*(1-p_inv_liq),0) -> 0 | ... BK37: =IF(BK$3=ROUND(p_stop_det,0)+1,INDEX($D$19:$BK$19,1,ROUND(p_stop_det,0))*(1-p_inv_liq),0) -> 0
A38: UTILIDAD ANTES DE IMPUESTOS | D38: =D15-D18*(1+p_expiry)-D25-D15*p_baddebt-D36-D26-D27-D28-D29-D30-D35-D37 -> -8071.9 | E38: =E15-E18*(1+p_expiry)-E25-E15*p_baddebt-E36-E26-E27-E28-E29-E30-E35-E37 -> -5417.9 | F38: =F15-F18*(1+p_expiry)-F25-F15*p_baddebt-F36-F26-F27-F28-F29-F30-F35-F37 -> -27132.9 | G38: =G15-G18*(1+p_expiry)-G25-G15*p_baddebt-G36-G26-G27-G28-G29-G30-G35-G37 -> -3310.9 | H38: =H15-H18*(1+p_expiry)-H25-H15*p_baddebt-H36-H26-H27-H28-H29-H30-H35-H37 -> -4695.9 | I38: =I15-I18*(1+p_expiry)-I25-I15*p_baddebt-I36-I26-I27-I28-I29-I30-I35-I37 -> -4882.9 | J38: =J15-J18*(1+p_expiry)-J25-J15*p_baddebt-J36-J26-J27-J28-J29-J30-J35-J37 -> -4882.9 | K38: =K15-K18*(1+p_expiry)-K25-K15*p_baddebt-K36-K26-K27-K28-K29-K30-K35-K37 -> -4882.9 | ... BK38: =BK15-BK18*(1+p_expiry)-BK25-BK15*p_baddebt-BK36-BK26-BK27-BK28-BK29-BK30-BK35-BK37 -> 5952.8825
A39: Impuesto sobre la renta pagado | D39: =IF(D$3=15,Anual!$C$14,IF(D$3=27,Anual!$D$14,IF(D$3=39,Anual!$E$14,IF(D$3=51,Anual!$F$14,0)))) -> 0 | E39: =IF(E$3=15,Anual!$C$14,IF(E$3=27,Anual!$D$14,IF(E$3=39,Anual!$E$14,IF(E$3=51,Anual!$F$14,0)))) -> 0 | F39: =IF(F$3=15,Anual!$C$14,IF(F$3=27,Anual!$D$14,IF(F$3=39,Anual!$E$14,IF(F$3=51,Anual!$F$14,0)))) -> 0 | G39: =IF(G$3=15,Anual!$C$14,IF(G$3=27,Anual!$D$14,IF(G$3=39,Anual!$E$14,IF(G$3=51,Anual!$F$14,0)))) -> 0 | H39: =IF(H$3=15,Anual!$C$14,IF(H$3=27,Anual!$D$14,IF(H$3=39,Anual!$E$14,IF(H$3=51,Anual!$F$14,0)))) -> 0 | I39: =IF(I$3=15,Anual!$C$14,IF(I$3=27,Anual!$D$14,IF(I$3=39,Anual!$E$14,IF(I$3=51,Anual!$F$14,0)))) -> 0 | J39: =IF(J$3=15,Anual!$C$14,IF(J$3=27,Anual!$D$14,IF(J$3=39,Anual!$E$14,IF(J$3=51,Anual!$F$14,0)))) -> 0 | K39: =IF(K$3=15,Anual!$C$14,IF(K$3=27,Anual!$D$14,IF(K$3=39,Anual!$E$14,IF(K$3=51,Anual!$F$14,0)))) -> 0 | ... BK39: =IF(BK$3=15,Anual!$C$14,IF(BK$3=27,Anual!$D$14,IF(BK$3=39,Anual!$E$14,IF(BK$3=51,Anual!$F$14,0)))) -> 0
A40: Impuesto de aviso de operación pagado | D40: 0 | E40: 0 | F40: 0 | G40: 0 | H40: 0 | I40: 0 | J40: 0 | K40: 0 | L40: 0 | M40: 0 | N40: 0 | O40: 0 | P40: 0 | Q40: 0 | R40: =IF(R$3<=ROUND(p_stop_det,0)+3,MAX(100,p_aviso*MAX(0,SUM($D$43:$O$43)+SUM(Anual!$C$15:$C$15)-SUM($D$44:$O$44))),0) -> 989.39318 | S40: 0 | T40: 0 | U40: 0 | V40: 0 | W40: 0 | X40: 0 | Y40: 0 | Z40: 0 | AA40: 0 | AB40: 0 | AC40: 0 | AD40: =IF(AD$3<=ROUND(p_stop_det,0)+3,MAX(100,p_aviso*MAX(0,SUM($D$43:$AA$43)+SUM(Anual!$C$15:$D$15)-SUM($D$44:$AA$44))),0) -> 3553.4921 | AE40: 0 | AF40: 0 | AG40: 0 | AH40: 0 | AI40: 0 | AJ40: 0 | AK40: 0 | AL40: 0 | AM40: 0 | AN40: 0 | AO40: 0 | AP40: =IF(AP$3<=ROUND(p_stop_det,0)+3,MAX(100,p_aviso*MAX(0,SUM($D$43:$AM$43)+SUM(Anual!$C$15:$E$15)-SUM($D$44:$AM$44))),0) -> 5119.3594 | AQ40: 0 | AR40: 0 | AS40: 0 | AT40: 0 | AU40: 0 | AV40: 0 | AW40: 0 | AX40: 0 | AY40: 0 | AZ40: 0 | BA40: 0 | BB40: =IF(BB$3<=ROUND(p_stop_det,0)+3,MAX(100,p_aviso*MAX(0,SUM($D$43:$AY$43)+SUM(Anual!$C$15:$F$15)-SUM($D$44:$AY$44))),0) -> 5359.1485 | BC40: 0 | BD40: 0 | BE40: 0 | BF40: 0 | BG40: 0 | BH40: 0 | BI40: 0 | BJ40: 0 | BK40: 0
A41: Caja antes de aportes | D41: =C45+D24-D23-D25-D26-D27-D28-D29-D30-D34-D35-D39-D40 -> -8071.9 | E41: =D45+E24-E23-E25-E26-E27-E28-E29-E30-E34-E35-E39-E40 -> -2004.2 | F41: =E45+F24-F23-F25-F26-F27-F28-F29-F30-F34-F35-F39-F40 -> -23719.2 | G41: =F45+G24-G23-G25-G26-G27-G28-G29-G30-G34-G35-G39-G40 -> 5016.8 | H41: =G45+H24-H23-H25-H26-H27-H28-H29-H30-H34-H35-H39-H40 -> 3631.8 | I41: =H45+I24-I23-I25-I26-I27-I28-I29-I30-I34-I35-I39-I40 -> 8663.6402 | J41: =I45+J24-J23-J25-J26-J27-J28-J29-J30-J34-J35-J39-J40 -> 7552.5818 | K41: =J45+K24-K23-K25-K26-K27-K28-K29-K30-K34-K35-K39-K40 -> 7827.139 | ... BK41: =BJ45+BK24-BK23-BK25-BK26-BK27-BK28-BK29-BK30-BK34-BK35-BK39-BK40 -> 157695.77
A42: Caja mínima requerida | D42: =p_mincash_m*D26 -> 3413.7 | E42: =p_mincash_m*E26 -> 3413.7 | F42: =p_mincash_m*F26 -> 8327.7 | G42: =p_mincash_m*G26 -> 8327.7 | H42: =p_mincash_m*H26 -> 14087.7 | I42: =p_mincash_m*I26 -> 14087.7 | J42: =p_mincash_m*J26 -> 14087.7 | K42: =p_mincash_m*K26 -> 14087.7 | ... BK42: =p_mincash_m*BK26 -> 14087.7
A43: APORTE DE CAPITAL | D43: =MAX(0,D42-D41) -> 11485.6 | E43: =MAX(0,E42-E41) -> 5417.9 | F43: =MAX(0,F42-F41) -> 32046.9 | G43: =MAX(0,G42-G41) -> 3310.9 | H43: =MAX(0,H42-H41) -> 10455.9 | I43: =MAX(0,I42-I41) -> 5424.0598 | J43: =MAX(0,J42-J41) -> 6535.1182 | K43: =MAX(0,K42-K41) -> 6260.561 | ... BK43: =MAX(0,BK42-BK41) -> 0
A44: DIVIDENDO PAGADO | D44: 0 | E44: 0 | F44: 0 | G44: 0 | H44: 0 | I44: 0 | J44: 0 | K44: 0 | L44: 0 | M44: 0 | N44: 0 | O44: 0 | P44: 0 | Q44: 0 | R44: 0 | S44: 0 | T44: 0 | U44: 0 | V44: 0 | W44: 0 | X44: 0 | Y44: 0 | Z44: 0 | AA44: =p_payout*MAX(0,MIN(AA41+AA43-2*AA42-Anual!$D$14,SUM(Anual!$C$15:$D$15)-SUM($D$44:Z$44))) -> 0 | AB44: 0 | AC44: 0 | AD44: 0 | AE44: 0 | AF44: 0 | AG44: 0 | AH44: 0 | AI44: 0 | AJ44: 0 | AK44: 0 | AL44: 0 | AM44: =p_payout*MAX(0,MIN(AM41+AM43-2*AM42-Anual!$E$14,SUM(Anual!$C$15:$E$15)-SUM($D$44:AL$44))) -> 2836.6406 | AN44: 0 | AO44: 0 | AP44: 0 | AQ44: 0 | AR44: 0 | AS44: 0 | AT44: 0 | AU44: 0 | AV44: 0 | AW44: 0 | AX44: 0 | AY44: =p_payout*MAX(0,MIN(AY41+AY43-2*AY42-Anual!$F$14,SUM(Anual!$C$15:$F$15)-SUM($D$44:AX$44))) -> 50794.463 | AZ44: 0 | BA44: 0 | BB44: 0 | BC44: 0 | BD44: 0 | BE44: 0 | BF44: 0 | BG44: 0 | BH44: 0 | BI44: 0 | BJ44: 0 | BK44: 0
A45: CAJA AL CIERRE | C45: 0 | D45: =D41+D43-D44 -> 3413.7 | E45: =E41+E43-E44 -> 3413.7 | F45: =F41+F43-F44 -> 8327.7 | G45: =G41+G43-G44 -> 8327.7 | H45: =H41+H43-H44 -> 14087.7 | I45: =I41+I43-I44 -> 14087.7 | J45: =J41+J43-J44 -> 14087.7 | K45: =K41+K43-K44 -> 14087.7 | ... BK45: =BK41+BK43-BK44 -> 157695.77
A46: FLUJO DE LOS ACCIONISTAS (sin valor terminal) | C46: =-c_phase0 -> -2675 | D46: =-D43+D44*(1-p_divtax) -> -11485.6 | E46: =-E43+E44*(1-p_divtax) -> -5417.9 | F46: =-F43+F44*(1-p_divtax) -> -32046.9 | G46: =-G43+G44*(1-p_divtax) -> -3310.9 | H46: =-H43+H44*(1-p_divtax) -> -10455.9 | I46: =-I43+I44*(1-p_divtax) -> -5424.0598 | J46: =-J43+J44*(1-p_divtax) -> -6535.1182 | K46: =-K43+K44*(1-p_divtax) -> -6260.561 | ... BK46: =-BK43+BK44*(1-p_divtax) -> 0
A48: La columna del mes 61 solo sirve para mirar el costo del mes siguiente al fijar el inventario del mes 60.

Sheet Anual
B1: Estado de resultados e impuestos (B/.)
B3: Concepto | C3: Año 1 | D3: Año 2 | E3: Año 3 | F3: Año 4 | G3: Año 5 | H3: Total
B4: Ventas | C4: =SUM(Mensual!D15:O15) -> 6302.4278 | D4: =SUM(Mensual!P15:AA15) -> 174117.93 | E4: =SUM(Mensual!AB15:AM15) -> 265071.34 | F4: =SUM(Mensual!AN15:AY15) -> 269198.52 | G4: =SUM(Mensual!AZ15:BK15) -> 261122.56 | H4: =SUM(C4:G4) -> 975812.78
B5: Costo de ventas (incl. mermas) | C5: =-SUM(Mensual!D18:O18)*(1+p_expiry) -> -2642.9332 | D5: =-SUM(Mensual!P18:AA18)*(1+p_expiry) -> -70272.883 | E5: =-SUM(Mensual!AB18:AM18)*(1+p_expiry) -> -110151 | F5: =-SUM(Mensual!AN18:AY18)*(1+p_expiry) -> -115701.16 | G5: =-SUM(Mensual!AZ18:BK18)*(1+p_expiry) -> -115701.16 | H5: =SUM(C5:G5) -> -414469.13
B6: Gastos variables, incobrables y factoring | C6: =-(SUM(Mensual!D25:O25)+SUM(Mensual!D15:O15)*p_baddebt+SUM(Mensual!D36:O36)) -> -315.12139 | D6: =-(SUM(Mensual!P25:AA25)+SUM(Mensual!P15:AA15)*p_baddebt+SUM(Mensual!P36:AA36)) -> -8705.8966 | E6: =-(SUM(Mensual!AB25:AM25)+SUM(Mensual!AB15:AM15)*p_baddebt+SUM(Mensual!AB36:AM36)) -> -13253.567 | F6: =-(SUM(Mensual!AN25:AY25)+SUM(Mensual!AN15:AY15)*p_baddebt+SUM(Mensual!AN36:AY36)) -> -13459.926 | G6: =-(SUM(Mensual!AZ25:BK25)+SUM(Mensual!AZ15:BK15)*p_baddebt+SUM(Mensual!AZ36:BK36)) -> -13056.128 | H6: =SUM(C6:G6) -> -48790.639
B7: Costos fijos y cargos anuales | C7: =-(SUM(Mensual!D26:O26)+SUM(Mensual!D30:O30)) -> -45962.3 | D7: =-(SUM(Mensual!P26:AA26)+SUM(Mensual!P30:AA30)) -> -56918.3 | E7: =-(SUM(Mensual!AB26:AM26)+SUM(Mensual!AB30:AM30)) -> -56918.3 | F7: =-(SUM(Mensual!AN26:AY26)+SUM(Mensual!AN30:AY30)) -> -56918.3 | G7: =-(SUM(Mensual!AZ26:BK26)+SUM(Mensual!AZ30:BK30)) -> -56918.3 | H7: =SUM(C7:G7) -> -273635.5
B8: Arranque y registros sanitarios | C8: =-(SUM(Mensual!D28:O28)+SUM(Mensual!D29:O29)) -> -35538.5 | D8: =-(SUM(Mensual!P28:AA28)+SUM(Mensual!P29:AA29)) -> -13056 | E8: =-(SUM(Mensual!AB28:AM28)+SUM(Mensual!AB29:AM29)) -> 0 | F8: =-(SUM(Mensual!AN28:AY28)+SUM(Mensual!AN29:AY29)) -> 0 | G8: =-(SUM(Mensual!AZ28:BK28)+SUM(Mensual!AZ29:BK29)) -> 0 | H8: =SUM(C8:G8) -> -48594.5
B9: Fianzas, posregistro y pérdidas por cierre | C9: =-(SUM(Mensual!D35:O35)+SUM(Mensual!D27:O27)+SUM(Mensual!D37:O37)) -> -1339.659 | D9: =-(SUM(Mensual!P35:AA35)+SUM(Mensual!P27:AA27)+SUM(Mensual!P37:AA37)) -> -3409.4672 | E9: =-(SUM(Mensual!AB35:AM35)+SUM(Mensual!AB27:AM27)+SUM(Mensual!AB37:AM37)) -> -4706.9835 | F9: =-(SUM(Mensual!AN35:AY35)+SUM(Mensual!AN27:AY27)+SUM(Mensual!AN37:AY37)) -> -4706.9835 | G9: =-(SUM(Mensual!AZ35:BK35)+SUM(Mensual!AZ27:BK27)+SUM(Mensual!AZ37:BK37)) -> -4706.9835 | H9: =SUM(C9:G9) -> -18870.077
B10: Utilidad antes de impuestos | C10: =SUM(Mensual!D38:O38) -> -79496.086 | D10: =SUM(Mensual!P38:AA38) -> 21755.385 | E10: =SUM(Mensual!AB38:AM38) -> 80041.494 | F10: =SUM(Mensual!AN38:AY38) -> 78412.152 | G10: =SUM(Mensual!AZ38:BK38) -> 70739.994 | H10: =SUM(C10:G10) -> 171452.94
B11: Pérdidas acumuladas deducibles este año (20% de cada pérdida previa) | C11: =0 -> 0 | D11: =0.2*MAX(0,-C10) -> 15899.217 | E11: =0.2*MAX(0,-C10)+0.2*MAX(0,-D10) -> 15899.217 | F11: =0.2*MAX(0,-C10)+0.2*MAX(0,-D10)+0.2*MAX(0,-E10) -> 15899.217 | G11: =0.2*MAX(0,-C10)+0.2*MAX(0,-D10)+0.2*MAX(0,-E10)+0.2*MAX(0,-F10) -> 15899.217
B12: Deducción aplicada (tope 50% de la renta) | C12: =MIN(0.5*MAX(0,C10),C11) -> 0 | D12: =MIN(0.5*MAX(0,D10),D11) -> 10877.692 | E12: =MIN(0.5*MAX(0,E10),E11) -> 15899.217 | F12: =MIN(0.5*MAX(0,F10),F11) -> 15899.217 | G12: =MIN(0.5*MAX(0,G10),G11) -> 15899.217
B13: Renta gravable | C13: =MAX(0,C10)-C12 -> 0 | D13: =MAX(0,D10)-D12 -> 10877.692 | E13: =MAX(0,E10)-E12 -> 64142.277 | F13: =MAX(0,F10)-F12 -> 62512.935 | G13: =MAX(0,G10)-G12 -> 54840.777 | H13: =SUM(C13:G13) -> 192373.68
B14: Impuesto sobre la renta (o CAIR si ventas > B/.1.5 millones) | C14: =MAX(p_isr*C13,IF(C4>1500000,0.011675*C4,0)) -> 0 | D14: =MAX(p_isr*D13,IF(D4>1500000,0.011675*D4,0)) -> 2719.4231 | E14: =MAX(p_isr*E13,IF(E4>1500000,0.011675*E4,0)) -> 16035.569 | F14: =MAX(p_isr*F13,IF(F4>1500000,0.011675*F4,0)) -> 15628.234 | G14: =MAX(p_isr*G13,IF(G4>1500000,0.011675*G4,0)) -> 13710.194 | H14: =SUM(C14:G14) -> 48093.42
B15: Utilidad neta | C15: =C10-C14 -> -79496.086 | D15: =D10-D14 -> 19035.962 | E15: =E10-E14 -> 64005.925 | F15: =F10-F14 -> 62783.918 | G15: =G10-G14 -> 57029.8 | H15: =SUM(C15:G15) -> 123359.52
B16: Margen neto | C16: =IF(C4>0,C15/C4,0) -> -12.613566 | D16: =IF(D4>0,D15/D4,0) -> 0.10932798 | E16: =IF(E4>0,E15/E4,0) -> 0.24146678 | F16: =IF(F4>0,F15/F4,0) -> 0.23322535 | G16: =IF(G4>0,G15/G4,0) -> 0.21840242
B17: Memo: impuesto de aviso de operación pagado (no se deduce de la renta en el modelo) | C17: =SUM(Mensual!D40:O40) -> 0 | D17: =SUM(Mensual!P40:AA40) -> 989.39318 | E17: =SUM(Mensual!AB40:AM40) -> 3553.4921 | F17: =SUM(Mensual!AN40:AY40) -> 5119.3594 | G17: =SUM(Mensual!AZ40:BK40) -> 5359.1485 | H17: =SUM(C17:G17) -> 15021.393
B18: Punto de equilibrio (ventas anuales que cubren fijos)
B19: Costos fijos anuales a plena operación | C19: =f_total*12+c_annual+c_n_reg1*p_postreg -> 59162.3
B20: Margen bruto promedio del portafolio | C20: =IF(s_rev_exp>0,s_gp_exp/s_rev_exp,0) -> 0.6191596
B21: Gastos variables (% ventas) | C21: =p_dist+p_penal+p_baddebt+p_expiry*(1-C20) -> 0.061425212
B22: Ventas de equilibrio (B/./año) | C22: =IF(C20-C21>0,C19/(C20-C21),0) -> 106076.12
B23: Ventas esperadas de la primera ola en madurez (B/./año) | C23: =s_rev_exp -> 213455.11

Sheet Valoración
B1: Valoración y capital requerido
B2: =CONCATENATE("Escenario activo: ",Supuestos!C3,IF(p_sl=1," | tarifas SignatureLex"," | tarifas de mercado")) -> Escenario activo: Base | tarifas de mercado
B4: Capital aportado por los socios durante 60 meses | C4: =SUM(Mensual!D43:BK43) -> 255258.81
B5: Gasto de fase 0 (antes de constituir, lo pagan los socios) | C5: =c_phase0 -> 2675
B6: Dividendos pagados (antes del 10%) | C6: =SUM(Mensual!D44:BK44) -> 53631.103
B7: Caja al mes 60 | C7: =Mensual!BK45 -> 157695.77
B8: Cuentas por cobrar al mes 60 | C8: =SUMPRODUCT((m_mes>60-c_dso_m)*Mensual!$D$15:$BK$15)*(1-p_baddebt)*(1-p_fact_share)+p_fact_share*Mensual!BK15*(1-p_baddebt)*(1-p_fact_cost*c_dso_m) -> 108257.06
B9: Inventario al mes 60 | C9: =Mensual!BK19 -> 22976.689
B10: Colateral de fianzas al mes 60 | C10: =Mensual!BK33 -> 34746.506
B11: Cuentas por pagar al proveedor al mes 60 | C11: =SUMPRODUCT((m_mes>60-MAX(0,c_credit_m-c_ship_m))*Mensual!$D$20:$BK$20)*(1-p_adv) -> 0
B12: Capital de trabajo neto al mes 60 | C12: =C8+C9+C10-C11 -> 165980.26
B13: Impuesto sobre la renta y aviso de operación del año 5 por pagar | C13: =Anual!G14+IF(60<=ROUND(p_stop_det,0)+3,MAX(100,p_aviso*MAX(0,C4+SUM(Anual!C15:G15)-C6)),0) -> 20209.939
B14: Valor terminal conservador (caja + recuperación del capital de trabajo) | C14: =C7+p_recov*C12-C13 -> 286868.06
B15: Valor terminal como negocio en marcha (caja + múltiplo de la utilidad del año 5) | C15: =C7-C13+p_gc_mult*MAX(0,Anual!G15) -> 308575.23
B16: Valor terminal usado en el caso "en marcha" (el mayor) | C16: =MAX(C14,C15) -> 308575.23
B17: Valor terminal neto del impuesto de dividendos (conservador) | C17: =C14-p_divtax*MAX(0,C14-C4) -> 283707.14
B18: Valor terminal neto del impuesto de dividendos (en marcha) | C18: =C16-p_divtax*MAX(0,C16-C4) -> 303243.59
C20: 0 | D20: 1 | E20: 2 | F20: 3 | G20: 4 | H20: 5 | I20: 6 | J20: 7 | K20: 8 | L20: 9 | M20: 10 | N20: 11 | O20: 12 | P20: 13 | Q20: 14 | R20: 15 | S20: 16 | T20: 17 | U20: 18 | V20: 19 | W20: 20 | X20: 21 | Y20: 22 | Z20: 23 | AA20: 24 | AB20: 25 | AC20: 26 | AD20: 27 | AE20: 28 | AF20: 29 | AG20: 30 | AH20: 31 | AI20: 32 | AJ20: 33 | AK20: 34 | AL20: 35 | AM20: 36 | AN20: 37 | AO20: 38 | AP20: 39 | AQ20: 40 | AR20: 41 | AS20: 42 | AT20: 43 | AU20: 44 | AV20: 45 | AW20: 46 | AX20: 47 | AY20: 48 | AZ20: 49 | BA20: 50 | BB20: 51 | BC20: 52 | BD20: 53 | BE20: 54 | BF20: 55 | BG20: 56 | BH20: 57 | BI20: 58 | BJ20: 59 | BK20: 60
B21: Flujo de los accionistas, conservador (mes 0 a 60, sigue a la derecha) | C21: =Mensual!C46 -> -2675 | D21: =Mensual!D46 -> -11485.6 | E21: =Mensual!E46 -> -5417.9 | F21: =Mensual!F46 -> -32046.9 | G21: =Mensual!G46 -> -3310.9 | H21: =Mensual!H46 -> -10455.9 | I21: =Mensual!I46 -> -5424.0598 | J21: =Mensual!J46 -> -6535.1182 | ... BJ21: =Mensual!BJ46 -> 0 | BK21: =Mensual!BK46+$C$17 -> 283707.14
B22: Flujo de los accionistas, en marcha | C22: =Mensual!C46 -> -2675 | D22: =Mensual!D46 -> -11485.6 | E22: =Mensual!E46 -> -5417.9 | F22: =Mensual!F46 -> -32046.9 | G22: =Mensual!G46 -> -3310.9 | H22: =Mensual!H46 -> -10455.9 | I22: =Mensual!I46 -> -5424.0598 | J22: =Mensual!J46 -> -6535.1182 | ... BJ22: =Mensual!BJ46 -> 0 | BK22: =Mensual!BK46+$C$18 -> 303243.59
B24: VPN al 15% anual (conservador) | C24: =SUMPRODUCT($C$21:$BK$21,1/(1+0.15)^($C$20:$BK$20/12)) -> -56080.884
B25: VPN a la tasa de descuento del escenario (conservador) | C25: =SUMPRODUCT($C$21:$BK$21,1/(1+p_disc)^($C$20:$BK$20/12)) -> -107028.63
B26: VPN al 15% anual (en marcha) | C26: =SUMPRODUCT($C$22:$BK$22,1/(1+0.15)^($C$20:$BK$20/12)) -> -46367.815
B27: TIR anual (conservador) | C27: =IFERROR((1+IRR($C$21:$BK$21,0.01))^12-1,IFERROR((1+IRR($C$21:$BK$21,-0.1))^12-1,IFERROR((1+IRR($C$21:$BK$21,-0.19))^12-1,"n.d."))) -> 0.067738654
B28: TIR anual (en marcha) | C28: =IFERROR((1+IRR($C$22:$BK$22,0.01))^12-1,IFERROR((1+IRR($C$22:$BK$22,-0.1))^12-1,IFERROR((1+IRR($C$22:$BK$22,-0.19))^12-1,"n.d."))) -> 0.083484167
B29: Múltiplo del capital (lo que vuelve / lo que se pone), conservador | C29: =IF(-SUMIF($C$21:$BK$21,"<0")>0,SUMIF($C$21:$BK$21,">0")/-SUMIF($C$21:$BK$21,"<0"),0) -> 1.2870555
B30: Capital máximo acumulado (pico de necesidad de caja de los socios) | C30: =-MIN(C34:BK34) -> 257933.81
B31: Ganancia de Zywie por su margen sobre el precio de fábrica (60 meses) | C31: =SUM(Mensual!D20:BK20)*s_fob_share*p_zy_markup/(1+p_zy_markup) -> 42357.105
B33: Flujo acumulado (conservador, sin valor terminal)
B34: Flujo acumulado de los accionistas | C34: =SUM($C$21:C21)-IF(0=60,$C$17,0) -> -2675 | D34: =SUM($C$21:D21)-IF(1=60,$C$17,0) -> -14160.6 | E34: =SUM($C$21:E21)-IF(2=60,$C$17,0) -> -19578.5 | F34: =SUM($C$21:F21)-IF(3=60,$C$17,0) -> -51625.4 | G34: =SUM($C$21:G21)-IF(4=60,$C$17,0) -> -54936.3 | H34: =SUM($C$21:H21)-IF(5=60,$C$17,0) -> -65392.2 | I34: =SUM($C$21:I21)-IF(6=60,$C$17,0) -> -70816.26 | J34: =SUM($C$21:J21)-IF(7=60,$C$17,0) -> -77351.378 | K34: =SUM($C$21:K21)-IF(8=60,$C$17,0) -> -83611.939 | L34: =SUM($C$21:L21)-IF(9=60,$C$17,0) -> -90165.154 | M34: =SUM($C$21:M21)-IF(10=60,$C$17,0) -> -97011.024 | N34: =SUM($C$21:N21)-IF(11=60,$C$17,0) -> -106366.68 | O34: =SUM($C$21:O21)-IF(12=60,$C$17,0) -> -131640.74 | P34: =SUM($C$21:P21)-IF(13=60,$C$17,0) -> -143764.55 | Q34: =SUM($C$21:Q21)-IF(14=60,$C$17,0) -> -154985.57 | R34: =SUM($C$21:R21)-IF(15=60,$C$17,0) -> -180991.81 | S34: =SUM($C$21:S21)-IF(16=60,$C$17,0) -> -192024.97 | T34: =SUM($C$21:T21)-IF(17=60,$C$17,0) -> -202491.91 | U34: =SUM($C$21:U21)-IF(18=60,$C$17,0) -> -225155.48 | V34: =SUM($C$21:V21)-IF(19=60,$C$17,0) -> -234182.29 | W34: =SUM($C$21:W21)-IF(20=60,$C$17,0) -> -234182.29 | X34: =SUM($C$21:X21)-IF(21=60,$C$17,0) -> -234500.88 | Y34: =SUM($C$21:Y21)-IF(22=60,$C$17,0) -> -234500.88 | Z34: =SUM($C$21:Z21)-IF(23=60,$C$17,0) -> -234500.88 | AA34: =SUM($C$21:AA21)-IF(24=60,$C$17,0) -> -240809.73 | AB34: =SUM($C$21:AB21)-IF(25=60,$C$17,0) -> -240809.73 | AC34: =SUM($C$21:AC21)-IF(26=60,$C$17,0) -> -240809.73 | AD34: =SUM($C$21:AD21)-IF(27=60,$C$17,0) -> -257933.81 | AE34: =SUM($C$21:AE21)-IF(28=60,$C$17,0) -> -257933.81 | AF34: =SUM($C$21:AF21)-IF(29=60,$C$17,0) -> -257933.81 | AG34: =SUM($C$21:AG21)-IF(30=60,$C$17,0) -> -257933.81 | AH34: =SUM($C$21:AH21)-IF(31=60,$C$17,0) -> -257933.81 | AI34: =SUM($C$21:AI21)-IF(32=60,$C$17,0) -> -257933.81 | AJ34: =SUM($C$21:AJ21)-IF(33=60,$C$17,0) -> -257933.81 | AK34: =SUM($C$21:AK21)-IF(34=60,$C$17,0) -> -257933.81 | AL34: =SUM($C$21:AL21)-IF(35=60,$C$17,0) -> -257933.81 | AM34: =SUM($C$21:AM21)-IF(36=60,$C$17,0) -> -255380.83 | AN34: =SUM($C$21:AN21)-IF(37=60,$C$17,0) -> -255380.83 | AO34: =SUM($C$21:AO21)-IF(38=60,$C$17,0) -> -255380.83 | AP34: =SUM($C$21:AP21)-IF(39=60,$C$17,0) -> -255380.83 | AQ34: =SUM($C$21:AQ21)-IF(40=60,$C$17,0) -> -255380.83 | AR34: =SUM($C$21:AR21)-IF(41=60,$C$17,0) -> -255380.83 | AS34: =SUM($C$21:AS21)-IF(42=60,$C$17,0) -> -255380.83 | AT34: =SUM($C$21:AT21)-IF(43=60,$C$17,0) -> -255380.83 | AU34: =SUM($C$21:AU21)-IF(44=60,$C$17,0) -> -255380.83 | AV34: =SUM($C$21:AV21)-IF(45=60,$C$17,0) -> -255380.83 | AW34: =SUM($C$21:AW21)-IF(46=60,$C$17,0) -> -255380.83 | AX34: =SUM($C$21:AX21)-IF(47=60,$C$17,0) -> -255380.83 | AY34: =SUM($C$21:AY21)-IF(48=60,$C$17,0) -> -209665.82 | AZ34: =SUM($C$21:AZ21)-IF(49=60,$C$17,0) -> -209665.82 | BA34: =SUM($C$21:BA21)-IF(50=60,$C$17,0) -> -209665.82 | BB34: =SUM($C$21:BB21)-IF(51=60,$C$17,0) -> -209665.82 | BC34: =SUM($C$21:BC21)-IF(52=60,$C$17,0) -> -209665.82 | BD34: =SUM($C$21:BD21)-IF(53=60,$C$17,0) -> -209665.82 | BE34: =SUM($C$21:BE21)-IF(54=60,$C$17,0) -> -209665.82 | BF34: =SUM($C$21:BF21)-IF(55=60,$C$17,0) -> -209665.82 | BG34: =SUM($C$21:BG21)-IF(56=60,$C$17,0) -> -209665.82 | BH34: =SUM($C$21:BH21)-IF(57=60,$C$17,0) -> -209665.82 | BI34: =SUM($C$21:BI21)-IF(58=60,$C$17,0) -> -209665.82 | BJ34: =SUM($C$21:BJ21)-IF(59=60,$C$17,0) -> -209665.82 | BK34: =SUM($C$21:BK21)-IF(60=60,$C$17,0) -> -209665.82
B36: Vista de un socio (participación y aportes según el trato)
B37: Participación del socio en las utilidades | C37: =(1-p_patel_eq)*p_jaime_frac -> 0.16666667
B38: Porcentaje del capital que aporta el socio | C38: =(1-p_patel_cash)*p_jaime_frac -> 0.16666667
B39: Capital total que pondría el socio (incluye su tercio de la fase 0) | C39: =C4*C38+C5*p_jaime_frac -> 43434.802
B40: Lo que recibiría el socio (dividendos y valor terminal netos, conservador) | C40: =(C6*(1-p_divtax)+C17)*C37 -> 55329.188
B41: Resultado neto del socio en 5 años (sin descontar) | C41: =C40-C39 -> 11894.387
B42: Capital del socio como % de sus ahorros líquidos (celda C17 de la hoja Capital por socio) | C42: =C39/'Capital por socio'!C17 -> 0.72391336
B44: Reparto del valor económico entre Patel y el lado panameño (nominal, 60 meses, conservador)
B45: Valor neto para todos los accionistas (lo que vuelve menos lo que se pone) | C45: =SUM($C$21:$BK$21) -> 74041.32
B46: Patel: margen de Zywie + su parte de lo distribuido - su parte del capital | C46: =C31+p_patel_eq*SUMIF(Valoración!$D$21:$BK$21,">0")-p_patel_cash*C4 -> 80715.265
B47: Lado panameño (3 socios): su parte de lo distribuido - su parte del capital - fase 0 | C47: =(1-p_patel_eq)*SUMIF(Valoración!$D$21:$BK$21,">0")-(1-p_patel_cash)*C4-C5 -> 35683.16
B48: Porcentaje del valor total que se lleva Patel | C48: =IF(C46+C47<>0,C46/(C46+C47),0) -> 0.6934395
B49: Nota: si el valor neto total es negativo, el porcentaje no tiene interpretación útil; mire los montos.

Sheet Escenarios
B1: Resultados por escenario (valores fijos del motor en Python)
B2: Para recalcular en vivo, cambie Supuestos!B3. Estos valores sirven de referencia y de control cruzado.
B4: Indicador | C4: Pesimista | D4: Base | E4: Optimista
B5: Ventas año 1 | C5: 0 | D5: 6302 | E5: 64787
B6: Ventas año 2 | C6: 1278 | D6: 174118 | E6: 900979
B7: Ventas año 3 | C7: 13740 | D7: 265071 | E7: 1373865
B8: Ventas año 5 | C8: 14226 | D8: 261123 | E8: 1384352
B9: Utilidad neta año 1 | C9: -142950 | D9: -79496 | E9: -11073
B10: Utilidad neta año 3 | C10: -99119 | D10: 64006 | E10: 590215
B11: Utilidad neta año 5 | C11: -99621 | D11: 57030 | E11: 595416
B12: Capital aportado (60 meses) | C12: 592688 | D12: 255259 | E12: 183263
B13: Pico de necesidad de caja de los socios | C13: 591371 | D13: 257934 | E13: 184263
B14: VPN al 15% (conservador) | C14: -429943 | D14: -56081 | E14: 950535
B15: VPN al 30% (conservador) | C15: -350888 | D15: -107029 | E15: 521065
B16: VPN al 15% (en marcha) | C16: -429943 | D16: -46368 | E16: 1798446
... B21: Ganancia de Zywie por su margen | C21: 3074 | D21: 42357 | E21: 63447
B24: Qué pasa si... (cambio de un supuesto sobre la base)
B25: Cambio | C25: Capital aportado | D25: VPN 15% | E25: TIR | F25: Múltiplo | G25: Ventas año 3
B26: Base | C26: 255258.81 | D26: -56080.884 | E26: 0.067738654 | F26: 1.2870555 | G26: 265071.34
B27: Crédito del proveedor 120 días, sin anticipo | C27: 214616.6 | D27: -39630.558 | E27: 0.083192112 | F27: 1.3633793 | G27: 265071.34
B28: Precio del proveedor a libro abierto (índice 1.05) | C28: 300217.41 | D28: -43277.199 | E28: 0.094511456 | F28: 1.3917934 | G28: 319908.12
B29: Sin coordinador pagado (los socios operan) | C29: 210332.72 | D29: 4199.7749 | E29: 0.15703343 | F29: 1.7050213 | G29: 265071.34
B30: Cobro en 105 días | C30: 237747.43 | D30: -49254.878 | E30: 0.074258056 | F30: 1.3212869 | G30: 265071.34
B31: + 6 productos SNC con fabricante verificado | C31: 273951.28 | D31: -9010.1411 | E31: 0.13846125 | F31: 1.6233918 | G31: 330462.34
B32: Escala: 20 productos en la segunda ola | C32: 347411.65 | D32: -28837.648 | E32: 0.11731175 | F32: 1.4815672 | G32: 384358.28
B33: Reestructurado: crédito 120 d + índice 1.05 + coordinador 1,000 | C33: 234012.88 | D33: -2670.0608 | E33: 0.14582864 | F33: 1.6332797 | G33: 319908.12
B34: Reestructurado + SNC | C34: 240612.74 | D34: 50024.455 | E34: 0.21900907 | F34: 2.0431711 | G34: 379951.26
B35: Reestructurado + SNC + escala 20 | C35: 315396 | D35: 88602.171 | E35: 0.2496982 | F35: 2.1322542 | G35: 502589.42
B36: Base con tarifas SignatureLex | C36: 294342.26 | D36: -91651.341 | E36: 0.033383779 | F36: 1.1407598 | G36: 265071.34
B37: Reestructurado + SNC + Bueno paga registros y 180 días | C37: 170473.93 | D37: 97936.688 | E37: 0.32633779 | F37: 2.6953207 | G37: 379951.26

Sheet Monte Carlo
B1: Simulación de Monte Carlo (20,000 escenarios por estrategia)
B2: Cada escenario sortea todos los supuestos (distribución triangular pesimista-base-optimista), los registros aprobados, cada renglón centralizado ganado o perdido, fallas del socio o de la planta y las compuertas de decisión.
B4: Estrategia | C4: VPN 15% promedio | D4: Prob. de perder dinero | E4: Prob. de perder más que la fase 0 | F4: Múltiplo mediano | G4: Múltiplo p90 | H4: Capital pico mediano* | I4: Capital pico p90*
B5: S.A. propia como la propone Patel, sin compuertas | C5: -157705.46 | D5: 0.774 | E5: 0.7691 | F5: 0.62044061 | G5: 1.2779615 | H5: 342691.52 | I5: 486499.4
B6: S.A. propia, con fase 0 y compuerta operativa | C6: -113639.31 | D6: 0.80605 | E6: 0.59495 | F6: 0.42359425 | G6: 1.2407906 | H6: 323190.64 | I6: 485879.99
B7: + crédito del proveedor y precio a libro abierto | C7: -108804.93 | D7: 0.71485 | E7: 0.58575 | F7: 0.64179391 | G7: 1.4326721 | H7: 314543.41 | I7: 462634.41
B8: + 6 productos SNC con fabricante verificado | C8: -81830.322 | D8: 0.50895 | E8: 0.37855 | F8: 0.98789044 | G8: 1.7175347 | H8: 326636.87 | I8: 454663.26
B9: + Bueno paga registros y da 180 días de crédito | C9: -31514.933 | D9: 0.4147 | E9: 0.285 | F9: 1.1779295 | G9: 2.1324354 | H9: 247001.9 | I9: 359158.01
B10: + sin coordinador pagado (un socio opera) | C10: 18115.294 | D10: 0.3094 | E10: 0.18365 | F10: 1.6176947 | G10: 2.8021278 | H10: 191912.08 | I10: 301711.21
B11: Registros propios y venta por un distribuidor establecido | C11: -24885.093 | D11: 0.7005 | E11: 0.4874 | F11: 0.54761106 | G11: 1.7000747 | H11: 82085.548 | I11: 97382.503
B12: * Máximo acumulado que aportan los socios, en los escenarios que pasan la fase 0. La probabilidad de perder y el múltiplo incluyen los casos que se detienen en la fase 0 (pierden solo esa fase).
B13: Percentiles del VPN al 15% (B/.)
B14: Estrategia | C14: p5 | D14: p10 | E14: p25 | F14: p50 | G14: p75 | H14: p90 | I14: p95
B15: S.A. propia como la propone Patel, sin compuertas | C15: -260854.91 | D15: -239042.27 | E15: -203725.88 | F15: -166254.97 | G15: -120558.28 | H15: -64887.409 | I15: -25910.373
B16: S.A. propia, con fase 0 y compuerta operativa | C16: -236022.28 | D16: -209989.9 | E16: -167571.57 | F16: -134545.08 | G16: -22584.82 | H16: -2705.7924 | I16: -1940.4708
B17: + crédito del proveedor y precio a libro abierto | C17: -225342.53 | D17: -199115.5 | E17: -158851.88 | F17: -128396.18 | G17: -47589.084 | H17: -2631.6978 | I17: 11540.308
B18: + 6 productos SNC con fabricante verificado | C18: -212782.81 | D18: -187143.19 | E18: -147154.53 | F18: -88280.468 | G18: -5044.9244 | H18: 16155.553 | I18: 58999.784
B19: + Bueno paga registros y da 180 días de crédito | C19: -153415.85 | D19: -129871.8 | E19: -93412.185 | F19: -29624.481 | G19: 6617.1307 | H19: 74617.76 | I19: 116071.88
B20: + sin coordinador pagado (un socio opera) | C20: -104329.01 | D20: -84488.685 | E20: -36605.85 | F20: 1437.2372 | G20: 66878.555 | H20: 131752.83 | I20: 173453.15
B21: Registros propios y venta por un distribuidor establecido | C21: -77300.45 | D21: -70364.922 | E21: -55079.35 | F21: -25477.26 | G21: -2695.8953 | H21: 17404.88 | I21: 38841.842
B23: Lo que arriesga un socio (1/3 de la fase 0; 1/6 del capital posterior y de las utilidades en la S.A.; 1/3 en la opción de registros)
B24: Estrategia | C24: Capital promedio (todos los escenarios) | D24: Capital promedio si el trato sigue | E24: Capital p90 si sigue | F24: Resultado neto promedio | G24: Prob. de que pierda | H24: Prob. de perder más que la fase 0 | I24: Kelly vs depósito 4%
B25: S.A. propia como la propone Patel, sin compuertas | C25: 58713.377 | D25: 58713.377 | E25: 81629.383 | F25: -15802.392 | G25: 0.78 | H25: 0.7691 | I25: 0
B26: S.A. propia, con fase 0 y compuerta operativa | C26: 43425.805 | D26: 54489.814 | E26: 81551.989 | F26: -9936.304 | G26: 0.81085 | H26: 0.59495 | I26: 0
B27: + crédito del proveedor y precio a libro abierto | C27: 46718.935 | D27: 53131.096 | E27: 77754.065 | F27: -6454.209 | G27: 0.71955 | H27: 0.58575 | I27: 0
B28: + 6 productos SNC con fabricante verificado | C28: 49255.811 | D28: 56024.596 | E28: 76402.714 | F28: 4920.9765 | G28: 0.51555 | H28: 0.37855 | I28: 0
B29: + Bueno paga registros y da 180 días de crédito | C29: 37899.399 | D29: 43071.745 | E29: 60645.019 | F29: 12307.642 | G29: 0.4206 | H29: 0.285 | I29: 28624.495
B30: + sin coordinador pagado (un socio opera) | C30: 30429.919 | D30: 34552.235 | E30: 51405.83 | F30: 23005.235 | G30: 0.31205 | H30: 0.18365 | I30: 25330.236
B31: + Patel aporta 70% del efectivo (sigue 50/50 en acciones) | C31: 23180.537 | D31: 26283.764 | E31: 36805.422 | F31: 27026.504 | G31: 0.29735 | H31: 0.1675 | I31: 29022.312
B32: + Patel aporta 80% del efectivo (sigue 50/50 en acciones) | C32: 15821.106 | D32: 17889.774 | E32: 24919.699 | F32: 34385.935 | G32: 0.25555 | H32: 0.1246 | I32: 29513.595
B33: Registros propios y venta por un distribuidor establecido | C33: 22296.842 | D33: 27594.31 | E33: 32460.834 | F33: -2362.1177 | G33: 0.7005 | H33: 0.4874 | I33: 0
B34: Capital de la opción de registros = un tercio del máximo acumulado (no hay caja común). Kelly: monto esperado que maximiza el crecimiento del patrimonio de B/.100,000; cuando el óptimo cae en el límite de no quebrar en el peor escenario, el monto es ese límite.
B36: Supuestos de riesgo de la simulación
B37: Planta con problemas de BPM: 15% de probabilidad; si la fase 0 no lo detecta (detecta 80%), provoca una falla de calidad entre los meses 12 y 36, se ejecuta la fianza y se pierde el inventario.
B38: Ruptura con el proveedor por otras causas: 4% anual desde el mes 6, con ejecución de fianzas.
B39: Fase 0: se descarta el trato si se detecta el problema de planta o si el índice de precio del proveedor supera 1.6.
B40: Compuerta operativa: 9 meses después de la primera venta, si las ventas anualizadas (más contratos centralizados adjudicados) no llegan a B/.90,000, se cierra y no se hace la segunda ola. Con la rampa base de 12 meses equivale a unos B/.108,000 en madurez, algo más que el equilibrio de B/.106,076.
B41: Cierres por compuerta: por etapas, 21% en la fase 0 y 17% en la operativa; en las versiones con los productos del sistema nervioso, 12% y 4.5%.
B42: Con el tope de precio de 1.1 veces de la compuerta 0 del plan (en vez de 1.6) en la versión con Bueno financiando, cuyo precio a libro abierto va de 0.95 a 1.30 veces la referencia, 52% de los escenarios se detiene en la fase 0, la probabilidad de perder más que la fase 0 queda en 15% y el VPN esperado en B/.-16,622.
B43: Correlaciones: participación descentralizada y probabilidad de ganar centralizado (0.6); mercado débil y mayor caída de precios (0.4).

Sheet Sensibilidad
B1: Sensibilidad del VPN al 15% (un supuesto a la vez, el resto en la base)
B2: VPN base: B/.-56,081. Capital base: B/.255,259.
B4: Supuesto | C4: Valor pesimista | D4: Valor optimista | E4: VPN pesimista | F4: VPN optimista | G4: Rango
B5: Costos fijos mensuales con cargas laborales e ITBMS (bloque, B/. al mes) | C5: 8400 | D5: 2655 | E5: -181294.4 | F5: 10360.55 | G5: =F5-E5 -> 191654.95
B6: Probabilidad de ganar un renglón centralizado ofertado | C6: 0.15 | D6: 0.45 | E6: -100412.62 | F6: -10433.66 | G6: =F6-E6 -> 89978.958
B7: Participación madura en compras descentralizadas (valor) | C7: 0.1 | D7: 0.32 | E7: -92199.17 | F7: -24199.993 | G7: =F7-E7 -> 67999.177
B8: Caída anual de precios a partir del año 2 | C8: 0.06 | D8: 0 | E8: -82692.572 | F8: -26823.874 | G8: =F8-E8 -> 55868.698
B9: Índice de precio del proveedor vs referencia FOB India | C9: 1.8 | D9: 1 | E9: -89615.384 | F9: -34923.56 | G9: =F9-E9 -> 54691.824
B10: Cantidad realmente comprada vs máxima del contrato | C10: 0.55 | D10: 0.9 | E10: -84092.863 | F10: -33565.781 | G10: =F10-E10 -> 50527.082
B11: Probabilidad de que MINSA haga su compra centralizada en el año | C11: 0.3 | D11: 0.7 | E11: -78450.111 | F11: -32273.369 | G11: =F11-E11 -> 46176.742
B12: Registros aprobados / registros presentados | C12: 0.7 | D12: 0.95 | E12: -81419.217 | F12: -37701.18 | G12: =F12-E12 -> 43718.038
B13: Factor de mercado (demanda futura vs datos 2025-26) | C13: 0.75 | D13: 1 | E13: -81188.171 | F13: -37872.33 | G13: =F13-E13 -> 43315.842
B14: Mes del primer contrato centralizado (LPU CSS / subasta MINSA) | C14: 27 | D14: 12 | E14: -87328.472 | F14: -44781.825 | G14: =F14-E14 -> 42546.648
B15: Productos de la segunda ola (sin equivalencia terapéutica, fabricante verificado) | C15: 0 | D15: 12 | E15: -76181.192 | F15: -37940.574 | G15: =F15-E15 -> 38240.617
B16: Tarifas legales SignatureLex vs mercado | C16: SignatureLex | D16: mercado | E16: -91651.341 | F16: -56080.884 | G16: =F16-E16 -> 35570.457
B17: Colateral en efectivo exigido por la aseguradora (% de la fianza) | C17: 1 | D17: 0.25 | E17: -74822.059 | F17: -46710.296 | G17: =F17-E17 -> 28111.763
B18: Precio de oferta descentralizado vs mediana actual | C18: 0.8 | D18: 0.95 | E18: -73648.629 | F18: -46805.484 | G18: =F18-E18 -> 26843.145
B19: Días de cobro: entrega hasta cobro | C19: 240 | D19: 105 | E19: -75829.465 | F19: -49254.878 | G19: =F19-E19 -> 26574.587
B20: Mermas y vencimientos (% del costo comprado) | C20: 0.08 | D20: 0.015 | E20: -65553.651 | F20: -53150.651 | G20: =F20-E20 -> 12402.999
B21: Meses para llegar a la participación madura en compras descentralizadas | C21: 18 | D21: 9 | E21: -63551.009 | F21: -51745.186 | G21: =F21-E21 -> 11805.823
B22: Crédito del proveedor desde el embarque | C22: 0 | D22: 120 | E22: -56080.884 | F22: -45320.061 | G22: =F22-E22 -> 10760.823
B23: Tiempo de reposición: orden al proveedor hasta stock en Panamá | C23: 120 | D23: 75 | E23: -60262.485 | F23: -56080.884 | G23: =F23-E23 -> 4181.6013
B24: Anticipo al proveedor al colocar la orden | C24: 1 | D24: 0 | E24: -58865.676 | F24: -54901.33 | G24: =F24-E24 -> 3964.3458
B25: Mes en que salen los registros sanitarios (desde la constitución) | C25: 9 | D25: 5 | E25: -58589.956 | F25: -55013.458 | G25: =F25-E25 -> 3576.498

Sheet Trato
B1: Estructuras de trato comparadas
B2: Efecto del margen de Zywie sobre el reparto del valor (caso base, mismo método que Valoración!C44:C48: lo distribuido menos el capital aportado).
B4: Margen de Zywie sobre fábrica | C4: Ganancia de Zywie (60 m) | D4: Valor para Patel | E4: Valor para el lado panameño | F4: Parte de Patel en el total
B5: 0 | C5: 0 | D5: 38358.16 | E5: 35683.16 | F5: 0.51806424
B6: 0.05 | C6: 15463.705 | D6: 53821.865 | E6: 35683.16 | F6: 0.60132786
B7: 0.1 | C7: 29521.619 | D7: 67879.779 | E7: 35683.16 | F7: 0.65544469
B8: 0.15 | C8: 42357.105 | D8: 80715.265 | E8: 35683.16 | F8: 0.6934395
B9: 0.25 | C9: 64947.561 | D9: 103305.72 | E9: 35683.16 | F9: 0.74326608
B10: 0.4 | C10: 92782.23 | D10: 131140.39 | E10: 35683.16 | F10: 0.78610238
B12: Lectura: con 50/50 en acciones y capital y sin margen de Zywie, Patel recibe la mitad. Cada punto de margen de Zywie traslada valor del lado panameño al indio, aunque el capital se divida 50/50.
B14: Opción de registros propios y distribuidor establecido (participación del distribuidor en la utilidad bruta)
B15: Escenario y regalía | C15: Capital pico | D15: VPN 15% | E15: TIR | F15: Múltiplo
B16: Pesimista, regalía 20% de la utilidad bruta | C16: 141445.03 | D16: -115475.92 | E16: n.d. | F16: 0
B17: Pesimista, regalía 30% de la utilidad bruta | C17: 139377.67 | D17: -114002.04 | E17: -0.99999922 | F17: 0.003609376
B18: Pesimista, regalía 40% de la utilidad bruta | C18: 137310.3 | D18: -112528.15 | E18: -0.99966401 | F18: 0.0080970747
B19: Base, regalía 20% de la utilidad bruta | C19: 75339.379 | D19: -35826.713 | E19: -0.095296001 | F19: 0.75490727
B20: Base, regalía 30% de la utilidad bruta | C20: 74247.283 | D20: -4347.2377 | E20: 0.12375904 | F20: 1.352812
B21: Base, regalía 40% de la utilidad bruta | C21: 73254.652 | D21: 26863.444 | E21: 0.29846694 | F21: 1.894594
B22: Optimista, regalía 20% de la utilidad bruta | C22: 66394.095 | D22: 274377.84 | E22: 1.3906692 | F22: 4.698042
B23: Optimista, regalía 30% de la utilidad bruta | C23: 65249.892 | D23: 453543.87 | E23: 1.9779584 | F23: 5.7626792
B24: Optimista, regalía 40% de la utilidad bruta | C24: 64105.689 | D24: 632646.72 | E24: 2.499708 | F24: 6.4667453

Sheet Capital por socio
B1: Cuánto capital tiene sentido que arriesgue cada socio
B2: Criterio de Kelly sobre la distribución simulada (20,000 escenarios) con un patrimonio líquido de referencia de B/.100,000: monto esperado que maximiza el crecimiento del patrimonio. Si el trato se detiene en la fase 0, cada socio solo pierde su parte de esa fase.
B4: Estrategia | C4: Capital promedio por socio (un tercio del lado panameño) si el trato sigue | D4: Resultado neto promedio | E4: Kelly vs depósito al 4%/año | F4: Kelly vs alternativa al 15%/año
B5: S.A. como la propone Patel | C5: 58713.377 | D5: -15802.392 | E5: 0 | F5: 0
B6: S.A. por etapas, reestructurada + SNC | C6: 56024.596 | D6: 4920.9765 | E6: 0 | F6: 0
B7: S.A. con Bueno financiando registros y crédito | C7: 43071.745 | D7: 12307.642 | E7: 28624.495 | F7: 0
B8: Lo anterior, sin coordinador pagado | C8: 34552.235 | D8: 23005.235 | E8: 25330.236 | F8: 0
B9: Bueno financiando, con tasa de victoria de 17% y precio de 1.25 veces | C9: 36362.752 | D9: -1857.8637 | E9: 0 | F9: 0
B10: Bueno financiando, con tope de precio de 1.1 veces en la fase 0 | C10: 43566.192 | D10: 6943.1655 | E10: 16751.88 | F10: 0
B11: Bueno financiando, Patel aporta 70% del efectivo (50/50 en acciones) | C11: 26283.764 | D11: 27026.504 | E11: 29022.312 | F11: 26195.589
B12: Registros propios + distribuidor (un tercio por socio) | C12: 27594.31 | D12: -2362.1177 | E12: 0 | F12: 0
B13: Kelly va de todo a nada según los supuestos. Con Bueno financiando y capital 50/50 cae en el límite de no quebrar en el peor escenario simulado; con el tope de precio de 1.1 veces, o frente a 15% si Patel aporta 70% del efectivo, es un óptimo interior. El tope de 15% de los ahorros es una decisión de prudencia, no un resultado del modelo.
B16: Calculadora en vivo
B17: Ahorros líquidos del socio (B/.): ejemplo, cambie este valor | C17: 60000
B18: Reserva para otros compromisos (B/.): ejemplo, cambie este valor | C18: 10000
B19: Tope recomendado para esta inversión (% de ahorros) | C19: 0.15
B20: Tope en balboas | C20: =MIN(C17*C19,C17-C18) -> 9000
B21: Capital que le pediría el escenario activo (Valoración!C39) | C21: =Valoración!C39 -> 43434.802
B22: ¿Cabe dentro del tope? | C22: =IF(C21<=C20,"Sí","No: hay que cambiar el trato o no entrar") -> No: hay que cambiar el trato o no entrar

Sheet Operación
B1: Operación: volumen físico, embarques y vida útil
B3: Producto (primera ola, madurez base) | C3: Unidades/año | D3: Ventas/año | E3: m³/año | F3: Costo/año | G3: B/. por m³
B4: PCT500 | C4: 2846424.2 | D4: 51235.636 | E4: 22.771394 | F4: 21689.753 | G4: 952.5
B5: PCTSYR | C5: 64756.187 | D5: 39362.538 | E5: 35.619465 | F5: 24997.507 | G5: 701.79345
B6: AMCTAB | C6: 29601.627 | D6: 5673.3564 | E6: 0.23681302 | F6: 3419.728 | G6: 14440.625
B7: AMCSUS | C7: 1159.7553 | D7: 4362.9994 | E7: 0.75406717 | F7: 1901.1289 | G7: 2521.1665
B8: CRO1G | C8: 20474.368 | D8: 11337.978 | E8: 1.2285112 | F8: 5750.6358 | G8: 4680.9794
B9: CTX1G | C9: 58921.673 | D9: 18547.103 | E9: 3.5354418 | F9: 9571.5312 | G9: 2707.3084
B10: ALBSUS | C10: 21712.922 | D10: 37687.361 | E10: 2.8227928 | F10: 3118.627 | G10: 1104.802
B11: MBZ100 | C11: 50472.929 | D11: 6412.3097 | E11: 0.25236465 | F11: 605.67515 | G11: 2400
B12: NYSSUS | C12: 4436.0495 | D12: 13662.733 | E12: 0.8872099 | F12: 2590.786 | G12: 2920.15
B13: HCTCRM | C13: 19545.509 | D13: 10885.093 | E13: 3.2253315 | F13: 5066.7823 | G13: 1570.9338
B14: MOMCRM | C14: 14615.046 | D14: 14288.004 | E14: 2.4117237 | F14: 2580.1767 | G14: 1069.8475
B15: Total | E15: =SUM(E4:E14) -> 73.745114 | F15: =SUM(F4:F14) -> 81292.331
B17: Lote económico de embarque (EOQ)
B18: Costo fijo por embarque (corredor, terminal, acarreo, documentos) | C18: 1000
B19: Costo de capital anual | C19: 0.15
B20: Almacenaje 3PL por m³ al mes | C20: 16
B21: Riesgo de merma anual sobre el valor | C21: 0.03
B22: Valor por m³ del portafolio | C22: =F15/E15 -> 1102.3419
B23: Costo de mantener 1 m³ un año | C23: =C19*C22+12*C20+C21*C22 -> 390.42155
B24: Lote económico (m³ por embarque) | C24: =SQRT(2*E15*C18/C23) -> 19.436351
B25: Embarques por año | C25: =E15/C24 -> 3.7941851
B27: Presupuesto de vida útil (regla de 18 meses al entregar)
B28: Vida útil aprobada del producto (meses) | C28: 24
B29: Vida útil mínima exigida al entregar (pliegos) | C29: 18
B30: Liberación en fábrica y despacho (meses) | C30: 1
B31: Tránsito y aduana (meses) | C31: =p_ship_m -> 2
B32: Pedido a entrega en hospital (meses) | C32: 0.25
B33: Tiempo máximo que puede pasar en bodega (meses) | C33: =C28-C29-C30-C31-C32 -> 2.75
B35: Con 24 meses de vida útil solo caben 2.75 meses en bodega: reposición mensual y poco inventario. Con 36 meses caben casi 15 meses: embarques trimestrales en contenedor.

Sheet Fuentes
B1: Fuentes principales
B3: Fuente | C3: Enlace
B4: PanamaCompra: LPU 01-2026 CSS (348 renglones, ofertas y adjudicación) | C4: https://apisv3.panamacompra.gob.pa/documentos-actos-publico/cuadroPropuesta/12/procesoVistaCuadroPropuesta/712894
B5: PanamaCompra: LPU 11-2026 CSS | C5: https://apisv3.panamacompra.gob.pa/documentos-actos-publico/cuadroPropuesta/12/procesoVistaCuadroPropuesta/712187
B6: Pliego LPU 01-2026 (pago a 90 días, 18 meses de vida útil, fianza de cumplimiento 30%) | C6: https://apisv3.panamacompra.gob.pa/procesos-contratacion-archivos/v2/download-file-2325E044-04B2-F011-80EA-0017A477FC74-ZA-101-1AZ-8120731-ZA-101-1AZ-8120731
B7: Pliego subasta en reversa MINSA 2026 (fianza 20%) | C7: https://apisv3.panamacompra.gob.pa/procesos-contratacion-archivos/v2/download-file-41E2472E-8233-F111-80EA-0017A477FC64-ZA-101-1AZ-9715601-ZA-101-1AZ-9715601
B8: Compra conjunta 2024, pliego (fianza 15%, 70% de compra garantizada) | C8: https://www.panamacompra.gob.pa/includes/veranexo.aspx?idattach=Pjc6Ojg4Njo=
B9: ANTAI: reportes mensuales de contrataciones (CSS, MINSA, patronatos) | C9: https://monitoreo.antai.gob.pa/
B10: Decreto Ejecutivo 27 de 2024 (tasas, licencias, registros, compras) | C10: https://www.minsa.gob.pa/sites/default/files/general/decreto_ejecutivo_27_de_10_de_mayo_de_2024.pdf
B11: Ley 419 de 2024 | C11: https://dnfd.minsa.gob.pa/sites/default/files/2025-08/Ley%20419%20de%201%20de%20febrero%20de%202024.pdf
B12: Resolución 985 de 2025 (173 principios activos con equivalencia terapéutica) | C12: https://www.minsa.gob.pa/sites/default/files/general/resolucion_985_go30317_08072025.pdf
B13: Resolución 181 de 2025 (BPA) | C13: https://dnfd.minsa.gob.pa/sites/default/files/2026-02/Resolucion%20181%20de%2014%20de%20agosto%20de%202025%20procedimiento%20de%20BPA.pdf
B14: DGI: Informe 930 de precios de transferencia (art. 762-I del Código Fiscal) | C14: https://dgi.mef.gob.pa/Internacional/I930.php
... B24: Banco General: tarifas de garantías (fianzas) 2026 | C24: https://www.bgeneral.com/
