Workbook
Name p_sc: Supuestos!$B$3
Name p_sl: Supuestos!$B$4
Name p_reg_m: Supuestos!$G$7
Name p_lead_days: Supuestos!$G$8
Name p_ship_m: Supuestos!$G$9
Name p_ramp_m: Supuestos!$G$10
Name p_cen_start: Supuestos!$G$11
Name p_mkt: Supuestos!$G$12
Name p_share_dec: Supuestos!$G$13
Name p_pwin_cen: Supuestos!$G$14
Name p_realiz: Supuestos!$G$15
Name p_realiz_minsa: Supuestos!$G$16
Name p_minsa_occ: Supuestos!$G$17
Name p_cc_w: Supuestos!$G$18
Name p_pf_dec: Supuestos!$G$19
Name p_pf_cen: Supuestos!$G$20
Name p_erosion: Supuestos!$G$21
Name p_gm_dec: Supuestos!$G$22
Name p_gm_cen: Supuestos!$G$23
Name p_sup_idx: Supuestos!$G$24
Name p_pack: Supuestos!$G$25
Name p_log_mult: Supuestos!$G$26
Name p_dist: Supuestos!$G$27
Name p_penal: Supuestos!$G$28
Name p_expiry: Supuestos!$G$29
Name p_baddebt: Supuestos!$G$30
Name p_dso_days: Supuestos!$G$31
Name p_cover_m: Supuestos!$G$32
Name p_cen_stock_m: Supuestos!$G$33
Name p_adv: Supuestos!$G$34
Name p_credit_days: Supuestos!$G$35
Name p_bond_css: Supuestos!$G$36
Name p_bond_minsa: Supuestos!$G$37
Name p_collat: Supuestos!$G$38
Name p_bond_prem: Supuestos!$G$39
Name p_bid_bond: Supuestos!$G$40
Name p_bid_m: Supuestos!$G$41
Name p_mincash_m: Supuestos!$G$42
Name p_rs_off: Supuestos!$G$43
Name p_rs_iea: Supuestos!$G$44
Name p_rs_law: Supuestos!$G$45
Name p_rs_smp: Supuestos!$G$46
Name p_rs_trad: Supuestos!$G$47
Name p_rs_succ: Supuestos!$G$48
Name p_postreg: Supuestos!$G$49
Name p_n2: Supuestos!$G$50
Name p_m2: Supuestos!$G$51
Name p_rel2: Supuestos!$G$52
Name p_fact_share: Supuestos!$G$53
Name p_fact_cost: Supuestos!$G$54
Name p_stop_det: Supuestos!$G$55
Name p_inv_liq: Supuestos!$G$56
Name p_isr: Supuestos!$G$57
Name p_divtax: Supuestos!$G$58
Name p_aviso: Supuestos!$G$59
Name p_oncost: Supuestos!$G$60
Name p_itbms_srv: Supuestos!$G$61
Name p_payout: Supuestos!$G$62
Name p_disc: Supuestos!$G$63
Name p_recov: Supuestos!$G$64

Sheet Léeme
A1: Modelo financiero: distribuidora de medicamentos para compras públicas en Panamá
A2: Versión auditada del 9 de octubre de 2026. Cifras en balboas (B/. = US$). Mes 1 del modelo = enero de 2027.
A4: Cómo usarlo
A5: 1. Elija el escenario en Supuestos!B3 (1 = pesimista, 2 = base, 3 = optimista). Todo el modelo se recalcula.
A6: 2. Cambie cualquier valor azul de las columnas D, E o F de Supuestos, o la columna «Incluir» de SKUs, para probar otra hipótesis.
A7: 3. Supuestos!B4 = 1 aplica las tarifas de la propuesta de SignatureLex en lugar de las de mercado.
A8: 4. Resultados vivos: Valoración (VPN, TIR, múltiplo, capital), Anual (estado de resultados e impuestos), Mensual (flujo de caja).
A9: 5. Las hojas Escenarios, Simulación y Sensibilidad son resultados fijos del motor en Python; no cambian al editar supuestos.
A11: Convenciones
A12: Texto azul = dato de entrada editable. Negro = fórmula. Verde = vínculo a otra hoja. Relleno amarillo = supuestos clave.
A13: En la columna Fuente: F = dato verificado en fuente abierta; R = referencia indirecta; E = estimación propia pendiente de cotización.
A15: Lógica del modelo (mes a mes, 60 meses desde la constitución de la S.A.)
... A31: El capital del caso base es un valor esperado sin fallas; para dimensionar el capital use los percentiles de la hoja Simulación.

Sheet Supuestos
A1: Supuestos
A3: Escenario | B3: 2 | C3: =CHOOSE($B$3,"Pesimista","Base","Optimista")
A4: SignatureLex | B4: 0 | C4: Usar tarifas de la propuesta de SignatureLex (1) o de mercado (0)
A6: Clave | B6: Parámetro | C6: Unidad | D6: Pesimista | E6: Base | F6: Optimista | G6: Usado | H6: Fuente o base
A7: reg_m | B7: Mes en que salen los registros sanitarios (presentados en el mes 3) | C7: mes | D7: 12 | E7: 9 | F7: 7 | G7: =CHOOSE(p_sc,D7,E7,F7) | H7: F: Ley 419 arts. 41 y 74 (20 días hábiles de la DNFD y 60 del laboratorio, unos 4 meses); E: base con 2 meses de observaciones, pesimista con subsanación y rezago
A8: lead_days | B8: Tiempo de reposición: orden al proveedor hasta stock en Panamá | C8: días | D8: 120 | E8: 90 | F8: 75 | G8: =CHOOSE(p_sc,D8,E8,F8) | H8: E: producción, flete marítimo con transbordo y aduana; se confirma con la fábrica y el agente de carga
A9: ship_m | B9: Meses entre embarque y stock disponible | C9: meses | D9: 2 | E9: 2 | F9: 2 | G9: =CHOOSE(p_sc,D9,E9,F9) | H9: E: tránsito con transbordo y desaduanaje
A10: ramp_m | B10: Meses para llegar a la participación madura en compras descentralizadas | C10: meses | D10: 18 | E10: 12 | F10: 9 | G10: =CHOOSE(p_sc,D10,E10,F10) | H10: E: curva de aprendizaje; los nuevos son descalificados 57% de las veces frente a 36% de los establecidos (OCDS MINSA 2021-2024)
A11: cen_start | B11: Mes en que podría arrancar el primer contrato centralizado (calendario de la LPU) | C11: mes | D11: 27 | E11: 20 | F11: 13 | G11: =CHOOSE(p_sc,D11,E11,F11) | H11: F: la LPU 01-2026 vence el 11-may-2027 y la siguiente se licitaría entre dic-2026 y feb-2027, antes de tener registros; la que sigue arrancaría hacia ago-2028 (mes 20). Optimista: la CSS prorroga y licita a inicios de 2028; pesimista: el calendario se corre 7 meses
A12: mkt | B12: Factor de mercado (demanda futura frente a 2025-2026) | C12: x | D12: 0.75 | E12: 0.9 | F12: 1 | G12: =CHOOSE(p_sc,D12,E12,F12) | H12: F: presupuesto de medicamentos de la CSS 2027 de B/.230.3 millones (-28.6%), en trámite; la CSS gastó en 2026 el 64% de lo presupuestado
A13: share_dec | B13: Participación madura en compras descentralizadas (valor) | C13: % | D13: 0.1 | E13: 0.22 | F13: 0.32 | G13: =CHOOSE(p_sc,D13,E13,F13) | H13: E: los nuevos ganan 36.6% de sus ofertas con precio (OCDS MINSA 2021-2024), ofertando en parte de los actos
A14: pwin_cen | B14: Probabilidad de ganar un renglón centralizado en el que se oferta | C14: % | D14: 0.15 | E14: 0.3 | F14: 0.45 | G14: =CHOOSE(p_sc,D14,E14,F14) | H14: F: los nuevos ganan 36.6% por oferta en el MINSA y la LPU 01-2026 da 39.9% por oferta; E: descuento por descalificación
A15: realiz | B15: Cantidad comprada frente a la máxima del contrato de la LPU | C15: % | D15: 0.55 | E15: 0.75 | F15: 0.9 | G15: =CHOOSE(p_sc,D15,E15,F15) | H15: F: compra mínima garantizada de 50% (Adenda 1 de la LPU 01-2026); E: el resto
A16: realiz_minsa | B16: Cantidad comprada frente a la del contrato del MINSA (subasta por cantidad fija) | C16: % | D16: 1 | E16: 1 | F16: 1 | G16: =CHOOSE(p_sc,D16,E16,F16) | H16: F: las subastas del MINSA de 2026 son por cantidad fija (informe de la SSR-000018)
A17: minsa_occ | B17: Probabilidad de que el MINSA haga su compra centralizada en el año | C17: % | D17: 0.3 | E17: 0.5 | F17: 0.7 | G17: =CHOOSE(p_sc,D17,E17,F17) | H17: F: 33 subastas del MINSA entre el 24-mar y el 29-may-2026 y ninguna después; la compra conjunta del DE 16 no tiene acto a octubre de 2026
A18: cc_w | B18: Parte de la cantidad de la compra conjunta de 2023 que se toma como demanda del MINSA | C18: % | D18: 0 | E18: 0.15 | F18: 0.5 | G18: =CHOOSE(p_sc,D18,E18,F18) | H18: F: de los renglones de la primera ola solo 3 de 9 aparecen como contratos y por 7-20% de lo pedido; las cifras de 2023 son ofertas, no adjudicaciones
... A43: rs_off | B43: Tasas oficiales por registro (DNFD 500 + MEF + refrendo) | C43: B/. | D43: 575 | E43: 570 | F43: 545 | G43: =CHOOSE(p_sc,D43,E43,F43) | H43: F: DE 27 art. 15; guía del MINSA de 2012 para MEF y refrendo
A44: rs_iea | B44: Análisis de control previo (IEA o INDICASAT) por producto | C44: B/. | D44: 2000 | E44: 1500 | F44: 1000 | G44: =IF(p_sl=1,1500,CHOOSE(p_sc,D44,E44,F44)) | H44: R: guía del MINSA de 2012 US$1,000; SignatureLex B/.1,500; la tarifa vigente no está publicada pese a la Ley 419 art. 79
A45: rs_law | B45: Honorario y gastos del abogado por registro | C45: B/. | D45: 1350 | E45: 800 | F45: 500 | G45: =IF(p_sl=1,1350,CHOOSE(p_sc,D45,E45,F45)) | H45: R: SignatureLex 600 + 750; arancel de 2001 B/.350
A46: rs_smp | B46: Muestras y courier por registro | C46: B/. | D46: 300 | E46: 150 | F46: 100 | G46: =CHOOSE(p_sc,D46,E46,F46) | H46: E
A47: rs_trad | B47: Traducciones oficiales por registro (CPP, BPM, poderes, etiquetas) | C47: B/. | D47: 1500 | E47: 600 | F47: 300 | G47: =CHOOSE(p_sc,D47,E47,F47) | H47: F: DE 27 art. 220 exige traductor público autorizado; E: monto
A48: rs_succ | B48: Registros aprobados / presentados | C48: % | D48: 0.7 | E48: 0.85 | F48: 0.95 | G48: =CHOOSE(p_sc,D48,E48,F48) | H48: E
A49: postreg | B49: Análisis posregistro por producto (2 en 5 años), por año | C49: B/. | D49: 800 | E49: 600 | F49: 400 | G49: =CHOOSE(p_sc,D49,E49,F49) | H49: F: Ley 419 art. 67; R: 2 x 1,500 / 5
A50: n2 | B50: Productos de la segunda ola (sin equivalencia terapéutica, fabricación verificada) | C50: productos | D50: 0 | E50: 6 | F50: 12 | G50: =CHOOSE(p_sc,D50,E50,F50) | H50: E: candidatos del catálogo con compras públicas; exigen prueba de licencia de fabricación de cada uno
A51: m2 | B51: Mes en que se presentan los registros de la segunda ola | C51: mes | D51: 24 | E51: 18 | F51: 15 | G51: =CHOOSE(p_sc,D51,E51,F51) | H51: Decisión: solo si la primera ola pasa la compuerta operativa
A52: rel2 | B52: Ingreso por producto de la segunda ola frente al promedio de la primera | C52: x | D52: 0.5 | E52: 0.7 | F52: 1 | G52: =CHOOSE(p_sc,D52,E52,F52) | H52: E
A53: fact_share | B53: Porcentaje de las ventas que se factoriza | C53: % | D53: 0 | E53: 0 | F53: 0 | G53: =CHOOSE(p_sc,D53,E53,F53) | H53: Opción; Ley 22 art. 97 permite ceder créditos
A54: fact_cost | B54: Costo mensual del factoring sobre lo cedido | C54: % | D54: 0.015 | E54: 0.0125 | F54: 0.01 | G54: =CHOOSE(p_sc,D54,E54,F54) | H54: R: Balboa Factoring 2025, 14.6-18.3% anual
A55: stop_det | B55: Mes de cierre del negocio (61 = no se cierra) | C55: mes | D55: 61 | E55: 61 | F55: 61 | G55: =CHOOSE(p_sc,D55,E55,F55) | H55: Interruptor
A56: inv_liq | B56: Recuperación del inventario si se cierra | C56: % | D56: 0.5 | E56: 0.5 | F56: 0.5 | G56: =CHOOSE(p_sc,D56,E56,F56) | H56: E
A57: isr | B57: Impuesto sobre la renta | C57: % | D57: 0.25 | E57: 0.25 | F57: 0.25 | G57: =CHOOSE(p_sc,D57,E57,F57) | H57: F: Código Fiscal art. 699
... A72: forfeit_frac | B72: Parte de la fianza de cumplimiento que se pierde si el Estado la ejecuta | C72: % | D72: 1 | E72: 1 | F72: 1 | G72: =CHOOSE(p_sc,D72,E72,F72) | H72: F: Ley 22 (ejecución de la fianza) y contragarantías de la aseguradora (pagaré, codeudores)
A74: Costos fijos mensuales (B/./mes)
A75: # | B75: Concepto | C75: Inicio | D75: Pesimista | E75: Base | F75: Optimista | G75: Usado (con cargas o ITBMS) | H75: Fuente o base | I75: Mes inicio | J75: Tipo
A76: 1 | B76: Regente farmacéutico (medio tiempo, mínimo 4 h diarias) | C76: licencia | D76: 1200 | E76: 700 | F76: 450 | G76: =CHOOSE(p_sc,D76,E76,F76)*(1+p_oncost) | H76: F: DE 27 art. 382; R: SignatureLex 400-500 al mes; Paylab 1,339-3,228 a tiempo completo | I76: =c_lic_m | J76: sueldo + cargas laborales
A77: 2 | B77: Operador logístico (3PL) licenciado: cuota mínima | C77: licencia | D77: 1200 | E77: 600 | F77: 300 | G77: =CHOOSE(p_sc,D77,E77,F77)*(1+p_itbms_srv) | H77: E: sin tarifa pública; cotizaciones pedidas | I77: =c_lic_m | J77: servicio + ITBMS
A78: 3 | B78: Contabilidad e impuestos | C78: mes 1 | D78: 450 | E78: 300 | F78: 200 | G78: =CHOOSE(p_sc,D78,E78,F78)*(1+p_itbms_srv) | H78: R: Healy Consultants 2026, unos 192 al mes; E | I78: =1 | J78: servicio + ITBMS
A79: 4 | B79: Auditoría anual de estados financieros, prorrateada | C79: mes 1 | D79: 400 | E79: 250 | F79: 150 | G79: =CHOOSE(p_sc,D79,E79,F79)*(1+p_itbms_srv) | H79: F: el Registro Nacional de Oferentes pide solvencia certificada por CPA o banco (DE 27 arts. 724-725); E: costo | I79: =1 | J79: servicio + ITBMS
A80: 5 | B80: Asesoría legal por hora (sin iguala) | C80: mes 1 | D80: 800 | E80: 300 | F80: 150 | G80: =CHOOSE(p_sc,D80,E80,F80)*(1+p_itbms_srv) | H80: R: SignatureLex B/.300 por hora; E: horas | I80: =1 | J80: servicio + ITBMS
A81: 6 | B81: Coordinador de licitaciones y operaciones (medio tiempo, desde la licencia) | C81: licencia | D81: 1000 | E81: 700 | F81: 550 | G81: =CHOOSE(p_sc,D81,E81,F81)*(1+p_oncost) | H81: R: Konzerta mayo de 2026, semi-senior a jefatura US$1,033-1,291 a tiempo completo; a medio tiempo | I81: =c_lic_m | J81: sueldo + cargas laborales
A82: 7 | B82: Coordinador: paso a tiempo completo desde el primer contrato centralizado | C82: 1er contrato centralizado | D82: 800 | E82: 600 | F82: 450 | G82: =CHOOSE(p_sc,D82,E82,F82)*(1+p_oncost) | H82: R: diferencia entre tiempo completo (1,800 / 1,300 / 1,000) y medio tiempo | I82: =c_cen_start | J82: sueldo + cargas laborales
A83: 8 | B83: Farmacovigilancia: responsable designado y diccionarios MedDRA y WHODrug | C83: licencia | D83: 300 | E83: 150 | F83: 75 | G83: =CHOOSE(p_sc,D83,E83,F83)*(1+p_itbms_srv) | H83: F: DE 27 arts. 257, 318 y 319; E: costo (sin tarifa pública) | I83: =c_lic_m | J83: servicio + ITBMS
A84: 9 | B84: Seguros (responsabilidad civil y de producto) | C84: licencia | D84: 200 | E84: 100 | F84: 75 | G84: =CHOOSE(p_sc,D84,E84,F84) | H84: E: sin tarifa pública | I84: =c_lic_m | J84: otro
A85: 10 | B85: Software, banca, telecomunicaciones y administración | C85: mes 1 | D85: 200 | E85: 120 | F85: 80 | G85: =CHOOSE(p_sc,D85,E85,F85)*(1+p_itbms_srv) | H85: E | I85: =1 | J85: servicio + ITBMS
A86: 11 | B86: Impuesto municipal | C86: mes 1 | D86: 200 | E86: 100 | F86: 100 | G86: =CHOOSE(p_sc,D86,E86,F86) | H86: E: tramo por confirmar con el municipio | I86: =1 | J86: otro
B87: Total costos fijos a plena operación | G87: =SUM(G76:G86)
A89: Gastos de arranque, una sola vez (B/.)
A90: # | B90: Concepto | C90: Mes | D90: Pesimista | E90: Base | F90: Optimista | G90: Usado (con ITBMS) | H90: Fuente o base | I90: SignatureLex | J90: Tipo
A91: 1 | B91: Fase 0: debida diligencia de la fábrica y de los documentos (antes de constituir) | C91: 0 | D91: 6000 | E91: 2500 | F91: 1000 | G91: =IF(AND(p_sl=1,I91>0),I91,CHOOSE(p_sc,D91,E91,F91))*(1+p_itbms_srv) | H91: E: auditoría virtual de planta y verificación documental | I91: 0 | J91: servicio + ITBMS
A92: 2 | B92: Fase 0: opinión legal escrita sobre la Ley 316 (parentesco), de un abogado independiente | C92: 0 | D92: 1500 | E92: 800 | F92: 500 | G92: =IF(AND(p_sl=1,I92>0),I92,CHOOSE(p_sc,D92,E92,F92))*(1+p_itbms_srv) | H92: R: SignatureLex B/.300 por hora; E: 2 a 5 horas | I92: 0 | J92: servicio + ITBMS
A93: 3 | B93: Constitución, libros, poderes, RUC, aviso de operación y municipal | C93: 1 | D93: 3500 | E93: 2500 | F93: 1500 | G93: =IF(AND(p_sl=1,I93>0),I93,CHOOSE(p_sc,D93,E93,F93))*(1+p_itbms_srv) | H93: R: SignatureLex unos 5,700; Expanship US$1,200-2,200 el primer año | I93: 5700 | J93: servicio + ITBMS
A94: 4 | B94: Pacto de accionistas, contrato de suministro exclusivo y acuerdo de calidad | C94: 1 | D94: 6200 | E94: 2500 | F94: 1500 | G94: =IF(AND(p_sl=1,I94>0),I94,CHOOSE(p_sc,D94,E94,F94))*(1+p_itbms_srv) | H94: R: escala de SignatureLex (B/.1,500 más 1% escalonado) | I94: 1750 | J94: servicio + ITBMS
A95: 5 | B95: Diagnóstico regulatorio y matriz de portafolio | C95: 1 | D95: 650 | E95: 650 | F95: 500 | G95: =IF(AND(p_sl=1,I95>0),I95,CHOOSE(p_sc,D95,E95,F95))*(1+p_itbms_srv) | H95: R: SignatureLex 500 + 150 | I95: 650 | J95: servicio + ITBMS
A96: 6 | B96: Apoyo para abrir la cuenta bancaria | C96: 1 | D96: 3150 | E96: 300 | F96: 0 | G96: =IF(AND(p_sl=1,I96>0),I96,CHOOSE(p_sc,D96,E96,F96))*(1+p_itbms_srv) | H96: R: SignatureLex 3,000 + 150; E: base | I96: 3150 | J96: servicio + ITBMS
A97: 7 | B97: Licencia de operación: tasa oficial 250 + planos, procedimientos e inspección | C97: 2 | D97: 4000 | E97: 1750 | F97: 1000 | G97: =IF(AND(p_sl=1,I97>0),I97,CHOOSE(p_sc,D97,E97,F97))*(1+p_itbms_srv) | H97: F: DE 27 art. 15 (200 + 50); R: SignatureLex 3,500 + 500 | I97: 4000 | J97: servicio + ITBMS
A98: 8 | B98: Revisión del 3PL y acuerdo de calidad | C98: 2 | D98: 2650 | E98: 750 | F98: 400 | G98: =IF(AND(p_sl=1,I98>0),I98,CHOOSE(p_sc,D98,E98,F98))*(1+p_itbms_srv) | H98: R: SignatureLex 2,500 + 150; E: base | I98: 2650 | J98: servicio + ITBMS
A99: 9 | B99: Programa de cumplimiento y anticorrupción | C99: 2 | D99: 3150 | E99: 1500 | F99: 800 | G99: =IF(AND(p_sl=1,I99>0),I99,CHOOSE(p_sc,D99,E99,F99))*(1+p_itbms_srv) | H99: R: SignatureLex 3,000 + 150 | I99: 3150 | J99: servicio + ITBMS
A100: 10 | B100: Certificado de buenas prácticas de almacenamiento | C100: 3 | D100: 100 | E100: 100 | F100: 100 | G100: =IF(AND(p_sl=1,I100>0),I100,CHOOSE(p_sc,D100,E100,F100)) | H100: F: DE 27 art. 15 | I100: 100 | J100: otro
A101: 11 | B101: Registro patronal en la CSS y contratos laborales | C101: 3 | D101: 900 | E101: 300 | F101: 100 | G101: =IF(AND(p_sl=1,I101>0),I101,CHOOSE(p_sc,D101,E101,F101))*(1+p_itbms_srv) | H101: R: SignatureLex 750 + 150 | I101: 900 | J101: servicio + ITBMS
A102: 12 | B102: PanamaCompra, Registro Nacional de Oferentes y proveedor de la CSS | C102: 4 | D102: 2700 | E102: 500 | F102: 0 | G102: =IF(AND(p_sl=1,I102>0),I102,CHOOSE(p_sc,D102,E102,F102))*(1+p_itbms_srv) | H102: F: trámites sin tasa oficial; R: SignatureLex 3 x (750 + 150) | I102: 2700 | J102: servicio + ITBMS
B103: Total arranque (incluye fase 0) | G103: =SUM(G91:G102)
B104: Fase 0 (filas con mes 0) | G104: =SUMIF(u_month,0,u_used)
A106: Cargos anuales (meses 1, 13, 25, 37 y 49; el aviso de operación se calcula aparte sobre el patrimonio)
B107: Tasa única de la S.A. | E107: 300 | G107: =E107 | H107: F: DGI | J107: otro
B108: Agente residente | E108: 350 | G108: =E108*(1+p_itbms_srv) | H108: R: SignatureLex B/.350 al año; mercado US$150-800 | J108: servicio + ITBMS
B109: Renovación de la licencia de operación (B/.200 cada 2 años) | E109: 100 | G109: =E109 | H109: F: DE 27 arts. 15 y 398 | J109: otro
B110: Total cargos anuales | G110: =SUM(G107:G109)
A112: Valores calculados (no editar)
A113: c_lic_m | B113: Mes de la licencia de operación | G113: =3
A114: c_rs_pay_m | B114: Mes en que se pagan los registros de la primera ola | G114: =3
A115: c_lead_m | B115: Tiempo de reposición (meses) | G115: =ROUND(p_lead_days/30,0)
A116: c_dso_m | B116: Días de cobro (meses) | G116: =ROUND(p_dso_days/30,0)
A117: c_credit_m | B117: Crédito del proveedor (meses) | G117: =ROUND(p_credit_days/30,0)
A118: c_ship_m | B118: Embarque a stock (meses) | G118: =ROUND(p_ship_m,0)
A119: c_reg_m | B119: Mes de registros (entero) | G119: =ROUND(p_reg_m,0)
A120: c_first_dec | B120: Primer mes con ventas descentralizadas | G120: =c_reg_m+c_lead_m
A121: c_cen_start | B121: Primer mes con contrato centralizado (el registro debe existir al ofertar, c_bid_m meses antes) | G121: =MAX(ROUND(p_cen_start,0)+15*ROUNDUP(MAX(0,c_reg_m+c_bid_m-ROUND(p_cen_start,0))/15,0),c_first_dec)
A122: c_rt | B122: Meses de trámite del registro | G122: =MAX(c_reg_m-c_rs_pay_m,1)
A123: c_m2 | B123: Mes de registros de la segunda ola | G123: =ROUND(p_m2,0)
A124: c_first_dec2 | B124: Primer mes con ventas de la segunda ola | G124: =c_m2+c_rt+c_lead_m
A125: c_c2_lpu | B125: Primer contrato de la LPU con productos de la segunda ola (siguiente ciclo de 15 meses) | G125: =c_cen_start+15*ROUNDUP(MAX(0,MAX(c_first_dec2,c_m2+c_rt+c_bid_m)-c_cen_start)/15,0)
A126: c_c2_minsa | B126: Primer contrato del MINSA con productos de la segunda ola (siguiente ciclo de 12 meses) | G126: =c_cen_start+12*ROUNDUP(MAX(0,MAX(c_first_dec2,c_m2+c_rt+1)-c_cen_start)/12,0)
A127: c_n1 | B127: Productos presentados en la primera ola | G127: =MAX(SUM(SKUs!$D$6:$D$24),1)
A128: c_k2 | B128: Factor de escala de la segunda ola | G128: =p_n2*p_rel2/c_n1
A129: c_rs_unit | B129: Costo total por registro (B/.; ITBMS sobre abogado y traducciones) | G129: =p_rs_off+p_rs_iea+(p_rs_law+p_rs_trad)*(1+p_itbms_srv)+p_rs_smp
A130: c_bid_m | B130: Meses de colateral de la fianza de propuesta (entero) | G130: =ROUND(p_bid_m,0)
A131: c_n_reg1 | B131: Registros aprobados esperados, primera ola | G131: =SUM(SKUs!$D$6:$D$24)*p_rs_succ
A132: c_n_reg2 | B132: Registros aprobados esperados, segunda ola | G132: =p_n2*p_rs_succ

Sheet SKUs
A1: Portafolio y economía por producto
A2: Demanda pública anualizada (LPU 01-2026; subasta del MINSA de 2026 o compra conjunta de 2023 x p_cc_w; compras menores 2025-2026 con precio ponderado). Ventas a madurez antes de rampa y erosión.
A3: Canales: LPU = licitación de precio único de la CSS; MINSA central = subasta en reversa o compra conjunta; desc. = contratación menor y compra menor ágil. Costo = referencia FOB x índice x (1 + empaque) + logística.
A5: ID | B5: Producto | C5: Grupo | D5: Incluir (1/0) | E5: FOB base (B/./u) | F5: Logística (B/./u) | G5: Fuente del costo | H5: CSS LPU: unid./año | I5: CSS LPU: precio | J5: MINSA central: unid./año | K5: MINSA central: precio | L5: CSS desc.: unid./año | M5: CSS desc.: precio | N5: MINSA/patronatos desc.: unid./año | O5: MINSA/patronatos desc.: precio | P5: Costo puesto en Panamá | Q5: Precio oferta LPU | R5: Precio oferta MINSA central | S5: Precio oferta CSS desc. | T5: Precio oferta MINSA desc. | U5: Margen LPU | V5: Margen MINSA central | W5: Margen CSS desc. | X5: Margen MINSA desc. | Y5: Oferta LPU | Z5: Oferta MINSA central | AA5: Oferta CSS desc. | AB5: Oferta MINSA desc. | AC5: Ventas CSS desc. (madurez) | AD5: Ventas MINSA desc. (madurez) | AE5: Ventas LPU si gana | AF5: Ventas MINSA central si gana | AG5: Costo CSS desc. | AH5: Costo MINSA desc. | AI5: Costo LPU | AJ5: Costo MINSA central | AK5: Ventas esperadas año maduro | AL5: Utilidad bruta esperada | AM5: Costo FOB (para Zywie) | AN5: Oferta LPU con fianza de propuesta (B/./año)
A6: PCT500 | B6: Paracetamol 500 mg tableta | C6: Primera ola | D6: 1 | E6: 0.0038 | F6: 0.00165 | G6: R: PMBI 2024-27 INR 2.74 por 10, TNMSC 2024 INR 23.48 por 100 y Assam 2025 INR 2.50 por 10; x1.4 = US$0.0034-0.0040; se usa 0.0038; blíster 5.5 cm3 | H6: 23770516 | I6: 0.01 | J6: 0 | K6: 0 | L6: 1141333 | M6: 0.02 | N6: 11112486 | O6: 0.0201 | P6: =E6*p_sup_idx*(1+p_pack)+F6*p_log_mult | Q6: =I6*p_pf_cen | R6: =K6*p_pf_cen | S6: =M6*p_pf_dec | T6: =O6*p_pf_dec | U6: =IF(Q6>0,1-P6/Q6,-9) | V6: =IF(R6>0,1-P6/R6,-9) | W6: =IF(S6>0,1-P6/S6,-9) | X6: =IF(T6>0,1-P6/T6,-9) | Y6: =IF(AND($D6=1,H6>0,U6>=p_gm_cen),1,0) | Z6: =IF(AND($D6=1,J6>0,V6>=p_gm_cen),1,0) | AA6: =IF(AND($D6=1,L6>0,W6>=p_gm_dec),1,0) | AB6: =IF(AND($D6=1,N6>0,X6>=p_gm_dec),1,0) | AC6: =AA6*L6*p_mkt*S6*p_rs_succ*p_share_dec | AD6: =AB6*N6*p_mkt*T6*p_rs_succ*p_share_dec | AE6: =Y6*H6*p_mkt*Q6*p_rs_succ*p_realiz | AF6: =Z6*J6*p_mkt*R6*p_rs_succ*p_realiz_minsa | AG6: =IF(S6>0,AC6*P6/S6,0) | AH6: =IF(T6>0,AD6*P6/T6,0) | AI6: =IF(Q6>0,AE6*P6/Q6,0) | AJ6: =IF(R6>0,AF6*P6/R6,0) | AK6: =AC6+AD6+AE6*p_pwin_cen+AF6*p_pwin_cen*p_minsa_occ | AL6: =(AC6-AG6)+(AD6-AH6)+(AE6-AI6)*p_pwin_cen+(AF6-AJ6)*p_pwin_cen*p_minsa_occ | AM6: =IF(P6>0,E6*p_sup_idx*(1+p_pack)/P6,0) | AN6: =IF(AND(Y6=1,H6>0),H6*p_mkt*Q6*p_rs_succ,0)
A7: PCTSYR | B7: Paracetamol 120-160 mg/5 ml jarabe, frasco 120 ml | C7: Primera ola | D7: 1 | E7: 0.1478 | F7: 0.135 | G7: R: TNMSC 2024 INR 5.72 y Assam 2025 INR 5.85 por 60 ml; a 120 ml se usa INR 10.2 (factor 1.75 por frasco más grande), x1.4; 450 cm3 | H7: 315718 | I7: 0.59 | J7: 524358 | K7: 0.4 | L7: 0 | M7: 0 | N7: 63302 | O7: 0.6938 | P7: =E7*p_sup_idx*(1+p_pack)+F7*p_log_mult | Q7: =I7*p_pf_cen | R7: =K7*p_pf_cen | S7: =M7*p_pf_dec | T7: =O7*p_pf_dec | U7: =IF(Q7>0,1-P7/Q7,-9) | V7: =IF(R7>0,1-P7/R7,-9) | W7: =IF(S7>0,1-P7/S7,-9) | X7: =IF(T7>0,1-P7/T7,-9) | Y7: =IF(AND($D7=1,H7>0,U7>=p_gm_cen),1,0) | Z7: =IF(AND($D7=1,J7>0,V7>=p_gm_cen),1,0) | AA7: =IF(AND($D7=1,L7>0,W7>=p_gm_dec),1,0) | AB7: =IF(AND($D7=1,N7>0,X7>=p_gm_dec),1,0) | AC7: =AA7*L7*p_mkt*S7*p_rs_succ*p_share_dec | AD7: =AB7*N7*p_mkt*T7*p_rs_succ*p_share_dec | AE7: =Y7*H7*p_mkt*Q7*p_rs_succ*p_realiz | AF7: =Z7*J7*p_mkt*R7*p_rs_succ*p_realiz_minsa | AG7: =IF(S7>0,AC7*P7/S7,0) | AH7: =IF(T7>0,AD7*P7/T7,0) | AI7: =IF(Q7>0,AE7*P7/Q7,0) | AJ7: =IF(R7>0,AF7*P7/R7,0) | AK7: =AC7+AD7+AE7*p_pwin_cen+AF7*p_pwin_cen*p_minsa_occ | AL7: =(AC7-AG7)+(AD7-AH7)+(AE7-AI7)*p_pwin_cen+(AF7-AJ7)*p_pwin_cen*p_minsa_occ | AM7: =IF(P7>0,E7*p_sup_idx*(1+p_pack)/P7,0) | AN7: =IF(AND(Y7=1,H7>0),H7*p_mkt*Q7*p_rs_succ,0)
A8: AMCTAB | B8: Amoxicilina + clavulánico 500/125 mg tableta | C8: Primera ola | D8: 1 | E8: 0.0754 | F8: 0.0036 | G8: R: PMBI 2024-26 INR 31.60 por 6 y TNMSC 2024 INR 30.81 por 6 (se usa INR 5.2 por tableta), x1.4; alu-alu 12 cm3 | H8: 46534 | I8: 0.179 | J8: =191135*p_cc_w | K8: 0.19 | L8: 0 | M8: 0 | N8: 30555 | O8: 0.3211 | P8: =E8*p_sup_idx*(1+p_pack)+F8*p_log_mult | Q8: =I8*p_pf_cen | R8: =K8*p_pf_cen | S8: =M8*p_pf_dec | T8: =O8*p_pf_dec | U8: =IF(Q8>0,1-P8/Q8,-9) | V8: =IF(R8>0,1-P8/R8,-9) | W8: =IF(S8>0,1-P8/S8,-9) | X8: =IF(T8>0,1-P8/T8,-9) | Y8: =IF(AND($D8=1,H8>0,U8>=p_gm_cen),1,0) | Z8: =IF(AND($D8=1,J8>0,V8>=p_gm_cen),1,0) | AA8: =IF(AND($D8=1,L8>0,W8>=p_gm_dec),1,0) | AB8: =IF(AND($D8=1,N8>0,X8>=p_gm_dec),1,0) | AC8: =AA8*L8*p_mkt*S8*p_rs_succ*p_share_dec | AD8: =AB8*N8*p_mkt*T8*p_rs_succ*p_share_dec | AE8: =Y8*H8*p_mkt*Q8*p_rs_succ*p_realiz | AF8: =Z8*J8*p_mkt*R8*p_rs_succ*p_realiz_minsa | AG8: =IF(S8>0,AC8*P8/S8,0) | AH8: =IF(T8>0,AD8*P8/T8,0) | AI8: =IF(Q8>0,AE8*P8/Q8,0) | AJ8: =IF(R8>0,AF8*P8/R8,0) | AK8: =AC8+AD8+AE8*p_pwin_cen+AF8*p_pwin_cen*p_minsa_occ | AL8: =(AC8-AG8)+(AD8-AH8)+(AE8-AI8)*p_pwin_cen+(AF8-AJ8)*p_pwin_cen*p_minsa_occ | AM8: =IF(P8>0,E8*p_sup_idx*(1+p_pack)/P8,0) | AN8: =IF(AND(Y8=1,H8>0),H8*p_mkt*Q8*p_rs_succ,0)
A9: AMCSUS | B9: Amoxicilina + clavulánico 400/57 mg/5 ml suspensión, frasco 100 ml | C9: Primera ola | D9: 1 | E9: 1.159 | F9: 0.15 | G9: R: PMBI 2023-26 INR 28.06 por 30 ml, escalado a 100 ml (x2.85 = INR 80), x1.4; 500 cm3 | H9: 10217 | I9: 1.98 | J9: 0 | K9: 0 | L9: 0 | M9: 0 | N9: 7463 | O9: 4.5197 | P9: =E9*p_sup_idx*(1+p_pack)+F9*p_log_mult | Q9: =I9*p_pf_cen | R9: =K9*p_pf_cen | S9: =M9*p_pf_dec | T9: =O9*p_pf_dec | U9: =IF(Q9>0,1-P9/Q9,-9) | V9: =IF(R9>0,1-P9/R9,-9) | W9: =IF(S9>0,1-P9/S9,-9) | X9: =IF(T9>0,1-P9/T9,-9) | Y9: =IF(AND($D9=1,H9>0,U9>=p_gm_cen),1,0) | Z9: =IF(AND($D9=1,J9>0,V9>=p_gm_cen),1,0) | AA9: =IF(AND($D9=1,L9>0,W9>=p_gm_dec),1,0) | AB9: =IF(AND($D9=1,N9>0,X9>=p_gm_dec),1,0) | AC9: =AA9*L9*p_mkt*S9*p_rs_succ*p_share_dec | AD9: =AB9*N9*p_mkt*T9*p_rs_succ*p_share_dec | AE9: =Y9*H9*p_mkt*Q9*p_rs_succ*p_realiz | AF9: =Z9*J9*p_mkt*R9*p_rs_succ*p_realiz_minsa | AG9: =IF(S9>0,AC9*P9/S9,0) | AH9: =IF(T9>0,AD9*P9/T9,0) | AI9: =IF(Q9>0,AE9*P9/Q9,0) | AJ9: =IF(R9>0,AF9*P9/R9,0) | AK9: =AC9+AD9+AE9*p_pwin_cen+AF9*p_pwin_cen*p_minsa_occ | AL9: =(AC9-AG9)+(AD9-AH9)+(AE9-AI9)*p_pwin_cen+(AF9-AJ9)*p_pwin_cen*p_minsa_occ | AM9: =IF(P9>0,E9*p_sup_idx*(1+p_pack)/P9,0) | AN9: =IF(AND(Y9=1,H9>0),H9*p_mkt*Q9*p_rs_succ,0)
A10: CRO1G | B10: Ceftriaxona 1 g vial (I.V.) | C10: Primera ola | D10: 1 | E10: 0.1956 | F10: 0.0162 | G10: R: Assam 2025 INR 12.6 y Delhi 2022 INR 15.48 por vial; se usa INR 13.5, x1.4; 54 cm3 | H10: 194242 | I10: 0.239 | J10: =201135*p_cc_w | K10: 0.25 | L10: 3899 | M10: 0.78 | N10: 43743 | O10: 0.452 | P10: =E10*p_sup_idx*(1+p_pack)+F10*p_log_mult | Q10: =I10*p_pf_cen | R10: =K10*p_pf_cen | S10: =M10*p_pf_dec | T10: =O10*p_pf_dec | U10: =IF(Q10>0,1-P10/Q10,-9) | V10: =IF(R10>0,1-P10/R10,-9) | W10: =IF(S10>0,1-P10/S10,-9) | X10: =IF(T10>0,1-P10/T10,-9) | Y10: =IF(AND($D10=1,H10>0,U10>=p_gm_cen),1,0) | Z10: =IF(AND($D10=1,J10>0,V10>=p_gm_cen),1,0) | AA10: =IF(AND($D10=1,L10>0,W10>=p_gm_dec),1,0) | AB10: =IF(AND($D10=1,N10>0,X10>=p_gm_dec),1,0) | AC10: =AA10*L10*p_mkt*S10*p_rs_succ*p_share_dec | AD10: =AB10*N10*p_mkt*T10*p_rs_succ*p_share_dec | AE10: =Y10*H10*p_mkt*Q10*p_rs_succ*p_realiz | AF10: =Z10*J10*p_mkt*R10*p_rs_succ*p_realiz_minsa | AG10: =IF(S10>0,AC10*P10/S10,0) | AH10: =IF(T10>0,AD10*P10/T10,0) | AI10: =IF(Q10>0,AE10*P10/Q10,0) | AJ10: =IF(R10>0,AF10*P10/R10,0) | AK10: =AC10+AD10+AE10*p_pwin_cen+AF10*p_pwin_cen*p_minsa_occ | AL10: =(AC10-AG10)+(AD10-AH10)+(AE10-AI10)*p_pwin_cen+(AF10-AJ10)*p_pwin_cen*p_minsa_occ | AM10: =IF(P10>0,E10*p_sup_idx*(1+p_pack)/P10,0) | AN10: =IF(AND(Y10=1,H10>0),H10*p_mkt*Q10*p_rs_succ,0)
A11: CTX1G | B11: Cefotaxima 1 g vial | C11: Primera ola | D11: 1 | E11: 0.2029 | F11: 0.0162 | G11: R: Assam 2025 INR 13.3 por vial (PMBI 500 mg con agua INR 12.32); se usa INR 14.0, x1.4; 54 cm3 | H11: 168687 | I11: 0.259 | J11: =177344*p_cc_w | K11: 0.27 | L11: 0 | M11: 0 | N11: 79691 | O11: 0.3987 | P11: =E11*p_sup_idx*(1+p_pack)+F11*p_log_mult | Q11: =I11*p_pf_cen | R11: =K11*p_pf_cen | S11: =M11*p_pf_dec | T11: =O11*p_pf_dec | U11: =IF(Q11>0,1-P11/Q11,-9) | V11: =IF(R11>0,1-P11/R11,-9) | W11: =IF(S11>0,1-P11/S11,-9) | X11: =IF(T11>0,1-P11/T11,-9) | Y11: =IF(AND($D11=1,H11>0,U11>=p_gm_cen),1,0) | Z11: =IF(AND($D11=1,J11>0,V11>=p_gm_cen),1,0) | AA11: =IF(AND($D11=1,L11>0,W11>=p_gm_dec),1,0) | AB11: =IF(AND($D11=1,N11>0,X11>=p_gm_dec),1,0) | AC11: =AA11*L11*p_mkt*S11*p_rs_succ*p_share_dec | AD11: =AB11*N11*p_mkt*T11*p_rs_succ*p_share_dec | AE11: =Y11*H11*p_mkt*Q11*p_rs_succ*p_realiz | AF11: =Z11*J11*p_mkt*R11*p_rs_succ*p_realiz_minsa | AG11: =IF(S11>0,AC11*P11/S11,0) | AH11: =IF(T11>0,AD11*P11/T11,0) | AI11: =IF(Q11>0,AE11*P11/Q11,0) | AJ11: =IF(R11>0,AF11*P11/R11,0) | AK11: =AC11+AD11+AE11*p_pwin_cen+AF11*p_pwin_cen*p_minsa_occ | AL11: =(AC11-AG11)+(AD11-AH11)+(AE11-AI11)*p_pwin_cen+(AF11-AJ11)*p_pwin_cen*p_minsa_occ | AM11: =IF(P11>0,E11*p_sup_idx*(1+p_pack)/P11,0) | AN11: =IF(AND(Y11=1,H11>0),H11*p_mkt*Q11*p_rs_succ,0)
A12: ALBSUS | B12: Albendazol 400 mg/10 ml suspensión | C12: Primera ola | D12: 1 | E12: 0.07 | F12: 0.024 | G12: R: PMBI 2022-25 INR 4.22 y Delhi 2022 INR 4.59 por 10 ml; x1.4 = US$0.062; se usa 0.07; 80 cm3 (el ganador de la LPU entregó 20 ml) | H12: 18762 | I12: 1.81 | J12: =194990*p_cc_w | K12: 1.86 | L12: 0 | M12: 0 | N12: 10114 | O12: 1.5163 | P12: =E12*p_sup_idx*(1+p_pack)+F12*p_log_mult | Q12: =I12*p_pf_cen | R12: =K12*p_pf_cen | S12: =M12*p_pf_dec | T12: =O12*p_pf_dec | U12: =IF(Q12>0,1-P12/Q12,-9) | V12: =IF(R12>0,1-P12/R12,-9) | W12: =IF(S12>0,1-P12/S12,-9) | X12: =IF(T12>0,1-P12/T12,-9) | Y12: =IF(AND($D12=1,H12>0,U12>=p_gm_cen),1,0) | Z12: =IF(AND($D12=1,J12>0,V12>=p_gm_cen),1,0) | AA12: =IF(AND($D12=1,L12>0,W12>=p_gm_dec),1,0) | AB12: =IF(AND($D12=1,N12>0,X12>=p_gm_dec),1,0) | AC12: =AA12*L12*p_mkt*S12*p_rs_succ*p_share_dec | AD12: =AB12*N12*p_mkt*T12*p_rs_succ*p_share_dec | AE12: =Y12*H12*p_mkt*Q12*p_rs_succ*p_realiz | AF12: =Z12*J12*p_mkt*R12*p_rs_succ*p_realiz_minsa | AG12: =IF(S12>0,AC12*P12/S12,0) | AH12: =IF(T12>0,AD12*P12/T12,0) | AI12: =IF(Q12>0,AE12*P12/Q12,0) | AJ12: =IF(R12>0,AF12*P12/R12,0) | AK12: =AC12+AD12+AE12*p_pwin_cen+AF12*p_pwin_cen*p_minsa_occ | AL12: =(AC12-AG12)+(AD12-AH12)+(AE12-AI12)*p_pwin_cen+(AF12-AJ12)*p_pwin_cen*p_minsa_occ | AM12: =IF(P12>0,E12*p_sup_idx*(1+p_pack)/P12,0) | AN12: =IF(AND(Y12=1,H12>0),H12*p_mkt*Q12*p_rs_succ,0)
A13: MBZ100 | B13: Mebendazol 100 mg tableta | C13: Primera ola | D13: 1 | E13: 0.0085 | F13: 0.0009 | G13: R: sin licitación india pública; precio al público de Jan Aushadhi INR 8.44 por 6 x0.42 = INR 0.59, x1.4; 3 cm3 | H13: 188514 | I13: 0.13 | J13: =179270*p_cc_w | K13: 0.13 | L13: 8000 | M13: 0.2188 | N13: 1714 | O13: 0.1753 | P13: =E13*p_sup_idx*(1+p_pack)+F13*p_log_mult | Q13: =I13*p_pf_cen | R13: =K13*p_pf_cen | S13: =M13*p_pf_dec | T13: =O13*p_pf_dec | U13: =IF(Q13>0,1-P13/Q13,-9) | V13: =IF(R13>0,1-P13/R13,-9) | W13: =IF(S13>0,1-P13/S13,-9) | X13: =IF(T13>0,1-P13/T13,-9) | Y13: =IF(AND($D13=1,H13>0,U13>=p_gm_cen),1,0) | Z13: =IF(AND($D13=1,J13>0,V13>=p_gm_cen),1,0) | AA13: =IF(AND($D13=1,L13>0,W13>=p_gm_dec),1,0) | AB13: =IF(AND($D13=1,N13>0,X13>=p_gm_dec),1,0) | AC13: =AA13*L13*p_mkt*S13*p_rs_succ*p_share_dec | AD13: =AB13*N13*p_mkt*T13*p_rs_succ*p_share_dec | AE13: =Y13*H13*p_mkt*Q13*p_rs_succ*p_realiz | AF13: =Z13*J13*p_mkt*R13*p_rs_succ*p_realiz_minsa | AG13: =IF(S13>0,AC13*P13/S13,0) | AH13: =IF(T13>0,AD13*P13/T13,0) | AI13: =IF(Q13>0,AE13*P13/Q13,0) | AJ13: =IF(R13>0,AF13*P13/R13,0) | AK13: =AC13+AD13+AE13*p_pwin_cen+AF13*p_pwin_cen*p_minsa_occ | AL13: =(AC13-AG13)+(AD13-AH13)+(AE13-AI13)*p_pwin_cen+(AF13-AJ13)*p_pwin_cen*p_minsa_occ | AM13: =IF(P13>0,E13*p_sup_idx*(1+p_pack)/P13,0) | AN13: =IF(AND(Y13=1,H13>0),H13*p_mkt*Q13*p_rs_succ,0)
A14: NYSSUS | B14: Nistatina 100,000 UI/ml suspensión, frasco 30 ml | C14: Primera ola | D14: 1 | E14: 0.42 | F14: 0.0555 | G14: R: sin precio indio público; se usa US$0.42 con UNICEF US$0.60 por 30 ml como techo; 185 cm3 | H14: 14898 | I14: 3.18 | J14: =18118*p_cc_w | K14: 3.39 | L14: 0 | M14: 0 | N14: 2142 | O14: 3.3201 | P14: =E14*p_sup_idx*(1+p_pack)+F14*p_log_mult | Q14: =I14*p_pf_cen | R14: =K14*p_pf_cen | S14: =M14*p_pf_dec | T14: =O14*p_pf_dec | U14: =IF(Q14>0,1-P14/Q14,-9) | V14: =IF(R14>0,1-P14/R14,-9) | W14: =IF(S14>0,1-P14/S14,-9) | X14: =IF(T14>0,1-P14/T14,-9) | Y14: =IF(AND($D14=1,H14>0,U14>=p_gm_cen),1,0) | Z14: =IF(AND($D14=1,J14>0,V14>=p_gm_cen),1,0) | AA14: =IF(AND($D14=1,L14>0,W14>=p_gm_dec),1,0) | AB14: =IF(AND($D14=1,N14>0,X14>=p_gm_dec),1,0) | AC14: =AA14*L14*p_mkt*S14*p_rs_succ*p_share_dec | AD14: =AB14*N14*p_mkt*T14*p_rs_succ*p_share_dec | AE14: =Y14*H14*p_mkt*Q14*p_rs_succ*p_realiz | AF14: =Z14*J14*p_mkt*R14*p_rs_succ*p_realiz_minsa | AG14: =IF(S14>0,AC14*P14/S14,0) | AH14: =IF(T14>0,AD14*P14/T14,0) | AI14: =IF(Q14>0,AE14*P14/Q14,0) | AJ14: =IF(R14>0,AF14*P14/R14,0) | AK14: =AC14+AD14+AE14*p_pwin_cen+AF14*p_pwin_cen*p_minsa_occ | AL14: =(AC14-AG14)+(AD14-AH14)+(AE14-AI14)*p_pwin_cen+(AF14-AJ14)*p_pwin_cen*p_minsa_occ | AM14: =IF(P14>0,E14*p_sup_idx*(1+p_pack)/P14,0) | AN14: =IF(AND(Y14=1,H14>0),H14*p_mkt*Q14*p_rs_succ,0)
A15: HCTCRM | B15: Hidrocortisona 1% crema, tubo 15 g | C15: Primera ola | D15: 1 | E15: 0.1988 | F15: 0.033 | G15: R: PMBI 2024-26 INR 13.72 por tubo x1.4; 110 cm3 | H15: 89267 | I15: 0.555 | J15: =44276*p_cc_w | K15: 0.58 | L15: 0 | M15: 0 | N15: 1564 | O15: 1.4679 | P15: =E15*p_sup_idx*(1+p_pack)+F15*p_log_mult | Q15: =I15*p_pf_cen | R15: =K15*p_pf_cen | S15: =M15*p_pf_dec | T15: =O15*p_pf_dec | U15: =IF(Q15>0,1-P15/Q15,-9) | V15: =IF(R15>0,1-P15/R15,-9) | W15: =IF(S15>0,1-P15/S15,-9) | X15: =IF(T15>0,1-P15/T15,-9) | Y15: =IF(AND($D15=1,H15>0,U15>=p_gm_cen),1,0) | Z15: =IF(AND($D15=1,J15>0,V15>=p_gm_cen),1,0) | AA15: =IF(AND($D15=1,L15>0,W15>=p_gm_dec),1,0) | AB15: =IF(AND($D15=1,N15>0,X15>=p_gm_dec),1,0) | AC15: =AA15*L15*p_mkt*S15*p_rs_succ*p_share_dec | AD15: =AB15*N15*p_mkt*T15*p_rs_succ*p_share_dec | AE15: =Y15*H15*p_mkt*Q15*p_rs_succ*p_realiz | AF15: =Z15*J15*p_mkt*R15*p_rs_succ*p_realiz_minsa | AG15: =IF(S15>0,AC15*P15/S15,0) | AH15: =IF(T15>0,AD15*P15/T15,0) | AI15: =IF(Q15>0,AE15*P15/Q15,0) | AJ15: =IF(R15>0,AF15*P15/R15,0) | AK15: =AC15+AD15+AE15*p_pwin_cen+AF15*p_pwin_cen*p_minsa_occ | AL15: =(AC15-AG15)+(AD15-AH15)+(AE15-AI15)*p_pwin_cen+(AF15-AJ15)*p_pwin_cen*p_minsa_occ | AM15: =IF(P15>0,E15*p_sup_idx*(1+p_pack)/P15,0) | AN15: =IF(AND(Y15=1,H15>0),H15*p_mkt*Q15*p_rs_succ,0)
A16: MOMCRM | B16: Mometasona 0.1% crema, tubo 15 g (renglón de corticoide de alta potencia) | C16: Primera ola | D16: 1 | E16: 0.1 | F16: 0.033 | G16: R: PMBI 2023-25 INR 6.00 por tubo; x1.4 = US$0.087; se usa 0.10; 110 cm3 | H16: 65534 | I16: 1.02 | J16: =34482*p_cc_w | K16: 0.65 | L16: 0 | M16: 0 | N16: 343 | O16: 3.66 | P16: =E16*p_sup_idx*(1+p_pack)+F16*p_log_mult | Q16: =I16*p_pf_cen | R16: =K16*p_pf_cen | S16: =M16*p_pf_dec | T16: =O16*p_pf_dec | U16: =IF(Q16>0,1-P16/Q16,-9) | V16: =IF(R16>0,1-P16/R16,-9) | W16: =IF(S16>0,1-P16/S16,-9) | X16: =IF(T16>0,1-P16/T16,-9) | Y16: =IF(AND($D16=1,H16>0,U16>=p_gm_cen),1,0) | Z16: =IF(AND($D16=1,J16>0,V16>=p_gm_cen),1,0) | AA16: =IF(AND($D16=1,L16>0,W16>=p_gm_dec),1,0) | AB16: =IF(AND($D16=1,N16>0,X16>=p_gm_dec),1,0) | AC16: =AA16*L16*p_mkt*S16*p_rs_succ*p_share_dec | AD16: =AB16*N16*p_mkt*T16*p_rs_succ*p_share_dec | AE16: =Y16*H16*p_mkt*Q16*p_rs_succ*p_realiz | AF16: =Z16*J16*p_mkt*R16*p_rs_succ*p_realiz_minsa | AG16: =IF(S16>0,AC16*P16/S16,0) | AH16: =IF(T16>0,AD16*P16/T16,0) | AI16: =IF(Q16>0,AE16*P16/Q16,0) | AJ16: =IF(R16>0,AF16*P16/R16,0) | AK16: =AC16+AD16+AE16*p_pwin_cen+AF16*p_pwin_cen*p_minsa_occ | AL16: =(AC16-AG16)+(AD16-AH16)+(AE16-AI16)*p_pwin_cen+(AF16-AJ16)*p_pwin_cen*p_minsa_occ | AM16: =IF(P16>0,E16*p_sup_idx*(1+p_pack)/P16,0) | AN16: =IF(AND(Y16=1,H16>0),H16*p_mkt*Q16*p_rs_succ,0)
A17: AMI10 | B17: Amitriptilina 10 mg tableta | C17: SNC | D17: 0 | E17: 0.0028 | F17: 0.00054 | G17: R: Assam 2025 INR 1.90 por 10 (PMBI INR 1.99; TNMSC INR 1.71), x1.4 | H17: 325776 | I17: 0.12 | J17: =152808*p_cc_w | K17: 0.12 | L17: 0 | M17: 0 | N17: 0 | O17: 0 | P17: =E17*p_sup_idx*(1+p_pack)+F17*p_log_mult | Q17: =I17*p_pf_cen | R17: =K17*p_pf_cen | S17: =M17*p_pf_dec | T17: =O17*p_pf_dec | U17: =IF(Q17>0,1-P17/Q17,-9) | V17: =IF(R17>0,1-P17/R17,-9) | W17: =IF(S17>0,1-P17/S17,-9) | X17: =IF(T17>0,1-P17/T17,-9) | Y17: =IF(AND($D17=1,H17>0,U17>=p_gm_cen),1,0) | Z17: =IF(AND($D17=1,J17>0,V17>=p_gm_cen),1,0) | AA17: =IF(AND($D17=1,L17>0,W17>=p_gm_dec),1,0) | AB17: =IF(AND($D17=1,N17>0,X17>=p_gm_dec),1,0) | AC17: =AA17*L17*p_mkt*S17*p_rs_succ*p_share_dec | AD17: =AB17*N17*p_mkt*T17*p_rs_succ*p_share_dec | AE17: =Y17*H17*p_mkt*Q17*p_rs_succ*p_realiz | AF17: =Z17*J17*p_mkt*R17*p_rs_succ*p_realiz_minsa | AG17: =IF(S17>0,AC17*P17/S17,0) | AH17: =IF(T17>0,AD17*P17/T17,0) | AI17: =IF(Q17>0,AE17*P17/Q17,0) | AJ17: =IF(R17>0,AF17*P17/R17,0) | AK17: =AC17+AD17+AE17*p_pwin_cen+AF17*p_pwin_cen*p_minsa_occ | AL17: =(AC17-AG17)+(AD17-AH17)+(AE17-AI17)*p_pwin_cen+(AF17-AJ17)*p_pwin_cen*p_minsa_occ | AM17: =IF(P17>0,E17*p_sup_idx*(1+p_pack)/P17,0) | AN17: =IF(AND(Y17=1,H17>0),H17*p_mkt*Q17*p_rs_succ,0)
A18: AMI25 | B18: Amitriptilina 25 mg tableta | C18: SNC | D18: 0 | E18: 0.0033 | F18: 0.00054 | G18: R: Assam 2025 INR 2.30 por 10 (TNMSC INR 19.63 por 100; PMBI INR 3.49 por 15), x1.4 | H18: 1953204 | I18: 0.027 | J18: 0 | K18: 0 | L18: 0 | M18: 0 | N18: 3086 | O18: 0.4 | P18: =E18*p_sup_idx*(1+p_pack)+F18*p_log_mult | Q18: =I18*p_pf_cen | R18: =K18*p_pf_cen | S18: =M18*p_pf_dec | T18: =O18*p_pf_dec | U18: =IF(Q18>0,1-P18/Q18,-9) | V18: =IF(R18>0,1-P18/R18,-9) | W18: =IF(S18>0,1-P18/S18,-9) | X18: =IF(T18>0,1-P18/T18,-9) | Y18: =IF(AND($D18=1,H18>0,U18>=p_gm_cen),1,0) | Z18: =IF(AND($D18=1,J18>0,V18>=p_gm_cen),1,0) | AA18: =IF(AND($D18=1,L18>0,W18>=p_gm_dec),1,0) | AB18: =IF(AND($D18=1,N18>0,X18>=p_gm_dec),1,0) | AC18: =AA18*L18*p_mkt*S18*p_rs_succ*p_share_dec | AD18: =AB18*N18*p_mkt*T18*p_rs_succ*p_share_dec | AE18: =Y18*H18*p_mkt*Q18*p_rs_succ*p_realiz | AF18: =Z18*J18*p_mkt*R18*p_rs_succ*p_realiz_minsa | AG18: =IF(S18>0,AC18*P18/S18,0) | AH18: =IF(T18>0,AD18*P18/T18,0) | AI18: =IF(Q18>0,AE18*P18/Q18,0) | AJ18: =IF(R18>0,AF18*P18/R18,0) | AK18: =AC18+AD18+AE18*p_pwin_cen+AF18*p_pwin_cen*p_minsa_occ | AL18: =(AC18-AG18)+(AD18-AH18)+(AE18-AI18)*p_pwin_cen+(AF18-AJ18)*p_pwin_cen*p_minsa_occ | AM18: =IF(P18>0,E18*p_sup_idx*(1+p_pack)/P18,0) | AN18: =IF(AND(Y18=1,H18>0),H18*p_mkt*Q18*p_rs_succ,0)
A19: QTP25 | B19: Quetiapina 25 mg tableta | C19: SNC | D19: 0 | E19: 0.0053 | F19: 0.00054 | G19: R: PMBI 2023-26 INR 3.69 por 10 x1.4 | H19: 0 | I19: 0 | J19: 0 | K19: 0 | L19: 0 | M19: 0 | N19: 558798 | O19: 0.18 | P19: =E19*p_sup_idx*(1+p_pack)+F19*p_log_mult | Q19: =I19*p_pf_cen | R19: =K19*p_pf_cen | S19: =M19*p_pf_dec | T19: =O19*p_pf_dec | U19: =IF(Q19>0,1-P19/Q19,-9) | V19: =IF(R19>0,1-P19/R19,-9) | W19: =IF(S19>0,1-P19/S19,-9) | X19: =IF(T19>0,1-P19/T19,-9) | Y19: =IF(AND($D19=1,H19>0,U19>=p_gm_cen),1,0) | Z19: =IF(AND($D19=1,J19>0,V19>=p_gm_cen),1,0) | AA19: =IF(AND($D19=1,L19>0,W19>=p_gm_dec),1,0) | AB19: =IF(AND($D19=1,N19>0,X19>=p_gm_dec),1,0) | AC19: =AA19*L19*p_mkt*S19*p_rs_succ*p_share_dec | AD19: =AB19*N19*p_mkt*T19*p_rs_succ*p_share_dec | AE19: =Y19*H19*p_mkt*Q19*p_rs_succ*p_realiz | AF19: =Z19*J19*p_mkt*R19*p_rs_succ*p_realiz_minsa | AG19: =IF(S19>0,AC19*P19/S19,0) | AH19: =IF(T19>0,AD19*P19/T19,0) | AI19: =IF(Q19>0,AE19*P19/Q19,0) | AJ19: =IF(R19>0,AF19*P19/R19,0) | AK19: =AC19+AD19+AE19*p_pwin_cen+AF19*p_pwin_cen*p_minsa_occ | AL19: =(AC19-AG19)+(AD19-AH19)+(AE19-AI19)*p_pwin_cen+(AF19-AJ19)*p_pwin_cen*p_minsa_occ | AM19: =IF(P19>0,E19*p_sup_idx*(1+p_pack)/P19,0) | AN19: =IF(AND(Y19=1,H19>0),H19*p_mkt*Q19*p_rs_succ,0)
A20: QTP100 | B20: Quetiapina 100 mg tableta | C20: SNC | D20: 0 | E20: 0.0138 | F20: 0.00066 | G20: R: interpolado de PMBI 25 y 200 mg x1.4 | H20: 0 | I20: 0 | J20: 0 | K20: 0 | L20: 0 | M20: 0 | N20: 509795 | O20: 0.13 | P20: =E20*p_sup_idx*(1+p_pack)+F20*p_log_mult | Q20: =I20*p_pf_cen | R20: =K20*p_pf_cen | S20: =M20*p_pf_dec | T20: =O20*p_pf_dec | U20: =IF(Q20>0,1-P20/Q20,-9) | V20: =IF(R20>0,1-P20/R20,-9) | W20: =IF(S20>0,1-P20/S20,-9) | X20: =IF(T20>0,1-P20/T20,-9) | Y20: =IF(AND($D20=1,H20>0,U20>=p_gm_cen),1,0) | Z20: =IF(AND($D20=1,J20>0,V20>=p_gm_cen),1,0) | AA20: =IF(AND($D20=1,L20>0,W20>=p_gm_dec),1,0) | AB20: =IF(AND($D20=1,N20>0,X20>=p_gm_dec),1,0) | AC20: =AA20*L20*p_mkt*S20*p_rs_succ*p_share_dec | AD20: =AB20*N20*p_mkt*T20*p_rs_succ*p_share_dec | AE20: =Y20*H20*p_mkt*Q20*p_rs_succ*p_realiz | AF20: =Z20*J20*p_mkt*R20*p_rs_succ*p_realiz_minsa | AG20: =IF(S20>0,AC20*P20/S20,0) | AH20: =IF(T20>0,AD20*P20/T20,0) | AI20: =IF(Q20>0,AE20*P20/Q20,0) | AJ20: =IF(R20>0,AF20*P20/R20,0) | AK20: =AC20+AD20+AE20*p_pwin_cen+AF20*p_pwin_cen*p_minsa_occ | AL20: =(AC20-AG20)+(AD20-AH20)+(AE20-AI20)*p_pwin_cen+(AF20-AJ20)*p_pwin_cen*p_minsa_occ | AM20: =IF(P20>0,E20*p_sup_idx*(1+p_pack)/P20,0) | AN20: =IF(AND(Y20=1,H20>0),H20*p_mkt*Q20*p_rs_succ,0)
A21: QTP200 | B21: Quetiapina 200 mg tableta | C21: SNC | D21: 0 | E21: 0.0216 | F21: 0.00075 | G21: R: PMBI 2023-25 INR 14.90 por 10 x1.4 | H21: 1376100 | I21: 0.079 | J21: 0 | K21: 0 | L21: 243829 | M21: 0.21 | N21: 28886 | O21: 0.2 | P21: =E21*p_sup_idx*(1+p_pack)+F21*p_log_mult | Q21: =I21*p_pf_cen | R21: =K21*p_pf_cen | S21: =M21*p_pf_dec | T21: =O21*p_pf_dec | U21: =IF(Q21>0,1-P21/Q21,-9) | V21: =IF(R21>0,1-P21/R21,-9) | W21: =IF(S21>0,1-P21/S21,-9) | X21: =IF(T21>0,1-P21/T21,-9) | Y21: =IF(AND($D21=1,H21>0,U21>=p_gm_cen),1,0) | Z21: =IF(AND($D21=1,J21>0,V21>=p_gm_cen),1,0) | AA21: =IF(AND($D21=1,L21>0,W21>=p_gm_dec),1,0) | AB21: =IF(AND($D21=1,N21>0,X21>=p_gm_dec),1,0) | AC21: =AA21*L21*p_mkt*S21*p_rs_succ*p_share_dec | AD21: =AB21*N21*p_mkt*T21*p_rs_succ*p_share_dec | AE21: =Y21*H21*p_mkt*Q21*p_rs_succ*p_realiz | AF21: =Z21*J21*p_mkt*R21*p_rs_succ*p_realiz_minsa | AG21: =IF(S21>0,AC21*P21/S21,0) | AH21: =IF(T21>0,AD21*P21/T21,0) | AI21: =IF(Q21>0,AE21*P21/Q21,0) | AJ21: =IF(R21>0,AF21*P21/R21,0) | AK21: =AC21+AD21+AE21*p_pwin_cen+AF21*p_pwin_cen*p_minsa_occ | AL21: =(AC21-AG21)+(AD21-AH21)+(AE21-AI21)*p_pwin_cen+(AF21-AJ21)*p_pwin_cen*p_minsa_occ | AM21: =IF(P21>0,E21*p_sup_idx*(1+p_pack)/P21,0) | AN21: =IF(AND(Y21=1,H21>0),H21*p_mkt*Q21*p_rs_succ,0)
A22: TPM100 | B22: Topiramato 100 mg tableta | C22: SNC | D22: 0 | E22: 0.0116 | F22: 0.0006 | G22: R: PMBI 2023-25 INR 7.98 por 10 x1.4 | H22: 443907 | I22: 0.065 | J22: 0 | K22: 0 | L22: 26343 | M22: 1.02 | N22: 4640 | O22: 1.18 | P22: =E22*p_sup_idx*(1+p_pack)+F22*p_log_mult | Q22: =I22*p_pf_cen | R22: =K22*p_pf_cen | S22: =M22*p_pf_dec | T22: =O22*p_pf_dec | U22: =IF(Q22>0,1-P22/Q22,-9) | V22: =IF(R22>0,1-P22/R22,-9) | W22: =IF(S22>0,1-P22/S22,-9) | X22: =IF(T22>0,1-P22/T22,-9) | Y22: =IF(AND($D22=1,H22>0,U22>=p_gm_cen),1,0) | Z22: =IF(AND($D22=1,J22>0,V22>=p_gm_cen),1,0) | AA22: =IF(AND($D22=1,L22>0,W22>=p_gm_dec),1,0) | AB22: =IF(AND($D22=1,N22>0,X22>=p_gm_dec),1,0) | AC22: =AA22*L22*p_mkt*S22*p_rs_succ*p_share_dec | AD22: =AB22*N22*p_mkt*T22*p_rs_succ*p_share_dec | AE22: =Y22*H22*p_mkt*Q22*p_rs_succ*p_realiz | AF22: =Z22*J22*p_mkt*R22*p_rs_succ*p_realiz_minsa | AG22: =IF(S22>0,AC22*P22/S22,0) | AH22: =IF(T22>0,AD22*P22/T22,0) | AI22: =IF(Q22>0,AE22*P22/Q22,0) | AJ22: =IF(R22>0,AF22*P22/R22,0) | AK22: =AC22+AD22+AE22*p_pwin_cen+AF22*p_pwin_cen*p_minsa_occ | AL22: =(AC22-AG22)+(AD22-AH22)+(AE22-AI22)*p_pwin_cen+(AF22-AJ22)*p_pwin_cen*p_minsa_occ | AM22: =IF(P22>0,E22*p_sup_idx*(1+p_pack)/P22,0) | AN22: =IF(AND(Y22=1,H22>0),H22*p_mkt*Q22*p_rs_succ,0)
B23: Totales (productos incluidos) | AC23: =SUM(AC6:AC22) | AD23: =SUM(AD6:AD22) | AE23: =SUM(AE6:AE22) | AF23: =SUM(AF6:AF22) | AG23: =SUM(AG6:AG22) | AH23: =SUM(AH6:AH22) | AI23: =SUM(AI6:AI22) | AJ23: =SUM(AJ6:AJ22) | ... AL23: =SUM(AL6:AL22) | AM23: =IF(SUM(AG6:AJ22)>0,SUMPRODUCT(AG6:AG22+AH6:AH22+AI6:AI22+AJ6:AJ22,AM6:AM22)/SUM(AG6:AJ22),0) | AN23: =SUM(AN6:AN22)

Sheet Mensual
A1: Flujo mensual (B/.)
C2: Mes 0
A3: Mes | C3: 0 | D3: 1 | E3: 2 | F3: 3 | G3: 4 | H3: 5 | I3: 6 | J3: 7 | K3: 8 | L3: 9 | M3: 10 | N3: 11 | O3: 12 | P3: 13 | Q3: 14 | R3: 15 | S3: 16 | T3: 17 | U3: 18 | V3: 19 | W3: 20 | X3: 21 | Y3: 22 | Z3: 23 | AA3: 24 | AB3: 25 | AC3: 26 | AD3: 27 | AE3: 28 | AF3: 29 | AG3: 30 | AH3: 31 | AI3: 32 | AJ3: 33 | AK3: 34 | AL3: 35 | AM3: 36 | AN3: 37 | AO3: 38 | AP3: 39 | AQ3: 40 | AR3: 41 | AS3: 42 | AT3: 43 | AU3: 44 | AV3: 45 | AW3: 46 | AX3: 47 | AY3: 48 | AZ3: 49 | BA3: 50 | BB3: 51 | BC3: 52 | BD3: 53 | BE3: 54 | BF3: 55 | BG3: 56 | BH3: 57 | BI3: 58 | BJ3: 59 | BK3: 60 | BL3: 61
A4: Año | D4: =INT((MIN(D$3,60)-1)/12)+1 | E4: =INT((MIN(E$3,60)-1)/12)+1 | F4: =INT((MIN(F$3,60)-1)/12)+1 | G4: =INT((MIN(G$3,60)-1)/12)+1 | H4: =INT((MIN(H$3,60)-1)/12)+1 | I4: =INT((MIN(I$3,60)-1)/12)+1 | J4: =INT((MIN(J$3,60)-1)/12)+1 | K4: =INT((MIN(K$3,60)-1)/12)+1 | ... BL4: =INT((MIN(BL$3,60)-1)/12)+1
A5: Factor de erosión de precios | D5: =(1-p_erosion)^(D4-1) | E5: =(1-p_erosion)^(E4-1) | F5: =(1-p_erosion)^(F4-1) | G5: =(1-p_erosion)^(G4-1) | H5: =(1-p_erosion)^(H4-1) | I5: =(1-p_erosion)^(I4-1) | J5: =(1-p_erosion)^(J4-1) | K5: =(1-p_erosion)^(K4-1) | ... BL5: =(1-p_erosion)^(BL4-1)
A6: Negocio activo (1/0) | D6: =IF(D$3<=ROUND(p_stop_det,0),1,0) | E6: =IF(E$3<=ROUND(p_stop_det,0),1,0) | F6: =IF(F$3<=ROUND(p_stop_det,0),1,0) | G6: =IF(G$3<=ROUND(p_stop_det,0),1,0) | H6: =IF(H$3<=ROUND(p_stop_det,0),1,0) | I6: =IF(I$3<=ROUND(p_stop_det,0),1,0) | J6: =IF(J$3<=ROUND(p_stop_det,0),1,0) | K6: =IF(K$3<=ROUND(p_stop_det,0),1,0) | ... BL6: =IF(BL$3<=ROUND(p_stop_det,0),1,0)
A7: Rampa primera ola | D7: =MAX(0,MIN(1,(D$3-c_first_dec+1)/p_ramp_m)) | E7: =MAX(0,MIN(1,(E$3-c_first_dec+1)/p_ramp_m)) | F7: =MAX(0,MIN(1,(F$3-c_first_dec+1)/p_ramp_m)) | G7: =MAX(0,MIN(1,(G$3-c_first_dec+1)/p_ramp_m)) | H7: =MAX(0,MIN(1,(H$3-c_first_dec+1)/p_ramp_m)) | I7: =MAX(0,MIN(1,(I$3-c_first_dec+1)/p_ramp_m)) | J7: =MAX(0,MIN(1,(J$3-c_first_dec+1)/p_ramp_m)) | K7: =MAX(0,MIN(1,(K$3-c_first_dec+1)/p_ramp_m)) | ... BL7: =MAX(0,MIN(1,(BL$3-c_first_dec+1)/p_ramp_m))
A8: Rampa segunda ola | D8: =MAX(0,MIN(1,(D$3-c_first_dec2+1)/p_ramp_m)) | E8: =MAX(0,MIN(1,(E$3-c_first_dec2+1)/p_ramp_m)) | F8: =MAX(0,MIN(1,(F$3-c_first_dec2+1)/p_ramp_m)) | G8: =MAX(0,MIN(1,(G$3-c_first_dec2+1)/p_ramp_m)) | H8: =MAX(0,MIN(1,(H$3-c_first_dec2+1)/p_ramp_m)) | I8: =MAX(0,MIN(1,(I$3-c_first_dec2+1)/p_ramp_m)) | J8: =MAX(0,MIN(1,(J$3-c_first_dec2+1)/p_ramp_m)) | K8: =MAX(0,MIN(1,(K$3-c_first_dec2+1)/p_ramp_m)) | ... BL8: =MAX(0,MIN(1,(BL$3-c_first_dec2+1)/p_ramp_m))
A9: Contratos centralizados activos | D9: =IF(D$3>=c_cen_start,1,0) | E9: =IF(E$3>=c_cen_start,1,0) | F9: =IF(F$3>=c_cen_start,1,0) | G9: =IF(G$3>=c_cen_start,1,0) | H9: =IF(H$3>=c_cen_start,1,0) | I9: =IF(I$3>=c_cen_start,1,0) | J9: =IF(J$3>=c_cen_start,1,0) | K9: =IF(K$3>=c_cen_start,1,0) | ... BL9: =IF(BL$3>=c_cen_start,1,0)
A10: LPU con segunda ola | D10: =IF(D$3>=c_c2_lpu,1,0) | E10: =IF(E$3>=c_c2_lpu,1,0) | F10: =IF(F$3>=c_c2_lpu,1,0) | G10: =IF(G$3>=c_c2_lpu,1,0) | H10: =IF(H$3>=c_c2_lpu,1,0) | I10: =IF(I$3>=c_c2_lpu,1,0) | J10: =IF(J$3>=c_c2_lpu,1,0) | K10: =IF(K$3>=c_c2_lpu,1,0) | ... BL10: =IF(BL$3>=c_c2_lpu,1,0)
A11: MINSA central con segunda ola | D11: =IF(D$3>=c_c2_minsa,1,0) | E11: =IF(E$3>=c_c2_minsa,1,0) | F11: =IF(F$3>=c_c2_minsa,1,0) | G11: =IF(G$3>=c_c2_minsa,1,0) | H11: =IF(H$3>=c_c2_minsa,1,0) | I11: =IF(I$3>=c_c2_minsa,1,0) | J11: =IF(J$3>=c_c2_minsa,1,0) | K11: =IF(K$3>=c_c2_minsa,1,0) | ... BL11: =IF(BL$3>=c_c2_minsa,1,0)
A12: Multiplicador descentralizado (olas) | D12: =1+c_k2*D8 | E12: =1+c_k2*E8 | F12: =1+c_k2*F8 | G12: =1+c_k2*G8 | H12: =1+c_k2*H8 | I12: =1+c_k2*I8 | J12: =1+c_k2*J8 | K12: =1+c_k2*K8 | ... BL12: =1+c_k2*BL8
A13: Multiplicador LPU (olas) | D13: =1+c_k2*D10 | E13: =1+c_k2*E10 | F13: =1+c_k2*F10 | G13: =1+c_k2*G10 | H13: =1+c_k2*H10 | I13: =1+c_k2*I10 | J13: =1+c_k2*J10 | K13: =1+c_k2*K10 | ... BL13: =1+c_k2*BL10
A14: Multiplicador MINSA central (olas) | D14: =1+c_k2*D11 | E14: =1+c_k2*E11 | F14: =1+c_k2*F11 | G14: =1+c_k2*G11 | H14: =1+c_k2*H11 | I14: =1+c_k2*I11 | J14: =1+c_k2*J11 | K14: =1+c_k2*K11 | ... BL14: =1+c_k2*BL11
A15: Ventas descentralizadas | D15: =(s_Rd3+s_Rd4)/12*D7*D12*D5*D6 | E15: =(s_Rd3+s_Rd4)/12*E7*E12*E5*E6 | F15: =(s_Rd3+s_Rd4)/12*F7*F12*F5*F6 | G15: =(s_Rd3+s_Rd4)/12*G7*G12*G5*G6 | H15: =(s_Rd3+s_Rd4)/12*H7*H12*H5*H6 | I15: =(s_Rd3+s_Rd4)/12*I7*I12*I5*I6 | J15: =(s_Rd3+s_Rd4)/12*J7*J12*J5*J6 | K15: =(s_Rd3+s_Rd4)/12*K7*K12*K5*K6 | ... BL15: =(s_Rd3+s_Rd4)/12*BL7*BL12*BL5*BL6
A16: Ventas centralizadas | D16: =(s_Rc1*p_pwin_cen*D13+s_Rc2*p_pwin_cen*p_minsa_occ*D14)/12*D9*D5*D6 | E16: =(s_Rc1*p_pwin_cen*E13+s_Rc2*p_pwin_cen*p_minsa_occ*E14)/12*E9*E5*E6 | F16: =(s_Rc1*p_pwin_cen*F13+s_Rc2*p_pwin_cen*p_minsa_occ*F14)/12*F9*F5*F6 | G16: =(s_Rc1*p_pwin_cen*G13+s_Rc2*p_pwin_cen*p_minsa_occ*G14)/12*G9*G5*G6 | H16: =(s_Rc1*p_pwin_cen*H13+s_Rc2*p_pwin_cen*p_minsa_occ*H14)/12*H9*H5*H6 | I16: =(s_Rc1*p_pwin_cen*I13+s_Rc2*p_pwin_cen*p_minsa_occ*I14)/12*I9*I5*I6 | J16: =(s_Rc1*p_pwin_cen*J13+s_Rc2*p_pwin_cen*p_minsa_occ*J14)/12*J9*J5*J6 | K16: =(s_Rc1*p_pwin_cen*K13+s_Rc2*p_pwin_cen*p_minsa_occ*K14)/12*K9*K5*K6 | ... BL16: =(s_Rc1*p_pwin_cen*BL13+s_Rc2*p_pwin_cen*p_minsa_occ*BL14)/12*BL9*BL5*BL6
A17: VENTAS TOTALES | D17: =D15+D16 | E17: =E15+E16 | F17: =F15+F16 | G17: =G15+G16 | H17: =H15+H16 | I17: =I15+I16 | J17: =J15+J16 | K17: =K15+K16 | ... BL17: =BL15+BL16
A18: Costo de ventas descentralizado | D18: =(s_Rd3k+s_Rd4k)/12*D7*D12*D6 | E18: =(s_Rd3k+s_Rd4k)/12*E7*E12*E6 | F18: =(s_Rd3k+s_Rd4k)/12*F7*F12*F6 | G18: =(s_Rd3k+s_Rd4k)/12*G7*G12*G6 | H18: =(s_Rd3k+s_Rd4k)/12*H7*H12*H6 | I18: =(s_Rd3k+s_Rd4k)/12*I7*I12*I6 | J18: =(s_Rd3k+s_Rd4k)/12*J7*J12*J6 | K18: =(s_Rd3k+s_Rd4k)/12*K7*K12*K6 | ... BL18: =(s_Rd3k+s_Rd4k)/12*BL7*BL12*BL6
A19: Costo de ventas centralizado | D19: =(s_Rc1k*p_pwin_cen*D13+s_Rc2k*p_pwin_cen*p_minsa_occ*D14)/12*D9*D6 | E19: =(s_Rc1k*p_pwin_cen*E13+s_Rc2k*p_pwin_cen*p_minsa_occ*E14)/12*E9*E6 | F19: =(s_Rc1k*p_pwin_cen*F13+s_Rc2k*p_pwin_cen*p_minsa_occ*F14)/12*F9*F6 | G19: =(s_Rc1k*p_pwin_cen*G13+s_Rc2k*p_pwin_cen*p_minsa_occ*G14)/12*G9*G6 | H19: =(s_Rc1k*p_pwin_cen*H13+s_Rc2k*p_pwin_cen*p_minsa_occ*H14)/12*H9*H6 | I19: =(s_Rc1k*p_pwin_cen*I13+s_Rc2k*p_pwin_cen*p_minsa_occ*I14)/12*I9*I6 | J19: =(s_Rc1k*p_pwin_cen*J13+s_Rc2k*p_pwin_cen*p_minsa_occ*J14)/12*J9*J6 | K19: =(s_Rc1k*p_pwin_cen*K13+s_Rc2k*p_pwin_cen*p_minsa_occ*K14)/12*K9*K6 | ... BL19: =(s_Rc1k*p_pwin_cen*BL13+s_Rc2k*p_pwin_cen*p_minsa_occ*BL14)/12*BL9*BL6
A20: COSTO DE VENTAS | D20: =D18+D19 | E20: =E18+E19 | F20: =F18+F19 | G20: =G18+G19 | H20: =H18+H19 | I20: =I18+I19 | J20: =J18+J19 | K20: =K18+K19 | ... BL20: =BL18+BL19
A21: Inventario objetivo al cierre (costo) | C21: 0 | D21: =IF(AND(D$3>=c_first_dec,D$3<=ROUND(p_stop_det,0)),(s_Rd3k+s_Rd4k)/12*E7*E12*p_cover_m+(s_Rc1k*p_pwin_cen*E13+s_Rc2k*p_pwin_cen*p_minsa_occ*E14)/12*E9*p_cen_stock_m,0) | E21: =IF(AND(E$3>=c_first_dec,E$3<=ROUND(p_stop_det,0)),(s_Rd3k+s_Rd4k)/12*F7*F12*p_cover_m+(s_Rc1k*p_pwin_cen*F13+s_Rc2k*p_pwin_cen*p_minsa_occ*F14)/12*F9*p_cen_stock_m,0) | F21: =IF(AND(F$3>=c_first_dec,F$3<=ROUND(p_stop_det,0)),(s_Rd3k+s_Rd4k)/12*G7*G12*p_cover_m+(s_Rc1k*p_pwin_cen*G13+s_Rc2k*p_pwin_cen*p_minsa_occ*G14)/12*G9*p_cen_stock_m,0) | G21: =IF(AND(G$3>=c_first_dec,G$3<=ROUND(p_stop_det,0)),(s_Rd3k+s_Rd4k)/12*H7*H12*p_cover_m+(s_Rc1k*p_pwin_cen*H13+s_Rc2k*p_pwin_cen*p_minsa_occ*H14)/12*H9*p_cen_stock_m,0) | H21: =IF(AND(H$3>=c_first_dec,H$3<=ROUND(p_stop_det,0)),(s_Rd3k+s_Rd4k)/12*I7*I12*p_cover_m+(s_Rc1k*p_pwin_cen*I13+s_Rc2k*p_pwin_cen*p_minsa_occ*I14)/12*I9*p_cen_stock_m,0) | I21: =IF(AND(I$3>=c_first_dec,I$3<=ROUND(p_stop_det,0)),(s_Rd3k+s_Rd4k)/12*J7*J12*p_cover_m+(s_Rc1k*p_pwin_cen*J13+s_Rc2k*p_pwin_cen*p_minsa_occ*J14)/12*J9*p_cen_stock_m,0) | J21: =IF(AND(J$3>=c_first_dec,J$3<=ROUND(p_stop_det,0)),(s_Rd3k+s_Rd4k)/12*K7*K12*p_cover_m+(s_Rc1k*p_pwin_cen*K13+s_Rc2k*p_pwin_cen*p_minsa_occ*K14)/12*K9*p_cen_stock_m,0) | K21: =IF(AND(K$3>=c_first_dec,K$3<=ROUND(p_stop_det,0)),(s_Rd3k+s_Rd4k)/12*L7*L12*p_cover_m+(s_Rc1k*p_pwin_cen*L13+s_Rc2k*p_pwin_cen*p_minsa_occ*L14)/12*L9*p_cen_stock_m,0) | ... BK21: =IF(AND(BK$3>=c_first_dec,BK$3<=ROUND(p_stop_det,0)),(s_Rd3k+s_Rd4k)/12*BL7*BL12*p_cover_m+(s_Rc1k*p_pwin_cen*BL13+s_Rc2k*p_pwin_cen*p_minsa_occ*BL14)/12*BL9*p_cen_stock_m,0)
A22: Mercancía recibida (costo, incl. mermas) | D22: =IF(D$3>ROUND(p_stop_det,0),0,D20*(1+p_expiry)+D21-C21) | E22: =IF(E$3>ROUND(p_stop_det,0),0,E20*(1+p_expiry)+E21-D21) | F22: =IF(F$3>ROUND(p_stop_det,0),0,F20*(1+p_expiry)+F21-E21) | G22: =IF(G$3>ROUND(p_stop_det,0),0,G20*(1+p_expiry)+G21-F21) | H22: =IF(H$3>ROUND(p_stop_det,0),0,H20*(1+p_expiry)+H21-G21) | I22: =IF(I$3>ROUND(p_stop_det,0),0,I20*(1+p_expiry)+I21-H21) | J22: =IF(J$3>ROUND(p_stop_det,0),0,J20*(1+p_expiry)+J21-I21) | K22: =IF(K$3>ROUND(p_stop_det,0),0,K20*(1+p_expiry)+K21-J21) | ... BK22: =IF(BK$3>ROUND(p_stop_det,0),0,BK20*(1+p_expiry)+BK21-BJ21)
A23: Pago de anticipos al proveedor | D23: =p_adv*IFERROR(INDEX($D$22:$BK$22,1,D$3+c_lead_m),0) | E23: =p_adv*IFERROR(INDEX($D$22:$BK$22,1,E$3+c_lead_m),0) | F23: =p_adv*IFERROR(INDEX($D$22:$BK$22,1,F$3+c_lead_m),0) | G23: =p_adv*IFERROR(INDEX($D$22:$BK$22,1,G$3+c_lead_m),0) | H23: =p_adv*IFERROR(INDEX($D$22:$BK$22,1,H$3+c_lead_m),0) | I23: =p_adv*IFERROR(INDEX($D$22:$BK$22,1,I$3+c_lead_m),0) | J23: =p_adv*IFERROR(INDEX($D$22:$BK$22,1,J$3+c_lead_m),0) | K23: =p_adv*IFERROR(INDEX($D$22:$BK$22,1,K$3+c_lead_m),0) | ... BK23: =p_adv*IFERROR(INDEX($D$22:$BK$22,1,BK$3+c_lead_m),0)
A24: Pago de saldos al proveedor | D24: =IF(AND(D$3+c_ship_m-c_credit_m>=1,D$3+c_ship_m-c_credit_m<=60),(1-p_adv)*INDEX($D$22:$BK$22,1,D$3+c_ship_m-c_credit_m),0) | E24: =IF(AND(E$3+c_ship_m-c_credit_m>=1,E$3+c_ship_m-c_credit_m<=60),(1-p_adv)*INDEX($D$22:$BK$22,1,E$3+c_ship_m-c_credit_m),0) | F24: =IF(AND(F$3+c_ship_m-c_credit_m>=1,F$3+c_ship_m-c_credit_m<=60),(1-p_adv)*INDEX($D$22:$BK$22,1,F$3+c_ship_m-c_credit_m),0) | G24: =IF(AND(G$3+c_ship_m-c_credit_m>=1,G$3+c_ship_m-c_credit_m<=60),(1-p_adv)*INDEX($D$22:$BK$22,1,G$3+c_ship_m-c_credit_m),0) | H24: =IF(AND(H$3+c_ship_m-c_credit_m>=1,H$3+c_ship_m-c_credit_m<=60),(1-p_adv)*INDEX($D$22:$BK$22,1,H$3+c_ship_m-c_credit_m),0) | I24: =IF(AND(I$3+c_ship_m-c_credit_m>=1,I$3+c_ship_m-c_credit_m<=60),(1-p_adv)*INDEX($D$22:$BK$22,1,I$3+c_ship_m-c_credit_m),0) | J24: =IF(AND(J$3+c_ship_m-c_credit_m>=1,J$3+c_ship_m-c_credit_m<=60),(1-p_adv)*INDEX($D$22:$BK$22,1,J$3+c_ship_m-c_credit_m),0) | K24: =IF(AND(K$3+c_ship_m-c_credit_m>=1,K$3+c_ship_m-c_credit_m<=60),(1-p_adv)*INDEX($D$22:$BK$22,1,K$3+c_ship_m-c_credit_m),0) | ... BK24: =IF(AND(BK$3+c_ship_m-c_credit_m>=1,BK$3+c_ship_m-c_credit_m<=60),(1-p_adv)*INDEX($D$22:$BK$22,1,BK$3+c_ship_m-c_credit_m),0)
A25: PAGOS AL PROVEEDOR | D25: =D23+D24 | E25: =E23+E24 | F25: =F23+F24 | G25: =G23+G24 | H25: =H23+H24 | I25: =I23+I24 | J25: =J23+J24 | K25: =K23+K24 | ... BK25: =BK23+BK24
A26: COBRANZA (incl. liquidación de inventario al cierre) | D26: =(1-p_fact_share)*IF(D$3-c_dso_m>=1,INDEX($D$17:$BK$17,1,D$3-c_dso_m),0)*(1-p_baddebt)+p_fact_share*IF(D$3-1>=1,INDEX($D$17:$BK$17,1,D$3-1),0)*(1-p_baddebt)*(1-p_fact_cost*c_dso_m)+IF(D$3=ROUND(p_stop_det,0)+1,INDEX($D$21:$BK$21,1,ROUND(p_stop_det,0))*p_inv_liq,0) | E26: =(1-p_fact_share)*IF(E$3-c_dso_m>=1,INDEX($D$17:$BK$17,1,E$3-c_dso_m),0)*(1-p_baddebt)+p_fact_share*IF(E$3-1>=1,INDEX($D$17:$BK$17,1,E$3-1),0)*(1-p_baddebt)*(1-p_fact_cost*c_dso_m)+IF(E$3=ROUND(p_stop_det,0)+1,INDEX($D$21:$BK$21,1,ROUND(p_stop_det,0))*p_inv_liq,0) | F26: =(1-p_fact_share)*IF(F$3-c_dso_m>=1,INDEX($D$17:$BK$17,1,F$3-c_dso_m),0)*(1-p_baddebt)+p_fact_share*IF(F$3-1>=1,INDEX($D$17:$BK$17,1,F$3-1),0)*(1-p_baddebt)*(1-p_fact_cost*c_dso_m)+IF(F$3=ROUND(p_stop_det,0)+1,INDEX($D$21:$BK$21,1,ROUND(p_stop_det,0))*p_inv_liq,0) | G26: =(1-p_fact_share)*IF(G$3-c_dso_m>=1,INDEX($D$17:$BK$17,1,G$3-c_dso_m),0)*(1-p_baddebt)+p_fact_share*IF(G$3-1>=1,INDEX($D$17:$BK$17,1,G$3-1),0)*(1-p_baddebt)*(1-p_fact_cost*c_dso_m)+IF(G$3=ROUND(p_stop_det,0)+1,INDEX($D$21:$BK$21,1,ROUND(p_stop_det,0))*p_inv_liq,0) | H26: =(1-p_fact_share)*IF(H$3-c_dso_m>=1,INDEX($D$17:$BK$17,1,H$3-c_dso_m),0)*(1-p_baddebt)+p_fact_share*IF(H$3-1>=1,INDEX($D$17:$BK$17,1,H$3-1),0)*(1-p_baddebt)*(1-p_fact_cost*c_dso_m)+IF(H$3=ROUND(p_stop_det,0)+1,INDEX($D$21:$BK$21,1,ROUND(p_stop_det,0))*p_inv_liq,0) | I26: =(1-p_fact_share)*IF(I$3-c_dso_m>=1,INDEX($D$17:$BK$17,1,I$3-c_dso_m),0)*(1-p_baddebt)+p_fact_share*IF(I$3-1>=1,INDEX($D$17:$BK$17,1,I$3-1),0)*(1-p_baddebt)*(1-p_fact_cost*c_dso_m)+IF(I$3=ROUND(p_stop_det,0)+1,INDEX($D$21:$BK$21,1,ROUND(p_stop_det,0))*p_inv_liq,0) | J26: =(1-p_fact_share)*IF(J$3-c_dso_m>=1,INDEX($D$17:$BK$17,1,J$3-c_dso_m),0)*(1-p_baddebt)+p_fact_share*IF(J$3-1>=1,INDEX($D$17:$BK$17,1,J$3-1),0)*(1-p_baddebt)*(1-p_fact_cost*c_dso_m)+IF(J$3=ROUND(p_stop_det,0)+1,INDEX($D$21:$BK$21,1,ROUND(p_stop_det,0))*p_inv_liq,0) | K26: =(1-p_fact_share)*IF(K$3-c_dso_m>=1,INDEX($D$17:$BK$17,1,K$3-c_dso_m),0)*(1-p_baddebt)+p_fact_share*IF(K$3-1>=1,INDEX($D$17:$BK$17,1,K$3-1),0)*(1-p_baddebt)*(1-p_fact_cost*c_dso_m)+IF(K$3=ROUND(p_stop_det,0)+1,INDEX($D$21:$BK$21,1,ROUND(p_stop_det,0))*p_inv_liq,0) | ... BK26: =(1-p_fact_share)*IF(BK$3-c_dso_m>=1,INDEX($D$17:$BK$17,1,BK$3-c_dso_m),0)*(1-p_baddebt)+p_fact_share*IF(BK$3-1>=1,INDEX($D$17:$BK$17,1,BK$3-1),0)*(1-p_baddebt)*(1-p_fact_cost*c_dso_m)+IF(BK$3=ROUND(p_stop_det,0)+1,INDEX($D$21:$BK$21,1,ROUND(p_stop_det,0))*p_inv_liq,0)
A27: Gastos variables (distribución y multas) | D27: =(p_dist+p_penal)*D17 | E27: =(p_dist+p_penal)*E17 | F27: =(p_dist+p_penal)*F17 | G27: =(p_dist+p_penal)*G17 | H27: =(p_dist+p_penal)*H17 | I27: =(p_dist+p_penal)*I17 | J27: =(p_dist+p_penal)*J17 | K27: =(p_dist+p_penal)*K17 | ... BK27: =(p_dist+p_penal)*BK17
A28: Costos fijos | D28: =IF(D$3>ROUND(p_stop_det,0)+3,0,SUMPRODUCT(f_used*(D$3>=f_start))) | E28: =IF(E$3>ROUND(p_stop_det,0)+3,0,SUMPRODUCT(f_used*(E$3>=f_start))) | F28: =IF(F$3>ROUND(p_stop_det,0)+3,0,SUMPRODUCT(f_used*(F$3>=f_start))) | G28: =IF(G$3>ROUND(p_stop_det,0)+3,0,SUMPRODUCT(f_used*(G$3>=f_start))) | H28: =IF(H$3>ROUND(p_stop_det,0)+3,0,SUMPRODUCT(f_used*(H$3>=f_start))) | I28: =IF(I$3>ROUND(p_stop_det,0)+3,0,SUMPRODUCT(f_used*(I$3>=f_start))) | J28: =IF(J$3>ROUND(p_stop_det,0)+3,0,SUMPRODUCT(f_used*(J$3>=f_start))) | K28: =IF(K$3>ROUND(p_stop_det,0)+3,0,SUMPRODUCT(f_used*(K$3>=f_start))) | ... BK28: =IF(BK$3>ROUND(p_stop_det,0)+3,0,SUMPRODUCT(f_used*(BK$3>=f_start)))
A29: Análisis posregistro | D29: =IF(D$3>ROUND(p_stop_det,0)+3,0,c_n_reg1*p_postreg/12*IF(D$3>=c_reg_m,1,0)+c_n_reg2*p_postreg/12*IF(D$3>=c_m2+c_rt,1,0)) | E29: =IF(E$3>ROUND(p_stop_det,0)+3,0,c_n_reg1*p_postreg/12*IF(E$3>=c_reg_m,1,0)+c_n_reg2*p_postreg/12*IF(E$3>=c_m2+c_rt,1,0)) | F29: =IF(F$3>ROUND(p_stop_det,0)+3,0,c_n_reg1*p_postreg/12*IF(F$3>=c_reg_m,1,0)+c_n_reg2*p_postreg/12*IF(F$3>=c_m2+c_rt,1,0)) | G29: =IF(G$3>ROUND(p_stop_det,0)+3,0,c_n_reg1*p_postreg/12*IF(G$3>=c_reg_m,1,0)+c_n_reg2*p_postreg/12*IF(G$3>=c_m2+c_rt,1,0)) | H29: =IF(H$3>ROUND(p_stop_det,0)+3,0,c_n_reg1*p_postreg/12*IF(H$3>=c_reg_m,1,0)+c_n_reg2*p_postreg/12*IF(H$3>=c_m2+c_rt,1,0)) | I29: =IF(I$3>ROUND(p_stop_det,0)+3,0,c_n_reg1*p_postreg/12*IF(I$3>=c_reg_m,1,0)+c_n_reg2*p_postreg/12*IF(I$3>=c_m2+c_rt,1,0)) | J29: =IF(J$3>ROUND(p_stop_det,0)+3,0,c_n_reg1*p_postreg/12*IF(J$3>=c_reg_m,1,0)+c_n_reg2*p_postreg/12*IF(J$3>=c_m2+c_rt,1,0)) | K29: =IF(K$3>ROUND(p_stop_det,0)+3,0,c_n_reg1*p_postreg/12*IF(K$3>=c_reg_m,1,0)+c_n_reg2*p_postreg/12*IF(K$3>=c_m2+c_rt,1,0)) | ... BK29: =IF(BK$3>ROUND(p_stop_det,0)+3,0,c_n_reg1*p_postreg/12*IF(BK$3>=c_reg_m,1,0)+c_n_reg2*p_postreg/12*IF(BK$3>=c_m2+c_rt,1,0))
A30: Gastos de arranque | D30: =SUMIF(u_month,D$3,u_used) | E30: =SUMIF(u_month,E$3,u_used) | F30: =SUMIF(u_month,F$3,u_used) | G30: =SUMIF(u_month,G$3,u_used) | H30: =SUMIF(u_month,H$3,u_used) | I30: =SUMIF(u_month,I$3,u_used) | J30: =SUMIF(u_month,J$3,u_used) | K30: =SUMIF(u_month,K$3,u_used) | ... BK30: =SUMIF(u_month,BK$3,u_used)
A31: Registros sanitarios | D31: =IF(D$3=c_rs_pay_m,SUM(SKUs!$D$6:$D$24)*c_rs_unit,0)+IF(D$3=MAX(1,MIN(60,c_m2)),p_n2*c_rs_unit,0) | E31: =IF(E$3=c_rs_pay_m,SUM(SKUs!$D$6:$D$24)*c_rs_unit,0)+IF(E$3=MAX(1,MIN(60,c_m2)),p_n2*c_rs_unit,0) | F31: =IF(F$3=c_rs_pay_m,SUM(SKUs!$D$6:$D$24)*c_rs_unit,0)+IF(F$3=MAX(1,MIN(60,c_m2)),p_n2*c_rs_unit,0) | G31: =IF(G$3=c_rs_pay_m,SUM(SKUs!$D$6:$D$24)*c_rs_unit,0)+IF(G$3=MAX(1,MIN(60,c_m2)),p_n2*c_rs_unit,0) | H31: =IF(H$3=c_rs_pay_m,SUM(SKUs!$D$6:$D$24)*c_rs_unit,0)+IF(H$3=MAX(1,MIN(60,c_m2)),p_n2*c_rs_unit,0) | I31: =IF(I$3=c_rs_pay_m,SUM(SKUs!$D$6:$D$24)*c_rs_unit,0)+IF(I$3=MAX(1,MIN(60,c_m2)),p_n2*c_rs_unit,0) | J31: =IF(J$3=c_rs_pay_m,SUM(SKUs!$D$6:$D$24)*c_rs_unit,0)+IF(J$3=MAX(1,MIN(60,c_m2)),p_n2*c_rs_unit,0) | K31: =IF(K$3=c_rs_pay_m,SUM(SKUs!$D$6:$D$24)*c_rs_unit,0)+IF(K$3=MAX(1,MIN(60,c_m2)),p_n2*c_rs_unit,0) | ... BK31: =IF(BK$3=c_rs_pay_m,SUM(SKUs!$D$6:$D$24)*c_rs_unit,0)+IF(BK$3=MAX(1,MIN(60,c_m2)),p_n2*c_rs_unit,0)
A32: Cargos anuales | D32: =IF(D$3>ROUND(p_stop_det,0)+3,0,IF(OR(D$3=1,D$3=13,D$3=25,D$3=37,D$3=49),c_annual,0)) | E32: =IF(E$3>ROUND(p_stop_det,0)+3,0,IF(OR(E$3=1,E$3=13,E$3=25,E$3=37,E$3=49),c_annual,0)) | F32: =IF(F$3>ROUND(p_stop_det,0)+3,0,IF(OR(F$3=1,F$3=13,F$3=25,F$3=37,F$3=49),c_annual,0)) | G32: =IF(G$3>ROUND(p_stop_det,0)+3,0,IF(OR(G$3=1,G$3=13,G$3=25,G$3=37,G$3=49),c_annual,0)) | H32: =IF(H$3>ROUND(p_stop_det,0)+3,0,IF(OR(H$3=1,H$3=13,H$3=25,H$3=37,H$3=49),c_annual,0)) | I32: =IF(I$3>ROUND(p_stop_det,0)+3,0,IF(OR(I$3=1,I$3=13,I$3=25,I$3=37,I$3=49),c_annual,0)) | J32: =IF(J$3>ROUND(p_stop_det,0)+3,0,IF(OR(J$3=1,J$3=13,J$3=25,J$3=37,J$3=49),c_annual,0)) | K32: =IF(K$3>ROUND(p_stop_det,0)+3,0,IF(OR(K$3=1,K$3=13,K$3=25,K$3=37,K$3=49),c_annual,0)) | ... BK32: =IF(BK$3>ROUND(p_stop_det,0)+3,0,IF(OR(BK$3=1,BK$3=13,BK$3=25,BK$3=37,BK$3=49),c_annual,0))
A33: Monto afianzado (cumplimiento, sobre la cantidad máxima) | D33: =(s_Rc1/p_realiz*p_pwin_cen*p_bond_css*15/12*D13*(1+IF(AND(D$3-c_cen_start>=15,MOD(D$3-c_cen_start,15)<ROUND(p_bond_tail_css,0)),1,0))+s_Rc2/p_realiz_minsa*p_pwin_cen*p_minsa_occ*p_bond_minsa*D14*(1+IF(AND(D$3-c_cen_start>=12,MOD(D$3-c_cen_start,12)<ROUND(p_bond_tail_minsa,0)),1,0)))*D9*D6 | E33: =(s_Rc1/p_realiz*p_pwin_cen*p_bond_css*15/12*E13*(1+IF(AND(E$3-c_cen_start>=15,MOD(E$3-c_cen_start,15)<ROUND(p_bond_tail_css,0)),1,0))+s_Rc2/p_realiz_minsa*p_pwin_cen*p_minsa_occ*p_bond_minsa*E14*(1+IF(AND(E$3-c_cen_start>=12,MOD(E$3-c_cen_start,12)<ROUND(p_bond_tail_minsa,0)),1,0)))*E9*E6 | F33: =(s_Rc1/p_realiz*p_pwin_cen*p_bond_css*15/12*F13*(1+IF(AND(F$3-c_cen_start>=15,MOD(F$3-c_cen_start,15)<ROUND(p_bond_tail_css,0)),1,0))+s_Rc2/p_realiz_minsa*p_pwin_cen*p_minsa_occ*p_bond_minsa*F14*(1+IF(AND(F$3-c_cen_start>=12,MOD(F$3-c_cen_start,12)<ROUND(p_bond_tail_minsa,0)),1,0)))*F9*F6 | G33: =(s_Rc1/p_realiz*p_pwin_cen*p_bond_css*15/12*G13*(1+IF(AND(G$3-c_cen_start>=15,MOD(G$3-c_cen_start,15)<ROUND(p_bond_tail_css,0)),1,0))+s_Rc2/p_realiz_minsa*p_pwin_cen*p_minsa_occ*p_bond_minsa*G14*(1+IF(AND(G$3-c_cen_start>=12,MOD(G$3-c_cen_start,12)<ROUND(p_bond_tail_minsa,0)),1,0)))*G9*G6 | H33: =(s_Rc1/p_realiz*p_pwin_cen*p_bond_css*15/12*H13*(1+IF(AND(H$3-c_cen_start>=15,MOD(H$3-c_cen_start,15)<ROUND(p_bond_tail_css,0)),1,0))+s_Rc2/p_realiz_minsa*p_pwin_cen*p_minsa_occ*p_bond_minsa*H14*(1+IF(AND(H$3-c_cen_start>=12,MOD(H$3-c_cen_start,12)<ROUND(p_bond_tail_minsa,0)),1,0)))*H9*H6 | I33: =(s_Rc1/p_realiz*p_pwin_cen*p_bond_css*15/12*I13*(1+IF(AND(I$3-c_cen_start>=15,MOD(I$3-c_cen_start,15)<ROUND(p_bond_tail_css,0)),1,0))+s_Rc2/p_realiz_minsa*p_pwin_cen*p_minsa_occ*p_bond_minsa*I14*(1+IF(AND(I$3-c_cen_start>=12,MOD(I$3-c_cen_start,12)<ROUND(p_bond_tail_minsa,0)),1,0)))*I9*I6 | J33: =(s_Rc1/p_realiz*p_pwin_cen*p_bond_css*15/12*J13*(1+IF(AND(J$3-c_cen_start>=15,MOD(J$3-c_cen_start,15)<ROUND(p_bond_tail_css,0)),1,0))+s_Rc2/p_realiz_minsa*p_pwin_cen*p_minsa_occ*p_bond_minsa*J14*(1+IF(AND(J$3-c_cen_start>=12,MOD(J$3-c_cen_start,12)<ROUND(p_bond_tail_minsa,0)),1,0)))*J9*J6 | K33: =(s_Rc1/p_realiz*p_pwin_cen*p_bond_css*15/12*K13*(1+IF(AND(K$3-c_cen_start>=15,MOD(K$3-c_cen_start,15)<ROUND(p_bond_tail_css,0)),1,0))+s_Rc2/p_realiz_minsa*p_pwin_cen*p_minsa_occ*p_bond_minsa*K14*(1+IF(AND(K$3-c_cen_start>=12,MOD(K$3-c_cen_start,12)<ROUND(p_bond_tail_minsa,0)),1,0)))*K9*K6 | ... BK33: =(s_Rc1/p_realiz*p_pwin_cen*p_bond_css*15/12*BK13*(1+IF(AND(BK$3-c_cen_start>=15,MOD(BK$3-c_cen_start,15)<ROUND(p_bond_tail_css,0)),1,0))+s_Rc2/p_realiz_minsa*p_pwin_cen*p_minsa_occ*p_bond_minsa*BK14*(1+IF(AND(BK$3-c_cen_start>=12,MOD(BK$3-c_cen_start,12)<ROUND(p_bond_tail_minsa,0)),1,0)))*BK9*BK6
A34: Fianza de propuesta vigente (LPU) | D34: =p_bid_bond*s_bid*15/12*D13*IF(AND(D$3>=c_cen_start-c_bid_m,MOD(D$3-(c_cen_start-c_bid_m),15)<c_bid_m),1,0)*D6 | E34: =p_bid_bond*s_bid*15/12*E13*IF(AND(E$3>=c_cen_start-c_bid_m,MOD(E$3-(c_cen_start-c_bid_m),15)<c_bid_m),1,0)*E6 | F34: =p_bid_bond*s_bid*15/12*F13*IF(AND(F$3>=c_cen_start-c_bid_m,MOD(F$3-(c_cen_start-c_bid_m),15)<c_bid_m),1,0)*F6 | G34: =p_bid_bond*s_bid*15/12*G13*IF(AND(G$3>=c_cen_start-c_bid_m,MOD(G$3-(c_cen_start-c_bid_m),15)<c_bid_m),1,0)*G6 | H34: =p_bid_bond*s_bid*15/12*H13*IF(AND(H$3>=c_cen_start-c_bid_m,MOD(H$3-(c_cen_start-c_bid_m),15)<c_bid_m),1,0)*H6 | I34: =p_bid_bond*s_bid*15/12*I13*IF(AND(I$3>=c_cen_start-c_bid_m,MOD(I$3-(c_cen_start-c_bid_m),15)<c_bid_m),1,0)*I6 | J34: =p_bid_bond*s_bid*15/12*J13*IF(AND(J$3>=c_cen_start-c_bid_m,MOD(J$3-(c_cen_start-c_bid_m),15)<c_bid_m),1,0)*J6 | K34: =p_bid_bond*s_bid*15/12*K13*IF(AND(K$3>=c_cen_start-c_bid_m,MOD(K$3-(c_cen_start-c_bid_m),15)<c_bid_m),1,0)*K6 | ... BK34: =p_bid_bond*s_bid*15/12*BK13*IF(AND(BK$3>=c_cen_start-c_bid_m,MOD(BK$3-(c_cen_start-c_bid_m),15)<c_bid_m),1,0)*BK6
A35: Colateral inmovilizado | C35: 0 | D35: =(D33+D34)*p_collat | E35: =(E33+E34)*p_collat | F35: =(F33+F34)*p_collat | G35: =(G33+G34)*p_collat | H35: =(H33+H34)*p_collat | I35: =(I33+I34)*p_collat | J35: =(J33+J34)*p_collat | K35: =(K33+K34)*p_collat | ... BK35: =(BK33+BK34)*p_collat
A36: Cambio en colateral | D36: =D35-C35 | E36: =E35-D35 | F36: =F35-E35 | G36: =G35-F35 | H36: =H35-G35 | I36: =I35-H35 | J36: =J35-I35 | K36: =K35-J35 | ... BK36: =BK35-BJ35
A37: Prima de fianzas | D37: =(D33+D34)*p_bond_prem/12 | E37: =(E33+E34)*p_bond_prem/12 | F37: =(F33+F34)*p_bond_prem/12 | G37: =(G33+G34)*p_bond_prem/12 | H37: =(H33+H34)*p_bond_prem/12 | I37: =(I33+I34)*p_bond_prem/12 | J37: =(J33+J34)*p_bond_prem/12 | K37: =(K33+K34)*p_bond_prem/12 | ... BK37: =(BK33+BK34)*p_bond_prem/12
A38: Costo de factoring | D38: =p_fact_share*D17*(1-p_baddebt)*p_fact_cost*c_dso_m | E38: =p_fact_share*E17*(1-p_baddebt)*p_fact_cost*c_dso_m | F38: =p_fact_share*F17*(1-p_baddebt)*p_fact_cost*c_dso_m | G38: =p_fact_share*G17*(1-p_baddebt)*p_fact_cost*c_dso_m | H38: =p_fact_share*H17*(1-p_baddebt)*p_fact_cost*c_dso_m | I38: =p_fact_share*I17*(1-p_baddebt)*p_fact_cost*c_dso_m | J38: =p_fact_share*J17*(1-p_baddebt)*p_fact_cost*c_dso_m | K38: =p_fact_share*K17*(1-p_baddebt)*p_fact_cost*c_dso_m | ... BK38: =p_fact_share*BK17*(1-p_baddebt)*p_fact_cost*c_dso_m
A39: Pérdida de inventario por cierre | D39: =IF(D$3=ROUND(p_stop_det,0)+1,INDEX($D$21:$BK$21,1,ROUND(p_stop_det,0))*(1-p_inv_liq),0) | E39: =IF(E$3=ROUND(p_stop_det,0)+1,INDEX($D$21:$BK$21,1,ROUND(p_stop_det,0))*(1-p_inv_liq),0) | F39: =IF(F$3=ROUND(p_stop_det,0)+1,INDEX($D$21:$BK$21,1,ROUND(p_stop_det,0))*(1-p_inv_liq),0) | G39: =IF(G$3=ROUND(p_stop_det,0)+1,INDEX($D$21:$BK$21,1,ROUND(p_stop_det,0))*(1-p_inv_liq),0) | H39: =IF(H$3=ROUND(p_stop_det,0)+1,INDEX($D$21:$BK$21,1,ROUND(p_stop_det,0))*(1-p_inv_liq),0) | I39: =IF(I$3=ROUND(p_stop_det,0)+1,INDEX($D$21:$BK$21,1,ROUND(p_stop_det,0))*(1-p_inv_liq),0) | J39: =IF(J$3=ROUND(p_stop_det,0)+1,INDEX($D$21:$BK$21,1,ROUND(p_stop_det,0))*(1-p_inv_liq),0) | K39: =IF(K$3=ROUND(p_stop_det,0)+1,INDEX($D$21:$BK$21,1,ROUND(p_stop_det,0))*(1-p_inv_liq),0) | ... BK39: =IF(BK$3=ROUND(p_stop_det,0)+1,INDEX($D$21:$BK$21,1,ROUND(p_stop_det,0))*(1-p_inv_liq),0)
A40: UTILIDAD ANTES DE IMPUESTOS | D40: =D17-D20*(1+p_expiry)-D27-D17*p_baddebt-D38-D28-D29-D30-D31-D32-D37-D39 | E40: =E17-E20*(1+p_expiry)-E27-E17*p_baddebt-E38-E28-E29-E30-E31-E32-E37-E39 | F40: =F17-F20*(1+p_expiry)-F27-F17*p_baddebt-F38-F28-F29-F30-F31-F32-F37-F39 | G40: =G17-G20*(1+p_expiry)-G27-G17*p_baddebt-G38-G28-G29-G30-G31-G32-G37-G39 | H40: =H17-H20*(1+p_expiry)-H27-H17*p_baddebt-H38-H28-H29-H30-H31-H32-H37-H39 | I40: =I17-I20*(1+p_expiry)-I27-I17*p_baddebt-I38-I28-I29-I30-I31-I32-I37-I39 | J40: =J17-J20*(1+p_expiry)-J27-J17*p_baddebt-J38-J28-J29-J30-J31-J32-J37-J39 | K40: =K17-K20*(1+p_expiry)-K27-K17*p_baddebt-K38-K28-K29-K30-K31-K32-K37-K39 | ... BK40: =BK17-BK20*(1+p_expiry)-BK27-BK17*p_baddebt-BK38-BK28-BK29-BK30-BK31-BK32-BK37-BK39
A41: Impuesto sobre la renta pagado | D41: =0 | E41: =0 | F41: =0 | G41: =0 | H41: =0 | I41: =0 | J41: =0 | K41: =0 | ... Q41: =0 | R41: =Anual!$C$14 | S41: =0 | T41: =0 | U41: =Anual!$C$14/3 | V41: =0 | W41: =0 | X41: =Anual!$C$14/3 | Y41: =0 | Z41: =0 | AA41: =Anual!$C$14/3 | AB41: =0 | AC41: =0 | AD41: =Anual!$D$14-Anual!$C$14 | AE41: =0 | AF41: =0 | AG41: =Anual!$D$14/3 | AH41: =0 | AI41: =0 | AJ41: =Anual!$D$14/3 | AK41: =0 | AL41: =0 | AM41: =Anual!$D$14/3 | AN41: =0 | AO41: =0 | AP41: =Anual!$E$14-Anual!$D$14 | AQ41: =0 | AR41: =0 | AS41: =Anual!$E$14/3 | AT41: =0 | AU41: =0 | AV41: =Anual!$E$14/3 | AW41: =0 | AX41: =0 | AY41: =Anual!$E$14/3 | AZ41: =0 | BA41: =0 | BB41: =Anual!$F$14-Anual!$E$14 | BC41: =0 | BD41: =0 | BE41: =Anual!$F$14/3 | BF41: =0 | BG41: =0 | BH41: =Anual!$F$14/3 | BI41: =0 | BJ41: =0 | BK41: =Anual!$F$14/3
A42: Impuesto de aviso de operación pagado | D42: 0 | E42: 0 | F42: 0 | G42: 0 | H42: 0 | I42: 0 | J42: 0 | K42: 0 | L42: 0 | M42: 0 | N42: 0 | O42: 0 | P42: 0 | Q42: 0 | R42: =IF(R$3<=ROUND(p_stop_det,0)+3,MIN(60000,MAX(100,p_aviso*MAX(0,SUM($D$45:$O$45)+SUM(Anual!$C$15:$C$15)-SUM($D$46:$O$46)-SUM($D$47:$O$47)))),0) | S42: 0 | T42: 0 | U42: 0 | V42: 0 | W42: 0 | X42: 0 | Y42: 0 | Z42: 0 | AA42: 0 | AB42: 0 | AC42: 0 | AD42: =IF(AD$3<=ROUND(p_stop_det,0)+3,MIN(60000,MAX(100,p_aviso*MAX(0,SUM($D$45:$AA$45)+SUM(Anual!$C$15:$D$15)-SUM($D$46:$AA$46)-SUM($D$47:$AA$47)))),0) | AE42: 0 | AF42: 0 | AG42: 0 | AH42: 0 | AI42: 0 | AJ42: 0 | AK42: 0 | AL42: 0 | AM42: 0 | AN42: 0 | AO42: 0 | AP42: =IF(AP$3<=ROUND(p_stop_det,0)+3,MIN(60000,MAX(100,p_aviso*MAX(0,SUM($D$45:$AM$45)+SUM(Anual!$C$15:$E$15)-SUM($D$46:$AM$46)-SUM($D$47:$AM$47)))),0) | AQ42: 0 | AR42: 0 | AS42: 0 | AT42: 0 | AU42: 0 | AV42: 0 | AW42: 0 | AX42: 0 | AY42: 0 | AZ42: 0 | BA42: 0 | BB42: =IF(BB$3<=ROUND(p_stop_det,0)+3,MIN(60000,MAX(100,p_aviso*MAX(0,SUM($D$45:$AY$45)+SUM(Anual!$C$15:$F$15)-SUM($D$46:$AY$46)-SUM($D$47:$AY$47)))),0) | BC42: 0 | BD42: 0 | BE42: 0 | BF42: 0 | BG42: 0 | BH42: 0 | BI42: 0 | BJ42: 0 | BK42: 0
A43: Caja antes de aportes | D43: =C49+D26-D25-D27-D28-D29-D30-D31-D32-D36-D37-D41-D42 | E43: =D49+E26-E25-E27-E28-E29-E30-E31-E32-E36-E37-E41-E42 | F43: =E49+F26-F25-F27-F28-F29-F30-F31-F32-F36-F37-F41-F42 | G43: =F49+G26-G25-G27-G28-G29-G30-G31-G32-G36-G37-G41-G42 | H43: =G49+H26-H25-H27-H28-H29-H30-H31-H32-H36-H37-H41-H42 | I43: =H49+I26-I25-I27-I28-I29-I30-I31-I32-I36-I37-I41-I42 | J43: =I49+J26-J25-J27-J28-J29-J30-J31-J32-J36-J37-J41-J42 | K43: =J49+K26-K25-K27-K28-K29-K30-K31-K32-K36-K37-K41-K42 | ... BK43: =BJ49+BK26-BK25-BK27-BK28-BK29-BK30-BK31-BK32-BK36-BK37-BK41-BK42
A44: Caja mínima requerida | D44: =p_mincash_m*D28 | E44: =p_mincash_m*E28 | F44: =p_mincash_m*F28 | G44: =p_mincash_m*G28 | H44: =p_mincash_m*H28 | I44: =p_mincash_m*I28 | J44: =p_mincash_m*J28 | K44: =p_mincash_m*K28 | ... BK44: =p_mincash_m*BK28
A45: APORTE DE CAPITAL | D45: =MAX(0,D44-D43) | E45: =MAX(0,E44-E43) | F45: =MAX(0,F44-F43) | G45: =MAX(0,G44-G43) | H45: =MAX(0,H44-H43) | I45: =MAX(0,I44-I43) | J45: =MAX(0,J44-J43) | K45: =MAX(0,K44-K43) | ... BK45: =MAX(0,BK44-BK43)
A46: DIVIDENDO PAGADO | D46: 0 | E46: 0 | F46: 0 | G46: 0 | H46: 0 | I46: 0 | J46: 0 | K46: 0 | L46: 0 | M46: 0 | N46: 0 | O46: 0 | P46: 0 | Q46: 0 | R46: 0 | S46: 0 | T46: 0 | U46: 0 | V46: 0 | W46: 0 | X46: 0 | Y46: 0 | Z46: 0 | AA46: =p_payout*MAX(0,MIN(AA43+AA45-2*AA44-Anual!$D$14,SUM(Anual!$C$15:$D$15)-SUM($D$46:Z$46))) | AB46: 0 | AC46: 0 | AD46: 0 | AE46: 0 | AF46: 0 | AG46: 0 | AH46: 0 | AI46: 0 | AJ46: 0 | AK46: 0 | AL46: 0 | AM46: =p_payout*MAX(0,MIN(AM43+AM45-2*AM44-Anual!$E$14,SUM(Anual!$C$15:$E$15)-SUM($D$46:AL$46))) | AN46: 0 | AO46: 0 | AP46: 0 | AQ46: 0 | AR46: 0 | AS46: 0 | AT46: 0 | AU46: 0 | AV46: 0 | AW46: 0 | AX46: 0 | AY46: =p_payout*MAX(0,MIN(AY43+AY45-2*AY44-Anual!$F$14,SUM(Anual!$C$15:$F$15)-SUM($D$46:AX$46))) | AZ46: 0 | BA46: 0 | BB46: 0 | BC46: 0 | BD46: 0 | BE46: 0 | BF46: 0 | BG46: 0 | BH46: 0 | BI46: 0 | BJ46: 0 | BK46: 0
A47: Devolución de caja a los socios después de un cierre | D47: =IF(AND(D$3>ROUND(p_stop_det,0)+3,D$3<60),MAX(0,D43+D45-D46),0) | E47: =IF(AND(E$3>ROUND(p_stop_det,0)+3,E$3<60),MAX(0,E43+E45-E46),0) | F47: =IF(AND(F$3>ROUND(p_stop_det,0)+3,F$3<60),MAX(0,F43+F45-F46),0) | G47: =IF(AND(G$3>ROUND(p_stop_det,0)+3,G$3<60),MAX(0,G43+G45-G46),0) | H47: =IF(AND(H$3>ROUND(p_stop_det,0)+3,H$3<60),MAX(0,H43+H45-H46),0) | I47: =IF(AND(I$3>ROUND(p_stop_det,0)+3,I$3<60),MAX(0,I43+I45-I46),0) | J47: =IF(AND(J$3>ROUND(p_stop_det,0)+3,J$3<60),MAX(0,J43+J45-J46),0) | K47: =IF(AND(K$3>ROUND(p_stop_det,0)+3,K$3<60),MAX(0,K43+K45-K46),0) | ... BK47: =IF(AND(BK$3>ROUND(p_stop_det,0)+3,BK$3<60),MAX(0,BK43+BK45-BK46),0)
A48: Impuesto de dividendos sobre lo devuelto por encima de lo aportado | D48: =p_divtax*(MAX(0,SUM($D$47:D47)-SUM($D$45:D45))-MAX(0,SUM($C$47:C47)-SUM($D$45:D45))) | E48: =p_divtax*(MAX(0,SUM($D$47:E47)-SUM($D$45:E45))-MAX(0,SUM($C$47:D47)-SUM($D$45:E45))) | F48: =p_divtax*(MAX(0,SUM($D$47:F47)-SUM($D$45:F45))-MAX(0,SUM($C$47:E47)-SUM($D$45:F45))) | G48: =p_divtax*(MAX(0,SUM($D$47:G47)-SUM($D$45:G45))-MAX(0,SUM($C$47:F47)-SUM($D$45:G45))) | H48: =p_divtax*(MAX(0,SUM($D$47:H47)-SUM($D$45:H45))-MAX(0,SUM($C$47:G47)-SUM($D$45:H45))) | I48: =p_divtax*(MAX(0,SUM($D$47:I47)-SUM($D$45:I45))-MAX(0,SUM($C$47:H47)-SUM($D$45:I45))) | J48: =p_divtax*(MAX(0,SUM($D$47:J47)-SUM($D$45:J45))-MAX(0,SUM($C$47:I47)-SUM($D$45:J45))) | K48: =p_divtax*(MAX(0,SUM($D$47:K47)-SUM($D$45:K45))-MAX(0,SUM($C$47:J47)-SUM($D$45:K45))) | ... BK48: =p_divtax*(MAX(0,SUM($D$47:BK47)-SUM($D$45:BK45))-MAX(0,SUM($C$47:BJ47)-SUM($D$45:BK45)))
A49: CAJA AL CIERRE | C49: 0 | D49: =D43+D45-D46-D47 | E49: =E43+E45-E46-E47 | F49: =F43+F45-F46-F47 | G49: =G43+G45-G46-G47 | H49: =H43+H45-H46-H47 | I49: =I43+I45-I46-I47 | J49: =J43+J45-J46-J47 | K49: =K43+K45-K46-K47 | ... BK49: =BK43+BK45-BK46-BK47
A50: FLUJO DE LOS ACCIONISTAS (sin valor terminal) | C50: =-c_phase0 | D50: =-D45+D46*(1-p_divtax)+D47-D48 | E50: =-E45+E46*(1-p_divtax)+E47-E48 | F50: =-F45+F46*(1-p_divtax)+F47-F48 | G50: =-G45+G46*(1-p_divtax)+G47-G48 | H50: =-H45+H46*(1-p_divtax)+H47-H48 | I50: =-I45+I46*(1-p_divtax)+I47-I48 | J50: =-J45+J46*(1-p_divtax)+J47-J48 | K50: =-K45+K46*(1-p_divtax)+K47-K48 | ... BK50: =-BK45+BK46*(1-p_divtax)+BK47-BK48
A52: La columna del mes 61 solo sirve para mirar el costo del mes siguiente al fijar el inventario del mes 60.

Sheet Anual
B1: Estado de resultados e impuestos (B/.)
B3: Concepto | C3: Año 1 | D3: Año 2 | E3: Año 3 | F3: Año 4 | G3: Año 5 | H3: Total
B4: Ventas | C4: =SUM(Mensual!D17:O17) | D4: =SUM(Mensual!P17:AA17) | E4: =SUM(Mensual!AB17:AM17) | F4: =SUM(Mensual!AN17:AY17) | G4: =SUM(Mensual!AZ17:BK17) | H4: =SUM(C4:G4)
B5: Costo de ventas (incl. mermas) | C5: =-SUM(Mensual!D20:O20)*(1+p_expiry) | D5: =-SUM(Mensual!P20:AA20)*(1+p_expiry) | E5: =-SUM(Mensual!AB20:AM20)*(1+p_expiry) | F5: =-SUM(Mensual!AN20:AY20)*(1+p_expiry) | G5: =-SUM(Mensual!AZ20:BK20)*(1+p_expiry) | H5: =SUM(C5:G5)
B6: Gastos variables, incobrables y factoring | C6: =-(SUM(Mensual!D27:O27)+SUM(Mensual!D17:O17)*p_baddebt+SUM(Mensual!D38:O38)) | D6: =-(SUM(Mensual!P27:AA27)+SUM(Mensual!P17:AA17)*p_baddebt+SUM(Mensual!P38:AA38)) | E6: =-(SUM(Mensual!AB27:AM27)+SUM(Mensual!AB17:AM17)*p_baddebt+SUM(Mensual!AB38:AM38)) | F6: =-(SUM(Mensual!AN27:AY27)+SUM(Mensual!AN17:AY17)*p_baddebt+SUM(Mensual!AN38:AY38)) | G6: =-(SUM(Mensual!AZ27:BK27)+SUM(Mensual!AZ17:BK17)*p_baddebt+SUM(Mensual!AZ38:BK38)) | H6: =SUM(C6:G6)
B7: Costos fijos y cargos anuales | C7: =-(SUM(Mensual!D28:O28)+SUM(Mensual!D32:O32)) | D7: =-(SUM(Mensual!P28:AA28)+SUM(Mensual!P32:AA32)) | E7: =-(SUM(Mensual!AB28:AM28)+SUM(Mensual!AB32:AM32)) | F7: =-(SUM(Mensual!AN28:AY28)+SUM(Mensual!AN32:AY32)) | G7: =-(SUM(Mensual!AZ28:BK28)+SUM(Mensual!AZ32:BK32)) | H7: =SUM(C7:G7)
B8: Arranque y registros sanitarios | C8: =-(SUM(Mensual!D30:O30)+SUM(Mensual!D31:O31)) | D8: =-(SUM(Mensual!P30:AA30)+SUM(Mensual!P31:AA31)) | E8: =-(SUM(Mensual!AB30:AM30)+SUM(Mensual!AB31:AM31)) | F8: =-(SUM(Mensual!AN30:AY30)+SUM(Mensual!AN31:AY31)) | G8: =-(SUM(Mensual!AZ30:BK30)+SUM(Mensual!AZ31:BK31)) | H8: =SUM(C8:G8)
B9: Fianzas, posregistro y pérdidas por cierre | C9: =-(SUM(Mensual!D37:O37)+SUM(Mensual!D29:O29)+SUM(Mensual!D39:O39)) | D9: =-(SUM(Mensual!P37:AA37)+SUM(Mensual!P29:AA29)+SUM(Mensual!P39:AA39)) | E9: =-(SUM(Mensual!AB37:AM37)+SUM(Mensual!AB29:AM29)+SUM(Mensual!AB39:AM39)) | F9: =-(SUM(Mensual!AN37:AY37)+SUM(Mensual!AN29:AY29)+SUM(Mensual!AN39:AY39)) | G9: =-(SUM(Mensual!AZ37:BK37)+SUM(Mensual!AZ29:BK29)+SUM(Mensual!AZ39:BK39)) | H9: =SUM(C9:G9)
B10: Utilidad antes de impuestos | C10: =SUM(Mensual!D40:O40) | D10: =SUM(Mensual!P40:AA40) | E10: =SUM(Mensual!AB40:AM40) | F10: =SUM(Mensual!AN40:AY40) | G10: =SUM(Mensual!AZ40:BK40) | H10: =SUM(C10:G10)
B11: Pérdidas acumuladas deducibles este año (20% de cada pérdida previa) | C11: =0 | D11: =0.2*MAX(0,-C10) | E11: =0.2*MAX(0,-C10)+0.2*MAX(0,-D10) | F11: =0.2*MAX(0,-C10)+0.2*MAX(0,-D10)+0.2*MAX(0,-E10) | G11: =0.2*MAX(0,-C10)+0.2*MAX(0,-D10)+0.2*MAX(0,-E10)+0.2*MAX(0,-F10)
B12: Deducción aplicada (tope 50% de la renta) | C12: =MIN(0.5*MAX(0,C10),C11) | D12: =MIN(0.5*MAX(0,D10),D11) | E12: =MIN(0.5*MAX(0,E10),E11) | F12: =MIN(0.5*MAX(0,F10),F11) | G12: =MIN(0.5*MAX(0,G10),G11)
B13: Renta gravable | C13: =MAX(0,C10)-C12 | D13: =MAX(0,D10)-D12 | E13: =MAX(0,E10)-E12 | F13: =MAX(0,F10)-F12 | G13: =MAX(0,G10)-G12 | H13: =SUM(C13:G13)
B14: Impuesto sobre la renta (o CAIR si ventas > B/.1.5 millones) | C14: =MAX(p_isr*C13,IF(C4>1500000,0.011675*C4,0)) | D14: =MAX(p_isr*D13,IF(D4>1500000,0.011675*D4,0)) | E14: =MAX(p_isr*E13,IF(E4>1500000,0.011675*E4,0)) | F14: =MAX(p_isr*F13,IF(F4>1500000,0.011675*F4,0)) | G14: =MAX(p_isr*G13,IF(G4>1500000,0.011675*G4,0)) | H14: =SUM(C14:G14)
B15: Utilidad neta | C15: =C10-C14 | D15: =D10-D14 | E15: =E10-E14 | F15: =F10-F14 | G15: =G10-G14 | H15: =SUM(C15:G15)
B16: Margen neto | C16: =IF(C4>0,C15/C4,0) | D16: =IF(D4>0,D15/D4,0) | E16: =IF(E4>0,E15/E4,0) | F16: =IF(F4>0,F15/F4,0) | G16: =IF(G4>0,G15/G4,0)
B17: Memo: impuesto de aviso de operación pagado (no se deduce de la renta en el modelo) | C17: =SUM(Mensual!D42:O42) | D17: =SUM(Mensual!P42:AA42) | E17: =SUM(Mensual!AB42:AM42) | F17: =SUM(Mensual!AN42:AY42) | G17: =SUM(Mensual!AZ42:BK42) | H17: =SUM(C17:G17)
B18: Punto de equilibrio (ventas anuales que cubren fijos)
B19: Costos fijos anuales a plena operación | C19: =f_total*12+c_annual+c_n_reg1*p_postreg
B20: Margen bruto promedio del portafolio | C20: =IF(s_rev_exp>0,s_gp_exp/s_rev_exp,0)
B21: Gastos variables (% ventas) | C21: =p_dist+p_penal+p_baddebt+p_expiry*(1-C20)
B22: Ventas de equilibrio (B/./año) | C22: =IF(C20-C21>0,C19/(C20-C21),0)
B23: Ventas esperadas de la primera ola en madurez (B/./año) | C23: =s_rev_exp

Sheet Valoración
B1: Valoración y capital requerido
B2: =CONCATENATE("Escenario activo: ",Supuestos!C3,IF(p_sl=1," | tarifas SignatureLex"," | tarifas de mercado"))
B4: Capital aportado por los socios durante 60 meses | C4: =SUM(Mensual!D45:BK45)
B5: Gasto de fase 0 (antes de constituir, lo pagan los socios) | C5: =c_phase0
B6: Dividendos pagados (antes del 10%) | C6: =SUM(Mensual!D46:BK46)
B7: Caja al mes 60 | C7: =Mensual!BK49
B8: Cuentas por cobrar al mes 60 | C8: =SUMPRODUCT((m_mes>60-c_dso_m)*Mensual!$D$17:$BK$17)*(1-p_baddebt)*(1-p_fact_share)+p_fact_share*Mensual!BK17*(1-p_baddebt)*(1-p_fact_cost*c_dso_m)
B9: Inventario al mes 60 | C9: =Mensual!BK21
B10: Colateral de fianzas al mes 60 | C10: =Mensual!BK35
B11: Cuentas por pagar al proveedor al mes 60 | C11: =SUMPRODUCT((m_mes>60-MAX(0,c_credit_m-c_ship_m))*Mensual!$D$22:$BK$22)*(1-p_adv)
B12: Capital de trabajo neto al mes 60 | C12: =C8+C9+C10-C11
B13: Impuesto sobre la renta (saldo después de las cuotas estimadas) y aviso de operación del año 5 por pagar | C13: =Anual!G14-Anual!F14+IF(60<=ROUND(p_stop_det,0)+3,MIN(60000,MAX(100,p_aviso*MAX(0,C4+SUM(Anual!C15:G15)-C6-SUM(Mensual!D47:BK47)))),0)
B14: Valor terminal conservador (caja + recuperación del capital de trabajo) | C14: =C7+p_recov*C12-C13
B15: Valor terminal como negocio en marcha (caja + múltiplo de la utilidad del año 5) | C15: =C7-C13+p_gc_mult*MAX(0,Anual!G15)
B16: Valor terminal usado en el caso "en marcha" (el mayor) | C16: =MAX(C14,C15)
B17: Valor terminal neto del impuesto de dividendos (conservador) | C17: =C14-p_divtax*MAX(0,C14-MAX(0,C4-SUM(Mensual!D47:BK47)))
B18: Valor terminal neto del impuesto de dividendos (en marcha) | C18: =C16-p_divtax*MAX(0,C16-MAX(0,C4-SUM(Mensual!D47:BK47)))
C20: 0 | D20: 1 | E20: 2 | F20: 3 | G20: 4 | H20: 5 | I20: 6 | J20: 7 | K20: 8 | L20: 9 | M20: 10 | N20: 11 | O20: 12 | P20: 13 | Q20: 14 | R20: 15 | S20: 16 | T20: 17 | U20: 18 | V20: 19 | W20: 20 | X20: 21 | Y20: 22 | Z20: 23 | AA20: 24 | AB20: 25 | AC20: 26 | AD20: 27 | AE20: 28 | AF20: 29 | AG20: 30 | AH20: 31 | AI20: 32 | AJ20: 33 | AK20: 34 | AL20: 35 | AM20: 36 | AN20: 37 | AO20: 38 | AP20: 39 | AQ20: 40 | AR20: 41 | AS20: 42 | AT20: 43 | AU20: 44 | AV20: 45 | AW20: 46 | AX20: 47 | AY20: 48 | AZ20: 49 | BA20: 50 | BB20: 51 | BC20: 52 | BD20: 53 | BE20: 54 | BF20: 55 | BG20: 56 | BH20: 57 | BI20: 58 | BJ20: 59 | BK20: 60
B21: Flujo de los accionistas, conservador (mes 0 a 60, sigue a la derecha) | C21: =Mensual!C50 | D21: =Mensual!D50 | E21: =Mensual!E50 | F21: =Mensual!F50 | G21: =Mensual!G50 | H21: =Mensual!H50 | I21: =Mensual!I50 | J21: =Mensual!J50 | ... BJ21: =Mensual!BJ50 | BK21: =Mensual!BK50+$C$17
B22: Flujo de los accionistas, en marcha | C22: =Mensual!C50 | D22: =Mensual!D50 | E22: =Mensual!E50 | F22: =Mensual!F50 | G22: =Mensual!G50 | H22: =Mensual!H50 | I22: =Mensual!I50 | J22: =Mensual!J50 | ... BJ22: =Mensual!BJ50 | BK22: =Mensual!BK50+$C$18
B24: VPN al 15% anual (conservador) | C24: =SUMPRODUCT($C$21:$BK$21,1/(1+0.15)^($C$20:$BK$20/12))
B25: VPN a la tasa de descuento del escenario (conservador) | C25: =SUMPRODUCT($C$21:$BK$21,1/(1+p_disc)^($C$20:$BK$20/12))
B26: VPN al 15% anual (en marcha) | C26: =SUMPRODUCT($C$22:$BK$22,1/(1+0.15)^($C$20:$BK$20/12))
B27: TIR anual (conservador) | C27: =IFERROR((1+IRR($C$21:$BK$21,0.01))^12-1,IFERROR((1+IRR($C$21:$BK$21,-0.1))^12-1,IFERROR((1+IRR($C$21:$BK$21,-0.19))^12-1,IFERROR((1+IRR($C$21:$BK$21,-0.3))^12-1,"n.d."))))
B28: TIR anual (en marcha) | C28: =IFERROR((1+IRR($C$22:$BK$22,0.01))^12-1,IFERROR((1+IRR($C$22:$BK$22,-0.1))^12-1,IFERROR((1+IRR($C$22:$BK$22,-0.19))^12-1,"n.d.")))
B29: Múltiplo del capital (lo que vuelve / lo que se pone), conservador | C29: =IF(-SUMIF($C$21:$BK$21,"<0")>0,SUMIF($C$21:$BK$21,">0")/-SUMIF($C$21:$BK$21,"<0"),0)
B30: Capital máximo acumulado (pico de necesidad de caja de los socios) | C30: =-MIN(C34:BK34)
B31: Ganancia de Zywie por su margen sobre el precio de fábrica (60 meses) | C31: =SUM(Mensual!D22:BK22)*s_fob_share*p_zy_markup/(1+p_zy_markup)
B33: Flujo acumulado (conservador, sin valor terminal)
B34: Flujo acumulado de los accionistas | C34: =SUM($C$21:C21)-IF(0=60,$C$17,0) | D34: =SUM($C$21:D21)-IF(1=60,$C$17,0) | E34: =SUM($C$21:E21)-IF(2=60,$C$17,0) | F34: =SUM($C$21:F21)-IF(3=60,$C$17,0) | G34: =SUM($C$21:G21)-IF(4=60,$C$17,0) | H34: =SUM($C$21:H21)-IF(5=60,$C$17,0) | I34: =SUM($C$21:I21)-IF(6=60,$C$17,0) | J34: =SUM($C$21:J21)-IF(7=60,$C$17,0) | K34: =SUM($C$21:K21)-IF(8=60,$C$17,0) | L34: =SUM($C$21:L21)-IF(9=60,$C$17,0) | M34: =SUM($C$21:M21)-IF(10=60,$C$17,0) | N34: =SUM($C$21:N21)-IF(11=60,$C$17,0) | O34: =SUM($C$21:O21)-IF(12=60,$C$17,0) | P34: =SUM($C$21:P21)-IF(13=60,$C$17,0) | Q34: =SUM($C$21:Q21)-IF(14=60,$C$17,0) | R34: =SUM($C$21:R21)-IF(15=60,$C$17,0) | S34: =SUM($C$21:S21)-IF(16=60,$C$17,0) | T34: =SUM($C$21:T21)-IF(17=60,$C$17,0) | U34: =SUM($C$21:U21)-IF(18=60,$C$17,0) | V34: =SUM($C$21:V21)-IF(19=60,$C$17,0) | W34: =SUM($C$21:W21)-IF(20=60,$C$17,0) | X34: =SUM($C$21:X21)-IF(21=60,$C$17,0) | Y34: =SUM($C$21:Y21)-IF(22=60,$C$17,0) | Z34: =SUM($C$21:Z21)-IF(23=60,$C$17,0) | AA34: =SUM($C$21:AA21)-IF(24=60,$C$17,0) | AB34: =SUM($C$21:AB21)-IF(25=60,$C$17,0) | AC34: =SUM($C$21:AC21)-IF(26=60,$C$17,0) | AD34: =SUM($C$21:AD21)-IF(27=60,$C$17,0) | AE34: =SUM($C$21:AE21)-IF(28=60,$C$17,0) | AF34: =SUM($C$21:AF21)-IF(29=60,$C$17,0) | AG34: =SUM($C$21:AG21)-IF(30=60,$C$17,0) | AH34: =SUM($C$21:AH21)-IF(31=60,$C$17,0) | AI34: =SUM($C$21:AI21)-IF(32=60,$C$17,0) | AJ34: =SUM($C$21:AJ21)-IF(33=60,$C$17,0) | AK34: =SUM($C$21:AK21)-IF(34=60,$C$17,0) | AL34: =SUM($C$21:AL21)-IF(35=60,$C$17,0) | AM34: =SUM($C$21:AM21)-IF(36=60,$C$17,0) | AN34: =SUM($C$21:AN21)-IF(37=60,$C$17,0) | AO34: =SUM($C$21:AO21)-IF(38=60,$C$17,0) | AP34: =SUM($C$21:AP21)-IF(39=60,$C$17,0) | AQ34: =SUM($C$21:AQ21)-IF(40=60,$C$17,0) | AR34: =SUM($C$21:AR21)-IF(41=60,$C$17,0) | AS34: =SUM($C$21:AS21)-IF(42=60,$C$17,0) | AT34: =SUM($C$21:AT21)-IF(43=60,$C$17,0) | AU34: =SUM($C$21:AU21)-IF(44=60,$C$17,0) | AV34: =SUM($C$21:AV21)-IF(45=60,$C$17,0) | AW34: =SUM($C$21:AW21)-IF(46=60,$C$17,0) | AX34: =SUM($C$21:AX21)-IF(47=60,$C$17,0) | AY34: =SUM($C$21:AY21)-IF(48=60,$C$17,0) | AZ34: =SUM($C$21:AZ21)-IF(49=60,$C$17,0) | BA34: =SUM($C$21:BA21)-IF(50=60,$C$17,0) | BB34: =SUM($C$21:BB21)-IF(51=60,$C$17,0) | BC34: =SUM($C$21:BC21)-IF(52=60,$C$17,0) | BD34: =SUM($C$21:BD21)-IF(53=60,$C$17,0) | BE34: =SUM($C$21:BE21)-IF(54=60,$C$17,0) | BF34: =SUM($C$21:BF21)-IF(55=60,$C$17,0) | BG34: =SUM($C$21:BG21)-IF(56=60,$C$17,0) | BH34: =SUM($C$21:BH21)-IF(57=60,$C$17,0) | BI34: =SUM($C$21:BI21)-IF(58=60,$C$17,0) | BJ34: =SUM($C$21:BJ21)-IF(59=60,$C$17,0) | BK34: =SUM($C$21:BK21)-IF(60=60,$C$17,0)
B36: Vista de un socio panameño (participación y aportes según el trato)
B37: Participación del socio en las utilidades | C37: =(1-p_patel_eq)*p_jaime_frac
B38: Porcentaje del capital que aporta el socio | C38: =(1-p_patel_cash)*p_jaime_frac
B39: Capital total que pondría el socio (incluye su tercio de la fase 0) | C39: =C4*C38+C5*p_jaime_frac
B40: Lo que recibiría el socio (dividendos y valor terminal netos, conservador) | C40: =(C6*(1-p_divtax)+SUM(Mensual!D47:BK47)-SUM(Mensual!D48:BK48)+C17)*C37
B41: Resultado neto del socio en 5 años (sin descontar) | C41: =C40-C39
B44: Reparto del valor económico entre Rutul Patel y el lado panameño (nominal, 60 meses, conservador)
B45: Valor neto para todos los accionistas (lo que vuelve menos lo que se pone) | C45: =SUM($C$21:$BK$21)
B46: Rutul Patel: margen de Zywie + su parte de lo distribuido - su parte del capital | C46: =C31+p_patel_eq*SUMIF(Valoración!$D$21:$BK$21,">0")-p_patel_cash*C4
B47: Lado panameño (3 socios): su parte de lo distribuido - su parte del capital - fase 0 | C47: =(1-p_patel_eq)*SUMIF(Valoración!$D$21:$BK$21,">0")-(1-p_patel_cash)*C4-C5
B48: Porcentaje del valor total que se lleva Rutul Patel | C48: =IF(C46+C47<>0,C46/(C46+C47),0)
B49: Nota: si el valor neto total es negativo, el porcentaje no tiene interpretación útil; mire los montos.

Sheet Escenarios
B1: Resultados por escenario (valores fijos del motor en Python)
B2: Para recalcular en vivo, cambie Supuestos!B3. Estos valores sirven de referencia y de control cruzado.
B4: Indicador | C4: Pesimista | D4: Base | E4: Optimista
B5: Ventas año 1 | C5: 0 | D5: 383.6599 | E5: 6679.0407
B6: Ventas año 2 | C6: 311.40477 | D6: 79893.709 | E6: 512766.73
B7: Ventas año 3 | C7: 6127.532 | D7: 176158.8 | E7: 1002806.8
B8: Ventas año 5 | C8: 6497.1447 | D8: 209152.91 | E8: 1091827
B9: Utilidad neta año 1 | C9: -167924.33 | D9: -95535.947 | E9: -56975.845
B10: Utilidad neta año 3 | C10: -95850.475 | D10: 8147.9311 | E10: 420522.07
B11: Utilidad neta año 5 | C11: -98157.465 | D11: 13727.891 | E11: 459281.22
B12: Capital (aportes más fase 0) | C12: 591968.85 | D12: 392937.99 | E12: 196374.21
B13: Mes del pico de capital | C13: 60 | D13: 45 | E13: 16
B14: VPN al 15% (conservador) | C14: -435375.31 | D14: -198692.76 | E14: 600643.02
B15: VPN al 30% (conservador) | C15: -359335.15 | D15: -207445.25 | E15: 297569.64
B16: TIR (conservador) | C16: -0.94843447 | D16: -0.12316651 | E16: 0.78516029
... B20: Ganancia de Zywie por su margen | C20: 1164.9306 | D20: 34440.873 | E20: 46381.894
B23: Qué pasaría si (cada fila cambia el caso base)
B24: Cambio | C24: Capital | D24: VPN 15% | E24: TIR | F24: Múltiplo | G24: Ventas año 3
B25: Caso base | C25: 392937.99 | D25: -198692.76 | E25: -0.12316651 | F25: 0.63326838 | G25: 176158.8
B26: Crédito de la fábrica de 120 días, sin anticipo | C26: 350007.22 | D26: -183848.58 | E26: -0.13438383 | F26: 0.60299075 | G26: 176158.8
B27: Precio de fábrica a 1.05 veces la referencia | C27: 375529.26 | D27: -176387.91 | E27: -0.088965537 | F27: 0.71818572 | G27: 182698.07
B28: Un socio coordina sin sueldo | C28: 338690.64 | D28: -146256.85 | E28: -0.061004132 | F28: 0.79820334 | G28: 176158.8
B29: Colateral de 50% de la fianza | C29: 351663.21 | D29: -185533.39 | E29: -0.12964084 | F29: 0.60933206 | G29: 176158.8
B30: Colateral de 100% de la fianza | C30: 434212.77 | D30: -211852.12 | E30: -0.11786464 | F30: 0.6526541 | G30: 176158.8
B31: La CSS prorroga la LPU vigente y la siguiente arranca en el mes 14 | C31: 383615.02 | D31: -195869.85 | E31: -0.10033414 | F31: 0.67449132 | G31: 194082.35
B32: El MINSA compra 50% de lo que pidió en la compra conjunta de 2023 | C32: 384851.4 | D32: -172578.12 | E32: -0.074873298 | F32: 0.75862011 | G32: 198288.03
B33: Más 6 productos de sistema nervioso (fabricante verificado) | C33: 391025.68 | D33: -147736.21 | E33: -0.014873808 | F33: 0.94504153 | G33: 247968.61
B34: La fábrica paga los registros, da 180 días de crédito y precio 1.05 | C34: 254121.96 | D34: -99076.587 | E34: -0.042493243 | F34: 0.8594745 | G34: 182698.07
B35: Lo anterior y un socio coordina sin sueldo | C35: 207119.28 | D35: -54231.91 | E35: 0.034635502 | F35: 1.1291794 | G35: 182698.07
B36: Lo anterior más sistema nervioso | C36: 201666.53 | D36: 4663.2684 | E36: 0.15840532 | F36: 1.7209203 | G36: 254292.94
... B38: Solo los 4 productos que pagan su registro | C38: 346807.68 | D38: -157705.84 | E38: -0.10647718 | F38: 0.69136247 | G38: 133525.47

Sheet Simulación
B1: Simulación de Monte Carlo: 20,000 escenarios por estructura (mismas semillas)
B2: Cada escenario sortea los supuestos (triangular pesimista-base-optimista), los registros aprobados, cada renglón centralizado, fallas de planta o de suministro y las compuertas de decisión.
B4: Estructura | C4: Se detiene en la fase 0 | D4: Cierra en la compuerta operativa | E4: Falla de planta o suministro | F4: Prob. de perder dinero | G4: Prob. de perder más que la fase 0 | H4: VPN 15% promedio | I4: Múltiplo mediano | J4: Capital mediano* | K4: Capital p80*
B5: A. Propuesta de Rutul Patel tal cual | C5: 0 | D5: 0 | E5: 0.28735 | F5: 0.98995 | G5: 0.98915 | H5: -241526.76 | I5: 0.34408031 | J5: 403969.91 | K5: 512914.6 | L5: 580249.2
B6: B. Por etapas, mismos términos | C6: 0.20285 | D6: 0.3379 | E6: 0.10465 | F6: 0.99205 | G6: 0.7883 | H6: -161936.82 | I6: 0.1746794 | J6: 277612.27 | K6: 472130.27 | L6: 549283.7
B7: C. Por etapas con términos negociados | C7: 0.11925 | D7: 0.30765 | E7: 0.12405 | F7: 0.97695 | G7: 0.8555 | H7: -173847.88 | I7: 0.23056432 | J7: 333236.18 | K7: 465974.96 | L7: 529575.19
B8: D. Por etapas; la fábrica paga registros y da crédito | C8: 0.11925 | D8: 0.30695 | E8: 0.12425 | F8: 0.93165 | G8: 0.8075 | H8: -122193.24 | I8: 0.27331559 | J8: 252401.9 | K8: 371373.94 | L8: 427004.7
B9: E. Registros más distribuidor establecido | C9: 0.2022 | D9: 0 | E9: 0 | F9: 0.98385 | G9: 0.77865 | H9: -70133.134 | I9: 0.16689851 | J9: 117232.53 | K9: 131448.5 | L9: 139300.69
B10: D más productos de sistema nervioso (si se verifica su fabricante) | C10: 0.11925 | D10: 0.10785 | E10: 0.15245 | F10: 0.6507 | G10: 0.52065 | H10: -91177.338 | I10: 0.78434741 | J10: 276770.34 | K10: 357822.62 | L10: 404224.77
B11: D con un socio como coordinador sin sueldo | C11: 0.11925 | D11: 0.30695 | E11: 0.12425 | F11: 0.8207 | G11: 0.69235 | H11: -88105.313 | I11: 0.35053488 | J11: 200522.71 | K11: 309097.27 | L11: 360578.6
B12: D más sistema nervioso y coordinador sin sueldo | C12: 0.11925 | D12: 0.10785 | E12: 0.15245 | F12: 0.4837 | G12: 0.3548 | H12: -54632.981 | I12: 1.0309684 | J12: 227974.7 | K12: 305022.87 | L12: 349159.36
B13: D con colateral de 100% de la fianza | C13: 0.11925 | D13: 0.30695 | E13: 0.12425 | F13: 0.94335 | G13: 0.8192 | H13: -134244.31 | I13: 0.34049088 | J13: 304425.99 | K13: 447792.33 | L13: 513132.99
B14: D con prueba de precio estricta en la fase 0 (1.1 veces la referencia) | C14: 0.52175 | D14: 0.15865 | E14: 0.06645 | F14: 0.9561 | G14: 0.43115 | H14: -67456.734 | I14: 0 | J14: 260841.87 | K14: 372063.11 | L14: 426928.05
B15: * Máximo acumulado que aportan los socios (aportes más fase 0, sin valor terminal), en los escenarios que pasan la fase 0.
B17: Lo que arriesga un socio panameño (un sexto del capital y de las utilidades más un tercio de la fase 0; un tercio en la estructura E)
B18: Estructura | C18: Capital mediano si sigue | D18: Capital p90 si sigue | E18: Resultado neto promedio | F18: Prob. de perder | G18: Resultado neto p90
B19: A. Propuesta de Rutul Patel tal cual | C19: 68018.422 | D19: 97363.873 | E19: -40438.789 | F19: 0.9908 | G19: -21429.058
B20: B. Por etapas, mismos términos | C20: 47008.728 | D20: 92296.028 | E20: -26380.459 | F20: 0.99275 | G20: -1333.5565
B21: C. Por etapas con términos negociados | C21: 56269.836 | D21: 88978.274 | E21: -27045.893 | F21: 0.97865 | G21: -1545.0975
B22: D. Por etapas; la fábrica paga registros y da crédito | C22: 42752.981 | D22: 71900.899 | E22: -18183.613 | F22: 0.936 | G22: -1123.7431
B23: E. Registros más distribuidor establecido | C23: 39077.511 | D23: 46433.565 | E23: -23242.404 | F23: 0.98385 | G23: -1223.6028
B24: D más productos de sistema nervioso (si se verifica su fabricante) | C24: 46840.954 | D24: 68090.779 | E24: -5844.5293 | F24: 0.6625 | G24: 17968.785
B25: D con un socio como coordinador sin sueldo | C25: 34118.04 | D25: 60776.688 | E25: -10478.329 | F25: 0.8301 | G25: 5941.6962
B26: D más sistema nervioso y coordinador sin sueldo | C26: 38713.892 | D26: 58891.03 | E26: 2420.5843 | F26: 0.4926 | G26: 27957.536
B27: D con colateral de 100% de la fianza | C27: 51469.207 | D27: 86207.703 | E27: -19361.121 | F27: 0.947 | G27: -1212.9263
B28: D con prueba de precio estricta en la fase 0 (1.1 veces la referencia) | C28: 44155.244 | D28: 71879.402 | E28: -10101.267 | F28: 0.95885 | G28: -937.5842
B29: D con Rutul Patel aportando 70% del efectivo | C29: 26199.275 | D29: 43752.014 | E29: -2909.6869 | F29: 0.7129 | G29: 17536.872
B30: D con Rutul Patel aportando 80% del efectivo | C30: 17889.13 | D30: 29653.168 | E30: 4727.2764 | F30: 0.60555 | G30: 29399.02
B32: Supuestos de riesgo de la simulación
B33: Planta con problemas de BPM: 15% de probabilidad; la fase 0 lo detecta 80% de las veces; si no, falla de calidad entre los meses 12 y 36, se ejecuta la fianza y se pierde el inventario.
B34: Ruptura del suministro por otras causas: 4% anual desde el mes 7, con ejecución de fianzas.
B35: Fase 0: se descarta el trato si se detecta el problema de planta o si el precio de la fábrica supera 1.6 veces la referencia (1.1 en la variante estricta).
B36: Compuerta operativa: 9 meses después de la primera venta, si las ventas anualizadas (más los contratos centralizados por arrancar) no llegan a B/.90,000, se cierra y no se hace la segunda ola.
B37: Correlaciones: participación descentralizada y probabilidad de ganar (0.6); mercado débil y mayor caída de precios (0.4); factor común de costos fijos (0.5).

Sheet Sensibilidad
B1: Sensibilidad del VPN al 15% y del capital (un supuesto a la vez, el resto en la base)
B2: VPN base: B/.-198,693. Capital base: B/.392,938.
B4: Supuesto | C4: Valor pesimista | D4: Valor optimista | E4: VPN pesimista | F4: VPN optimista | G4: Rango del VPN | H4: Capital pesimista | I4: Capital optimista
B5: Costos fijos mensuales con cargas e ITBMS (bloque) | C5: 7824.5 | D5: 2986 | E5: -328447.41 | F5: -138267.78 | G5: =F5-E5 | H5: 546099.53 | I5: 329838.4
B6: Índice del precio de la fábrica frente a la referencia FOB | C6: 1.8 | D6: 1 | E6: -223892.33 | F6: -169432.54 | G6: =F6-E6 | H6: 368864.96 | I6: 372190.81
B7: Caída anual de precios a partir del año 2 | C7: 0.06 | D7: 0 | E7: -224421.42 | F7: -172355.48 | G7: =F7-E7 | H7: 409187.27 | I7: 380389.99
B8: Participación madura en compras descentralizadas (valor) | C8: 0.1 | D8: 0.32 | E8: -226885.8 | F8: -176193.48 | G8: =F8-E8 | H8: 408864.06 | I8: 383897.77
B9: Colateral en efectivo que pide la aseguradora o el banco (% de la fianza) | C9: 1 | D9: 0.25 | E9: -211852.12 | F9: -172572.57 | G9: =F9-E9 | H9: 434212.77 | I9: 312118.01
B10: Parte de la cantidad de la compra conjunta de 2023 que se toma como demanda del MINSA | C10: 0 | D10: 0.5 | E10: -210168.09 | F10: -172578.12 | G10: =F10-E10 | H10: 398786.3 | I10: 384851.4
B11: Probabilidad de ganar un renglón centralizado en el que se oferta | C11: 0.15 | D11: 0.45 | E11: -216865.71 | F11: -186584.58 | G11: =F11-E11 | H11: 366102.87 | I11: 456993.22
B12: Productos de la segunda ola (sin equivalencia terapéutica, fabricación verificada) | C12: 0 | D12: 12 | E12: -185654.23 | F12: -212540.79 | G12: =F12-E12 | H12: 319237.54 | I12: 467461.2
B13: Cantidad comprada frente a la máxima del contrato de la LPU | C13: 0.55 | D13: 0.9 | E13: -211575.3 | F13: -189096.44 | G13: =F13-E13 | H13: 391110.28 | I13: 394437.42
B14: Días de cobro: entrega hasta cobro | C14: 240 | D14: 105 | E14: -214445.95 | F14: -193003.34 | G14: =F14-E14 | H14: 447565.72 | I14: 374513.1
B15: Precio de oferta descentralizado frente al precio ponderado actual | C15: 0.8 | D15: 0.95 | E15: -210990.94 | F15: -191914.62 | G15: =F15-E15 | H15: 403653.65 | I15: 388683.62
B16: Factor de mercado (demanda futura frente a 2025-2026) | C16: 0.75 | D16: 1 | E16: -210044.69 | F16: -191303.14 | G16: =F16-E16 | H16: 376847.74 | I16: 404078.54
... B27: Mes en que podría arrancar el primer contrato centralizado (calendario de la LPU) | C27: 27 | D27: 14 | E27: -198702.49 | F27: -195869.85 | G27: =F27-E27 | H27: 408914.14 | I27: 383615.02

Sheet Vida útil
B1: Presupuesto de vida útil (regla de 18 meses al entregar)
B3: Vida útil aprobada del producto (meses) | C3: 24
B4: Vida útil mínima exigida al entregar (pliego de la LPU) | C4: 18
B5: Liberación en fábrica y despacho (meses) | C5: 1
B6: Tránsito y aduana (meses) | C6: =p_ship_m
B7: Pedido a entrega en hospital (meses) | C7: 0.25
B8: Tiempo máximo que puede pasar en bodega (meses) | C8: =C3-C4-C5-C6-C7
B10: Con 24 meses de vida útil caben unos 2.75 meses en bodega: reposición mensual y poco inventario. Con 36 meses caben casi 15.

Sheet Fuentes
B1: Fuentes principales
B3: Fuente | C3: Enlace
B4: PanamaCompra: cuadro de propuestas de la LPU 01-2026 de la CSS | C4: https://apisv3.panamacompra.gob.pa/documentos-actos-publico/cuadroPropuesta/12/procesoVistaCuadroPropuesta/712894
B5: Ley 419 de 2024 (medicamentos y compras públicas de medicamentos) | C5: https://dnfd.minsa.gob.pa/sites/default/files/2025-08/Ley%20419%20de%201%20de%20febrero%20de%202024.pdf
B6: Ley 462 de 2025 (reforma de la CSS y de la Ley 419) | C6: https://www.css.gob.pa/wp-content/uploads/2025/03/Ley-462-de-2025.pdf
B7: Ley 316 de 2022 (conflicto de intereses) | C7: https://s3-legispan.asamblea.gob.pa/legispan/NORMAS/2020/2022/LEY/Administrador%20Legispan_29602-A_2022_8_18_ASAMBLEA%20NACIONAL_316.pdf
B8: Decreto Ejecutivo 27 de 2024 (tasas, licencias, registros, compras) | C8: https://www.minsa.gob.pa/sites/default/files/general/decreto_ejecutivo_27_de_10_de_mayo_de_2024.pdf
B9: Resolución 985 de 2025 (principios activos con equivalencia terapéutica) | C9: https://www.minsa.gob.pa/sites/default/files/general/resolucion_985_go30317_08072025.pdf
B10: PMBI: compras concluidas 2022-2025 (precios domésticos indios) | C10: https://www.pmbi.co.in/Data/Awarded_Tender/Procurement%20Dept%202022_2025_13022026.pdf
B11: TNMSC: licitación e-018/2024 (precios domésticos indios) | C11: https://tnmsc.tn.gov.in/linkfiles/news_events/N2502472.pdf
B12: Assam Medical Services Corporation: último precio de compra (2025) | C12: https://amscl.assam.gov.in/sites/default/files/public_utility/Rates%20LPP-Drugs.pdf
B13: RBI: tasa de referencia INR/USD | C13: https://www.rbi.org.in/
B14: AJOT: tarifas FAK de CMA CGM del subcontinente indio a Latinoamérica (jun-2026) | C14: https://www.ajot.com/news/cma-cgm-fak-rates-from-the-indian-subcontinent-to-latin-america-and-north-europe-the-mediterranean-north-africa
... B17: Registro completo de verificaciones (474 afirmaciones con fuente y fecha) | C17: research/verificacion_2026-10-09/registro_verificaciones.csv (repositorio)
